Workbook

Sheet 6月日经营数据
A1: 2025年南京项目处理经营情况（6月）
A3: 科目 | C3: 45809 | D3: =C3+1 -> 45810 | E3: =D3+1 -> 45811 | F3: =E3+1 -> 45812 | G3: =F3+1 -> 45813 | H3: =G3+1 -> 45814 | I3: =H3+1 -> 45815 | J3: =I3+1 -> 45816 | K3: =J3+1 -> 45817 | ... AG3: =AF3+1 -> 45839 | AH3: 月度合计
C4: 进口处理 | D4: 进口处理 | E4: 进口处理 | F4: 进口处理 | G4: 进口处理 | H4: 进口处理 | I4: 进口处理 | J4: 进口处理 | K4: 进口处理 | L4: 进口处理 | M4: 进口处理 | N4: 进口处理 | O4: 进口处理 | P4: 进口处理 | Q4: 进口处理 | R4: 进口处理 | S4: 进口处理 | T4: 进口处理 | U4: 进口处理 | V4: 进口处理 | W4: 进口处理 | X4: 进口处理 | Y4: 进口处理 | Z4: 进口处理 | AA4: 进口处理 | AB4: 进口处理 | AC4: 进口处理 | AD4: 进口处理 | AE4: 进口处理 | AF4: 进口处理 | AG4: 进口处理 | AH4: 进口处理
A5: 1 | B5: 散件处理量 | C5: =SUMIFS('6月处理量'!$F:$F,'6月处理量'!$A:$A,C3) -> 626140 | D5: =SUMIFS('6月处理量'!$F:$F,'6月处理量'!$A:$A,D3) -> 612040 | E5: =SUMIFS('6月处理量'!$F:$F,'6月处理量'!$A:$A,E3) -> 700265 | F5: =SUMIFS('6月处理量'!$F:$F,'6月处理量'!$A:$A,F3) -> 743201 | G5: =SUMIFS('6月处理量'!$F:$F,'6月处理量'!$A:$A,G3) -> 790629 | H5: =SUMIFS('6月处理量'!$F:$F,'6月处理量'!$A:$A,H3) -> 770752 | I5: =SUMIFS('6月处理量'!$F:$F,'6月处理量'!$A:$A,I3) -> 758273 | J5: =SUMIFS('6月处理量'!$F:$F,'6月处理量'!$A:$A,J3) -> 749111 | ... AG5: =SUMIFS('6月处理量'!$F:$F,'6月处理量'!$A:$A,AG3) -> 0 | AH5: =SUM(C5:AG5) -> 22173981
A6: 2 | B6: 散件处理单价 | C6: 0.1667 | D6: 0.1667 | E6: 0.1667 | F6: 0.1667 | G6: 0.1667 | H6: 0.1667 | I6: 0.1667 | J6: 0.1667 | K6: 0.1667 | L6: 0.1667 | M6: 0.1667 | N6: 0.1667 | O6: 0.1667 | P6: 0.1667 | Q6: 0.1667 | R6: 0.1667 | S6: 0.1667 | T6: 0.1667 | U6: 0.1667 | V6: 0.1667 | W6: 0.1667 | X6: 0.1667 | Y6: 0.1667 | Z6: 0.1667 | AA6: 0.1667 | AB6: 0.1667 | AC6: 0.1667 | AD6: 0.1667 | AE6: 0.1667 | AF6: 0.1667 | AH6: 0.1667
A7: 3 | B7: 散件处理收入 | C7: 104377.54 | D7: 102027.07 | E7: 116734.18 | F7: 123891.61 | G7: 131797.85 | H7: 128484.36 | I7: 126404.11 | J7: 124876.8 | K7: 118175.8 | L7: 125769.65 | M7: 128137.29 | N7: 126079.71 | O7: 132056.24 | P7: 126895.37 | Q7: 120701.97 | R7: 124206.34 | S7: 125173.03 | T7: 126261.08 | U7: 133446.52 | V7: 131387.61 | W7: 135726.47 | X7: 131644.32 | Y7: 123039.94 | Z7: 119158.16 | AA7: 123127.95 | AB7: 116612.98 | AC7: 118228.64 | AD7: 116579.98 | AE7: 119867.14 | AF7: 115532.94 | AH7: =SUM(C7:AG7) -> 3696402.6
A8: 4 | B8: 考核扣款 | C8: 3000 | D8: 3000 | E8: 3000 | F8: 3000 | G8: 3000 | H8: 3000 | I8: 3000 | J8: 3000 | K8: 3000 | L8: 3000 | M8: 3000 | N8: 3000 | O8: 3000 | P8: 3000 | Q8: 3000 | R8: 3000 | S8: 3000 | T8: 3000 | U8: 3000 | V8: 3000 | W8: 3000 | X8: 3000 | Y8: 3000 | Z8: 3000 | AA8: 3000 | AB8: 3000 | AC8: 3000 | AD8: 3000 | AE8: 3000 | AF8: 3000 | AH8: =SUM(C8:AG8) -> 90000
A9: 5 | B9: 补贴费用 | AH9: =SUM(C9:AG9) -> 0
A10: 6 | B10: 开票金额 | C10: 101377.54 | D10: 99027.07 | E10: 113734.18 | F10: 120891.61 | G10: 128797.85 | H10: 125484.36 | I10: 123404.11 | J10: 121876.8 | K10: 115175.8 | L10: 122769.65 | M10: 125137.29 | N10: 123079.71 | O10: 129056.24 | P10: 123895.37 | Q10: 117701.97 | R10: 121206.34 | S10: 122173.03 | T10: 123261.08 | U10: 130446.52 | V10: 128387.61 | W10: 132726.47 | X10: 128644.32 | Y10: 120039.94 | Z10: 116158.16 | AA10: 120127.95 | AB10: 113612.98 | AC10: 115228.64 | AD10: 113579.98 | AE10: 116867.14 | AF10: 112532.94 | AH10: =SUM(C10:AG10) -> 3606402.6
A11: 一、主营业务收入总计 | C11: 95639.19 | D11: 93421.76 | E11: 107296.4 | F11: 114048.69 | G11: 121507.41 | H11: 118381.47 | I11: 116418.97 | J11: 114978.11 | K11: 108656.42 | L11: 115820.42 | M11: 118054.05 | N11: 116112.93 | O11: 121751.17 | P11: 116882.42 | Q11: 111039.59 | R11: 114345.6 | S11: 115257.58 | T11: 116284.04 | U11: 123062.75 | V11: 121120.39 | W11: 125213.65 | X11: 121362.57 | Y11: 113245.23 | Z11: 109583.17 | AA11: 113328.25 | AB11: 107182.06 | AC11: 108706.26 | AD11: 107150.92 | AE11: 110252.02 | AF11: 106163.15 | AH11: =SUM(C11:AG11) -> 3402266.6
A12: 1 | B12: 管理人员数量 | C12: 20 | D12: 19 | E12: 22 | F12: 21 | G12: 22 | H12: 22 | I12: 21 | J12: 18 | K12: 22 | L12: 23 | M12: 22 | N12: 21 | O12: 20 | P12: 17 | Q12: 18 | R12: 19 | S12: 20 | T12: 22 | U12: 22 | V12: 22 | W12: 22 | X12: 17 | Y12: 20 | Z12: 20 | AA12: 19 | AB12: 19 | AC12: 23 | AD12: 20 | AE12: 22 | AF12: 22 | AH12: =SUM(C12:AG12) -> 617
A13: 2 | B13: 自有员工数量 | C13: 291 | D13: 299 | E13: 293 | F13: 302 | G13: 310 | H13: 297 | I13: 302 | J13: 309 | K13: 295 | L13: 299 | M13: 302 | N13: 301 | O13: 316 | P13: 315 | Q13: 312 | R13: 307 | S13: 312 | T13: 309 | U13: 319 | V13: 311 | W13: 309 | X13: 318 | Y13: 307 | Z13: 320 | AA13: 316 | AB13: 317 | AC13: 314 | AD13: 318 | AE13: 324 | AF13: 301 | AH13: =SUM(C13:AG13) -> 9245
A14: 3 | B14: 劳务人员数量 | C14: 58 | D14: 49 | E14: 49 | F14: 50 | G14: 49 | H14: 58 | I14: 56 | J14: 48 | K14: 48 | L14: 47 | M14: 46 | N14: 53 | O14: 48 | P14: 46 | Q14: 46 | R14: 45 | S14: 45 | T14: 48 | U14: 46 | V14: 50 | W14: 47 | X14: 50 | Y14: 50 | Z14: 49 | AA14: 46 | AB14: 44 | AC14: 49 | AD14: 51 | AE14: 40 | AF14: 52 | AH14: =SUM(C14:AG14) -> 1463
A15: 4 | B15: 总人数 | C15: 369 | D15: 367 | E15: 364 | F15: 373 | G15: 381 | H15: 377 | I15: 379 | J15: 375 | K15: 365 | L15: 369 | M15: 370 | N15: 375 | O15: 384 | P15: 378 | Q15: 376 | R15: 371 | S15: 377 | T15: 379 | U15: 387 | V15: 383 | W15: 378 | X15: 385 | Y15: 377 | Z15: 389 | AA15: 381 | AB15: 380 | AC15: 386 | AD15: 389 | AE15: 386 | AF15: 375 | AH15: =SUM(C15:AG15) -> 11325
A16: 5 | B16: 总工时 | C16: 3960 | D16: 3912 | E16: 3872 | F16: 4000.5 | G16: 4087.5 | H16: 4042 | I16: 4066.5 | J16: 4046.5 | K16: 3897 | L16: 3926 | M16: 3962 | N16: 4023.5 | O16: 4124.5 | P16: 4100.5 | Q16: 4059.5 | R16: 3997.5 | S16: 4072.5 | T16: 4067 | U16: 4151 | V16: 4165 | W16: 4104.5 | X16: 4212.5 | Y16: 4105 | Z16: 4197.5 | AA16: 4109 | AB16: 4110 | AC16: 4120.5 | AD16: 4251.5 | AE16: 4148.5 | AF16: 4008.5 | AH16: =SUM(C16:AG16) -> 121900.5
A17: 人均效能 | C17: 1696.8564 | D17: 1667.6839 | E17: 1923.8049 | F17: 1992.496 | G17: 2075.1417 | H17: 2044.435 | I17: 2000.7203 | J17: 1997.6293 | K17: 1942.2274 | L17: 2044.626 | M17: 2077.4865 | N17: 2016.872 | O17: 2062.9661 | P17: 2013.8095 | Q17: 1925.7101 | R17: 2008.3261 | S17: 1991.7454 | T17: 1998.4565 | U17: 2068.5245 | V17: 2057.8799 | W17: 2153.9577 | X17: 2051.1896 | Y17: 1957.8037 | Z17: 1837.5476 | AA17: 1938.6352 | AB17: 1840.8895 | AC17: 1837.3834 | AD17: 1797.7892 | AE17: 1862.8472 | AF17: 1848.1573 | AH17: =AH5/AH15 -> 1957.9674
A18: 人均小时效能 | C18: 158.11616 | D18: 156.45194 | E18: 180.85356 | F18: 185.77703 | G18: 193.42606 | H18: 190.6858 | I18: 186.46822 | J18: 185.12566 | K18: 181.9125 | L18: 192.17193 | M18: 194.0106 | N18: 187.97738 | O18: 192.06667 | P18: 185.64078 | Q18: 178.36359 | R18: 186.38874 | S18: 184.38011 | T18: 186.23433 | U18: 192.84967 | V18: 189.23601 | W18: 198.36667 | X18: 187.46777 | Y18: 179.80317 | Z18: 170.29327 | AA18: 179.75663 | AB18: 170.20389 | AC18: 172.12232 | AD18: 164.49253 | AE18: 173.32988 | AF18: 172.89734 | AH18: =AH5/AH16 -> 181.9023
A19: 1 | B19: 自有员工工资 | C19: 60248.65 | D19: 61254 | E19: 60570.8 | F19: 62686.4 | G19: 64468.95 | H19: 61740.9 | I19: 62593.2 | J19: 63935.65 | K19: 61121.2 | L19: 61811.85 | M19: 62784.15 | N19: 62371.95 | O19: 65352.05 | P19: 65427 | Q19: 64642.45 | R19: 63669 | S19: 64907 | T19: 64421.45 | U19: 66377.45 | V19: 65733.75 | W19: 65175.1 | X19: 66610.45 | Y19: 64661.2 | Z19: 66581.6 | AA19: 65567.8 | AB19: 65999.55 | AC19: 65179.6 | AD19: 67151.85 | AE19: 67601.45 | AF19: 62408.05 | AH19: =SUM(C19:AG19) -> 1923054.5
A20: 2 | B20: 员工宿舍费 | C20: 1300 | D20: 1300 | E20: 1300 | F20: 1300 | G20: 1300 | H20: 1300 | I20: 1300 | J20: 1300 | K20: 1300 | L20: 1300 | M20: 1300 | N20: 1300 | O20: 1300 | P20: 1300 | Q20: 1300 | R20: 1300 | S20: 1300 | T20: 1300 | U20: 1300 | V20: 1300 | W20: 1300 | X20: 1300 | Y20: 1300 | Z20: 1300 | AA20: 1300 | AB20: 1300 | AC20: 1300 | AD20: 1300 | AE20: 1300 | AF20: 1300 | AH20: =SUM(C20:AG20) -> 39000
A21: 3 | B21: 意外险 | C21: 282.92 | D21: 290.69 | E21: 284.86 | F21: 293.61 | G21: 301.39 | H21: 288.75 | I21: 293.61 | J21: 300.42 | K21: 286.81 | L21: 290.69 | M21: 293.61 | N21: 292.64 | O21: 307.22 | P21: 306.25 | Q21: 303.33 | R21: 298.47 | S21: 303.33 | T21: 300.42 | U21: 310.14 | V21: 302.36 | W21: 300.42 | X21: 309.17 | Y21: 298.47 | Z21: 311.11 | AA21: 307.22 | AB21: 308.19 | AC21: 305.28 | AD21: 309.17 | AE21: 315 | AF21: 292.64 | AH21: =SUM(C21:AG21) -> 8988.19
A22: 4 | B22: 雇主险 | C22: 331.42 | D22: 340.53 | E22: 333.69 | F22: 343.94 | G22: 353.06 | H22: 338.25 | I22: 343.94 | J22: 351.92 | K22: 335.97 | L22: 340.53 | M22: 343.94 | N22: 342.81 | O22: 359.89 | P22: 358.75 | Q22: 355.33 | R22: 349.64 | S22: 355.33 | T22: 351.92 | U22: 363.31 | V22: 354.19 | W22: 351.92 | X22: 362.17 | Y22: 349.64 | Z22: 364.44 | AA22: 359.89 | AB22: 361.03 | AC22: 357.61 | AD22: 362.17 | AE22: 369 | AF22: 342.81 | AH22: =SUM(C22:AG22) -> 10529.04
A23: 5 | B23: 员工餐费 | C23: 2488 | D23: 2544 | E23: 2520 | F23: 2584 | G23: 2656 | H23: 2552 | I23: 2584 | J23: 2616 | K23: 2536 | L23: 2576 | M23: 2592 | N23: 2576 | O23: 2688 | P23: 2656 | Q23: 2640 | R23: 2608 | S23: 2656 | T23: 2648 | U23: 2728 | V23: 2664 | W23: 2648 | X23: 2680 | Y23: 2616 | Z23: 2720 | AA23: 2680 | AB23: 2688 | AC23: 2696 | AD23: 2704 | AE23: 2768 | AF23: 2584 | AH23: =SUM(C23:AG23) -> 78896
A24: 6 | B24: 高温福利费用 | F24: 4500 | AH24: =SUM(C24:AG24) -> 4500
A25: 7 | B25: 劳务人员工资 | C25: 15295 | D25: 12960.5 | E25: 12960.5 | F25: 13225 | G25: 12960.5 | H25: 15341 | I25: 14812 | J25: 12696 | K25: 12696 | L25: 12431.5 | M25: 12167 | N25: 14018.5 | O25: 12696 | P25: 12167 | Q25: 12167 | R25: 11902.5 | S25: 12167 | T25: 12696 | U25: 12167 | V25: 13225 | W25: 12431.5 | X25: 13225 | Y25: 13225 | Z25: 12880 | AA25: 12167 | AB25: 11638 | AC25: 12960.5 | AD25: 13489.5 | AE25: 10580 | AF25: 13754 | AH25: =SUM(C25:AG25) -> 387101.5
A26: 8 | B26: 物料采购 | C26: 1560 | D26: 1560 | E26: 1560 | F26: 1560 | G26: 1560 | H26: 1560 | I26: 1560 | J26: 1560 | K26: 1560 | L26: 1560 | M26: 1489.28 | AH26: =SUM(C26:AG26) -> 17089.28
A27: 9 | B27: 工单赔付 | C27: 3333.33 | D27: 3333.33 | E27: 3333.33 | F27: 3333.33 | G27: 3333.33 | H27: 3333.33 | I27: 3333.33 | J27: 3333.33 | K27: 3333.33 | L27: 3333.33 | M27: 3333.33 | N27: 3333.33 | O27: 3333.33 | P27: 3333.33 | Q27: 3333.33 | R27: 3333.33 | S27: 3333.33 | T27: 3333.33 | U27: 3333.33 | V27: 3333.33 | W27: 3333.33 | X27: 3333.33 | Y27: 3333.33 | Z27: 3333.33 | AA27: 3333.33 | AB27: 3333.33 | AC27: 3333.33 | AD27: 3333.33 | AE27: 3333.33 | AF27: 3333.33 | AH27: =SUM(C27:AG27) -> 99999.9
A28: 10 | B28: 设备成本摊销 | C28: 35089.62 | D28: 35089.62 | E28: 35089.62 | F28: 35089.62 | G28: 35089.62 | H28: 35089.62 | I28: 35089.62 | J28: 35089.62 | K28: 35089.62 | L28: 35089.62 | M28: 35089.62 | N28: 35089.62 | O28: 35089.62 | P28: 35089.62 | Q28: 35089.62 | R28: 35089.62 | S28: 35089.62 | T28: 35089.62 | U28: 35089.62 | V28: 35089.62 | W28: 35089.62 | X28: 35089.62 | Y28: 35089.62 | Z28: 35089.62 | AA28: 35089.62 | AB28: 35089.62 | AC28: 35089.62 | AD28: 35089.62 | AE28: 35089.62 | AF28: 35089.62 | AH28: =SUM(C28:AG28) -> 1052688.6
A29: 二、主营业务成本总计 | C29: 119928.94 | D29: 118672.67 | E29: 117952.8 | F29: 124915.9 | G29: 122022.85 | H29: 121543.85 | I29: 121909.7 | J29: 121182.94 | K29: 118258.93 | L29: 118733.52 | M29: 119392.93 | N29: 119324.85 | O29: 121126.11 | P29: 120637.95 | Q29: 119831.06 | R29: 118550.56 | S29: 120111.61 | T29: 120140.74 | U29: 121668.85 | V29: 122002.25 | W29: 120629.89 | X29: 122909.74 | Y29: 120873.26 | Z29: 122580.1 | AA29: 120804.86 | AB29: 120717.72 | AC29: 121221.94 | AD29: 123739.64 | AE29: 121356.4 | AF29: 119104.45 | AH29: =SUM(AH19:AH28) -> 3621847
A30: 主营业务税金及附加 | C30: 688.6 | D30: 672.64 | E30: 772.53 | F30: 821.15 | G30: 874.85 | H30: 852.35 | I30: 838.22 | J30: 827.84 | K30: 782.33 | L30: 833.91 | M30: 849.99 | N30: 836.01 | O30: 876.61 | P30: 841.55 | Q30: 799.49 | R30: 823.29 | S30: 829.85 | T30: 837.25 | U30: 886.05 | V30: 872.07 | W30: 901.54 | X30: 873.81 | Y30: 815.37 | Z30: 789 | AA30: 815.96 | AB30: 771.71 | AC30: 782.69 | AD30: 771.49 | AE30: 793.81 | AF30: 764.37 | AH30: =SUM(C30:AG30) -> 24496.33
A31: 三、主营业务利润（亏损以“-”号填列) | C31: -24978.35 | D31: -25923.55 | E31: -11428.93 | F31: -11688.36 | G31: -1390.29 | H31: -4014.73 | I31: -6328.95 | J31: -7032.67 | K31: -10384.84 | L31: -3747.01 | M31: -2188.87 | N31: -4047.93 | O31: -251.55 | P31: -4597.08 | Q31: -9590.96 | R31: -5028.25 | S31: -5683.88 | T31: -4693.95 | U31: 507.85 | V31: -1753.93 | W31: 3682.22 | X31: -2420.98 | Y31: -8443.4 | Z31: -13785.93 | AA31: -8292.57 | AB31: -14307.37 | AC31: -13298.37 | AD31: -17360.21 | AE31: -11898.19 | AF31: -13705.67 | AH31: =AH11-AH29-AH30 -> -244076.7
A32: 1 | B32: 管理人员工资 | C32: 10268.93 | D32: 10268.93 | E32: 10268.93 | F32: 10268.93 | G32: 10268.93 | H32: 10268.93 | I32: 10268.93 | J32: 10268.93 | K32: 10268.93 | L32: 10268.93 | M32: 10268.93 | N32: 10268.93 | O32: 10268.93 | P32: 10268.93 | Q32: 10268.93 | R32: 10268.93 | S32: 10268.93 | T32: 10268.93 | U32: 10268.93 | V32: 10268.93 | W32: 10268.93 | X32: 10268.93 | Y32: 10268.93 | Z32: 10268.93 | AA32: 10268.93 | AB32: 10268.93 | AC32: 10268.93 | AD32: 10268.93 | AE32: 10268.93 | AF32: 10268.93 | AH32: =SUM(C32:AG32) -> 308067.9
A33: 2 | B33: 人事工资 | C33: 700 | D33: 700 | E33: 700 | F33: 700 | G33: 700 | H33: 700 | I33: 700 | J33: 700 | K33: 700 | L33: 700 | M33: 700 | N33: 700 | O33: 700 | P33: 700 | Q33: 700 | R33: 700 | S33: 700 | T33: 700 | U33: 700 | V33: 700 | W33: 700 | X33: 700 | Y33: 700 | Z33: 700 | AA33: 700 | AB33: 700 | AC33: 700 | AD33: 700 | AE33: 700 | AF33: 700 | AH33: =SUM(C33:AG33) -> 21000
A34: 3 | B34: 社会保险费 | C34: 1350 | D34: 1350 | E34: 1350 | F34: 1350 | G34: 1350 | H34: 1350 | I34: 1350 | J34: 1350 | K34: 1350 | L34: 1350 | M34: 1350 | N34: 1350 | O34: 1350 | P34: 1350 | Q34: 1350 | R34: 1350 | S34: 1350 | T34: 1350 | U34: 1350 | V34: 1350 | W34: 1350 | X34: 1350 | Y34: 1350 | Z34: 1350 | AA34: 1350 | AB34: 1350 | AC34: 1350 | AD34: 1350 | AE34: 1350 | AF34: 1350 | AH34: =SUM(C34:AG34) -> 40500
A35: 4 | B35: 意外险 | C35: 29.17 | D35: 29.17 | E35: 29.17 | F35: 29.17 | G35: 29.17 | H35: 29.17 | I35: 29.17 | J35: 29.17 | K35: 29.17 | L35: 29.17 | M35: 29.17 | N35: 29.17 | O35: 29.17 | P35: 29.17 | Q35: 29.17 | R35: 29.17 | S35: 29.17 | T35: 29.17 | U35: 29.17 | V35: 29.17 | W35: 29.17 | X35: 29.17 | Y35: 29.17 | Z35: 29.17 | AA35: 29.17 | AB35: 29.17 | AC35: 29.17 | AD35: 29.17 | AE35: 29.17 | AF35: 29.17 | AH35: =SUM(C35:AG35) -> 875.1
A36: 5 | B36: 雇主险 | C36: 34.17 | D36: 34.17 | E36: 34.17 | F36: 34.17 | G36: 34.17 | H36: 34.17 | I36: 34.17 | J36: 34.17 | K36: 34.17 | L36: 34.17 | M36: 34.17 | N36: 34.17 | O36: 34.17 | P36: 34.17 | Q36: 34.17 | R36: 34.17 | S36: 34.17 | T36: 34.17 | U36: 34.17 | V36: 34.17 | W36: 34.17 | X36: 34.17 | Y36: 34.17 | Z36: 34.17 | AA36: 34.17 | AB36: 34.17 | AC36: 34.17 | AD36: 34.17 | AE36: 34.17 | AF36: 34.17 | AH36: =SUM(C36:AG36) -> 1025.1
A37: 6 | B37: 福利费 | AH37: =SUM(C37:AG37) -> 0
A38: 7 | B38: 招聘费 | D38: 80 | E38: 100 | F38: 140 | G38: 220 | H38: 100 | I38: 180 | J38: 280 | K38: 280 | L38: 240 | M38: 220 | N38: 160 | O38: 220 | P38: 220 | Q38: 300 | R38: 400 | S38: 300 | T38: 180 | U38: 340 | V38: 360 | W38: 420 | X38: 340 | Y38: 340 | Z38: 420 | AA38: 420 | AB38: 480 | AC38: 500 | AD38: 440 | AE38: 600 | AF38: 600 | AH38: =SUM(C38:AG38) -> 8880
A39: 8 | B39: 招标代理费 | AH39: =SUM(C39:AG39) -> 0
A40: 9 | B40: 其他 | AH40: =SUM(C40:AG40) -> 0
A41: 10 | B41: 设备维修费 | L41: 330 | AH41: =SUM(C41:AG41) -> 330
A42: 11 | B42: 人员差旅费 | AH42: =SUM(C42:AG42) -> 0
A43: 13
A44: 14
A45: 四、管理费用合计 | C45: =SUM(C32:C44) -> 12382.27 | D45: =SUM(D32:D44) -> 12462.27 | E45: =SUM(E32:E44) -> 12482.27 | F45: =SUM(F32:F44) -> 12522.27 | G45: =SUM(G32:G44) -> 12602.27 | H45: =SUM(H32:H44) -> 12482.27 | I45: =SUM(I32:I44) -> 12562.27 | J45: =SUM(J32:J44) -> 12662.27 | ... AH45: =SUM(AH32:AH44) -> 380678.1
A46: 五、利润总额（亏损总额以“-”号填列） | C46: =ROUND(C31-C45,2) -> -37360.62 | D46: =D31-D45 -> -38385.82 | E46: =E31-E45 -> -23911.2 | F46: =F31-F45 -> -24210.63 | G46: =G31-G45 -> -13992.56 | H46: =H31-H45 -> -16497 | I46: =I31-I45 -> -18891.22 | J46: =J31-J45 -> -19694.94 | K46: =K31-K45 -> -23047.11 | ... AG46: =AG31-AG45 -> 0 | AH46: =ROUND(AH31-AH45,2) -> -624754.8
A47: 六、亏损分析 | C47: 细分三高速拐弯机轨道磨损，增加10人进行人工操作，19点维修完成 | N47: 邮政省公司副总现场参观检查，全场卫生清理，开机时间延后 | O47: 翻盘机故障12：30-17：30维修5小时，异小件留人处理 | P47: 小件区开拆循环线拐弯机故障两条维修4：10-9：10修复，用时5小时 | Z47: 邮政集团及省安全组上午9点现场检查，白班增加投入12人进行现场整理 | AB47: 粗分一拆解8点开始，粗分二摆轮故障5小时，细分8滚筒故障3小时，人员增投20人应急操作成本增加 | AC47: 粗分一拆解维修，单班增投8人，全天共增投16人应急分流操作 | AD47: 粗分一拆解维修，单班增投8人，全天共增投16人应急分流操作 | AE47: 粗分一拆解维修，白班增投8人 | AF47: 粗分十拆解维修，单班增投8人，全天共增投16人应急分流操作
A48: 注：请注意业务量跳档时单价的变化
T50: 南京项目人效
T51: 部门 | V51: 南京进口
T52: 日期 | V52: 45838
T53: 管理人数 | V53: 22
T54: 自有员工 | V54: 301
T55: 劳务人员 | V55: 52
T56: 总人数 | V56: 375
T57: 散件处理量 | V57: 693059
T58: 总工时 | V58: 4008.5
T59: 人均小时效能 | V59: 172.89734

Sheet 6月处理量
A1: 日 | B1: 新一代查询业务量 （散件外走） | C1: 新一代查询业务量 （分拣封发） | D1: 新一代查询业务量 （总包经转） | E1: 平刷件量(剔除） | F1: 合计
A2: 45809 | B2: 256690 | C2: 522646 | D2: 19473 | E2: 172669 | F2: =SUM(B2:D2)-E2 -> 626140
A3: =A2+1 -> 45810 | B3: 218158 | C3: 473152 | D3: 18667 | E3: 97937 | F3: =SUM(B3:D3)-E3 -> 612040
A4: =A3+1 -> 45811 | B4: 267556 | C4: 436925 | D4: 25058 | E4: 29274 | F4: =SUM(B4:D4)-E4 -> 700265
A5: =A4+1 -> 45812 | B5: 297968 | C5: 472805 | D5: 29548 | E5: 57120 | F5: =SUM(B5:D5)-E5 -> 743201
A6: =A5+1 -> 45813 | B6: 299810 | C6: 512419 | D6: 30641 | E6: 52241 | F6: =SUM(B6:D6)-E6 -> 790629
A7: =A6+1 -> 45814 | B7: 300884 | C7: 511750 | D7: 32255 | E7: 74137 | F7: =SUM(B7:D7)-E7 -> 770752
A8: =A7+1 -> 45815 | B8: 288774 | C8: 642639 | D8: 27851 | E8: 200991 | F8: =SUM(B8:D8)-E8 -> 758273
A9: =A8+1 -> 45816 | B9: 292802 | C9: 590922 | D9: 27227 | E9: 161840 | F9: =SUM(B9:D9)-E9 -> 749111
A10: =A9+1 -> 45817 | B10: 273151 | C10: 495061 | D10: 26143 | E10: 85442 | F10: =SUM(B10:D10)-E10 -> 708913
A11: =A10+1 -> 45818 | B11: 304463 | C11: 487423 | D11: 30054 | E11: 67473 | F11: =SUM(B11:D11)-E11 -> 754467
A12: =A11+1 -> 45819 | B12: 306613 | C12: 510775 | D12: 30774 | E12: 79492 | F12: =SUM(B12:D12)-E12 -> 768670
A13: =A12+1 -> 45820 | B13: 293214 | C13: 495303 | D13: 29333 | E13: 61523 | F13: =SUM(B13:D13)-E13 -> 756327
A14: =A13+1 -> 45821 | B14: 310592 | C14: 513480 | D14: 32843 | E14: 64736 | F14: =SUM(B14:D14)-E14 -> 792179
... A31: =A30+1 -> 45838 | B31: 275507 | C31: 445495 | D31: 28344 | E31: 56287 | F31: =SUM(B31:D31)-E31 -> 693059
A32: =A31+1 -> 45839 | F32: =SUM(B32:D32)-E32 -> 0
A33: 合计 | B33: =SUM(B2:B32) -> 8625514 | C33: =SUM(C2:C32) -> 15406222 | D33: =SUM(D2:D32) -> 838428 | E33: =SUM(E2:E32) -> 2696183 | F33: =SUM(F2:F32) -> 22173981

Sheet 7月日经营数据
A1: 2025年南京项目处理经营情况（7月）
A3: 科目 | C3: 45839 | D3: =C3+1 -> 45840 | E3: =D3+1 -> 45841 | F3: =E3+1 -> 45842 | G3: =F3+1 -> 45843 | H3: =G3+1 -> 45844 | I3: =H3+1 -> 45845 | J3: =I3+1 -> 45846 | K3: =J3+1 -> 45847 | ... AG3: =AF3+1 -> 45869 | AH3: 月度合计
C4: 进口处理 | D4: 进口处理 | E4: 进口处理 | F4: 进口处理 | G4: 进口处理 | H4: 进口处理 | I4: 进口处理 | J4: 进口处理 | K4: 进口处理 | L4: 进口处理 | M4: 进口处理 | N4: 进口处理 | O4: 进口处理 | P4: 进口处理 | Q4: 进口处理 | R4: 进口处理 | S4: 进口处理 | T4: 进口处理 | U4: 进口处理 | V4: 进口处理 | W4: 进口处理 | X4: 进口处理 | Y4: 进口处理 | Z4: 进口处理 | AA4: 进口处理 | AB4: 进口处理 | AC4: 进口处理 | AD4: 进口处理 | AE4: 进口处理 | AF4: 进口处理 | AG4: 进口处理 | AH4: 进口处理
A5: 1 | B5: 散件处理量 | C5: =SUMIFS('7月处理量'!$F:$F,'7月处理量'!$A:$A,C3) -> 683425 | D5: =SUMIFS('7月处理量'!$F:$F,'7月处理量'!$A:$A,D3) -> 703537 | E5: =SUMIFS('7月处理量'!$F:$F,'7月处理量'!$A:$A,E3) -> 690093 | F5: =SUMIFS('7月处理量'!$F:$F,'7月处理量'!$A:$A,F3) -> 729987 | G5: =SUMIFS('7月处理量'!$F:$F,'7月处理量'!$A:$A,G3) -> 749412 | H5: =SUMIFS('7月处理量'!$F:$F,'7月处理量'!$A:$A,H3) -> 708683 | I5: =SUMIFS('7月处理量'!$F:$F,'7月处理量'!$A:$A,I3) -> 702077 | J5: =SUMIFS('7月处理量'!$F:$F,'7月处理量'!$A:$A,J3) -> 734319 | ... AG5: =SUMIFS('7月处理量'!$F:$F,'7月处理量'!$A:$A,AG3) -> 664209 | AH5: =SUM(C5:AG5) -> 21618238
A6: 2 | B6: 散件处理单价 | C6: 0.1667 | D6: 0.1667 | E6: 0.1667 | F6: 0.1667 | G6: 0.1667 | H6: 0.1667 | I6: 0.1667 | J6: 0.1667 | K6: 0.1667 | L6: 0.1667 | M6: 0.1667 | N6: 0.1667 | O6: 0.1667 | P6: 0.1667 | Q6: 0.1667 | R6: 0.1667 | S6: 0.1667 | T6: 0.1667 | U6: 0.1667 | V6: 0.1667 | W6: 0.1667 | X6: 0.1667 | Y6: 0.1667 | Z6: 0.1667 | AA6: 0.1667 | AB6: 0.1667 | AC6: 0.1667 | AD6: 0.1667 | AE6: 0.1667 | AF6: 0.1667 | AG6: 0.1667 | AH6: 0.1667
A7: 3 | B7: 散件处理收入 | C7: 113926.95 | D7: 117279.62 | E7: 115038.5 | F7: 121688.83 | G7: 124926.98 | H7: 118137.46 | I7: 117036.24 | J7: 122410.98 | K7: 125209.7 | L7: 119321.86 | M7: 119553.41 | N7: 118702.9 | O7: 111158.56 | P7: 111273.08 | Q7: 118609.55 | R7: 116172.9 | S7: 120600.78 | T7: 118809.76 | U7: 119655.59 | V7: 116620.15 | W7: 114463.89 | X7: 113714.74 | Y7: 122272.62 | Z7: 116046.87 | AA7: 115470.76 | AB7: 110254.71 | AC7: 110821.33 | AD7: 106690.5 | AE7: 108532.04 | AF7: 108635.39 | AG7: 110723.64 | AH7: =SUM(C7:AG7) -> 3603760.3
A8: 4 | B8: 考核扣款 | C8: 3000 | D8: 3000 | E8: 3000 | F8: 3000 | G8: 3000 | H8: 3000 | I8: 3000 | J8: 3000 | K8: 3000 | L8: 3000 | M8: 3000 | N8: 3000 | O8: 3000 | P8: 3000 | Q8: 3000 | R8: 3000 | S8: 3000 | T8: 3000 | U8: 3000 | V8: 3000 | W8: 3000 | X8: 3000 | Y8: 3000 | Z8: 3000 | AA8: 3000 | AB8: 3000 | AC8: 3000 | AD8: 3000 | AE8: 3000 | AF8: 3000 | AG8: 3000 | AH8: =SUM(C8:AG8) -> 93000
A9: 5 | B9: 补贴费用 | AH9: =SUM(C9:AG9) -> 0
A10: 6 | B10: 开票金额 | C10: 110926.95 | D10: 114279.62 | E10: 112038.5 | F10: 118688.83 | G10: 121926.98 | H10: 115137.46 | I10: 114036.24 | J10: 119410.98 | K10: 122209.7 | L10: 116321.86 | M10: 116553.41 | N10: 115702.9 | O10: 108158.56 | P10: 108273.08 | Q10: 115609.55 | R10: 113172.9 | S10: 117600.78 | T10: 115809.76 | U10: 116655.59 | V10: 113620.15 | W10: 111463.89 | X10: 110714.74 | Y10: 119272.62 | Z10: 113046.87 | AA10: 112470.76 | AB10: 107254.71 | AC10: 107821.33 | AD10: 103690.5 | AE10: 105532.04 | AF10: 105635.39 | AG10: 107723.64 | AH10: =SUM(C10:AG10) -> 3510760.3
A11: 一、主营业务收入总计 | C11: 104648.07 | D11: 107810.96 | E11: 105696.7 | F11: 111970.59 | G11: 115025.45 | H11: 108620.25 | I11: 107581.36 | J11: 112651.87 | K11: 115292.17 | L11: 109737.6 | M11: 109956.05 | N11: 109153.68 | O11: 102036.38 | P11: 102144.42 | Q11: 109065.61 | R11: 106766.89 | S11: 110944.13 | T11: 109254.49 | U11: 110052.44 | V11: 107188.82 | W11: 105154.61 | X11: 104447.87 | Y11: 112521.34 | Z11: 106647.99 | AA11: 106104.49 | AB11: 101183.69 | AC11: 101718.24 | AD11: 97821.23 | AE11: 99558.53 | AF11: 99656.03 | AG11: 101626.08 | AH11: =SUM(C11:AG11) -> 3312038
A12: 1 | B12: 管理人员数量 | C12: 21 | D12: 22 | E12: 20 | F12: 24 | G12: 22 | H12: 22 | I12: 20 | J12: 21 | K12: 21 | L12: 23 | M12: 23 | N12: 24 | O12: 20 | P12: 21 | Q12: 21 | R12: 19 | S12: 21 | T12: 21 | U12: 22 | V12: 22 | W12: 20 | X12: 21 | Y12: 20 | Z12: 20 | AA12: 21 | AB12: 20 | AC12: 21 | AD12: 21 | AE12: 21 | AF12: 23 | AG12: 24 | AH12: =SUM(C12:AG12) -> 662
A13: 2 | B13: 自有员工数量 | C13: 286 | D13: 293 | E13: 285 | F13: 270 | G13: 269 | H13: 278 | I13: 265 | J13: 278 | K13: 277 | L13: 288 | M13: 291 | N13: 281 | O13: 287 | P13: 279 | Q13: 285 | R13: 268 | S13: 283 | T13: 276 | U13: 286 | V13: 284 | W13: 280 | X13: 286 | Y13: 292 | Z13: 290 | AA13: 293 | AB13: 297 | AC13: 301 | AD13: 296 | AE13: 302 | AF13: 301 | AG13: 306 | AH13: =SUM(C13:AG13) -> 8853
A14: 3 | B14: 劳务人员数量 | C14: 55 | D14: 64 | E14: 77 | F14: 95 | G14: 93 | H14: 86 | I14: 79 | J14: 118 | K14: 114 | L14: 105 | M14: 96 | N14: 84 | O14: 90 | P14: 78 | Q14: 84 | R14: 94 | S14: 94 | T14: 94 | U14: 93 | V14: 89 | W14: 84 | X14: 88 | Y14: 89 | Z14: 86 | AA14: 85 | AB14: 76 | AC14: 65 | AD14: 65 | AE14: 64 | AF14: 60 | AG14: 57 | AH14: =SUM(C14:AG14) -> 2601
A15: 4 | B15: 总人数 | C15: 362 | D15: 379 | E15: 382 | F15: 389 | G15: 384 | H15: 386 | I15: 364 | J15: 417 | K15: 412 | L15: 416 | M15: 410 | N15: 389 | O15: 397 | P15: 378 | Q15: 390 | R15: 381 | S15: 398 | T15: 391 | U15: 401 | V15: 395 | W15: 384 | X15: 395 | Y15: 401 | Z15: 396 | AA15: 399 | AB15: 393 | AC15: 387 | AD15: 382 | AE15: 387 | AF15: 384 | AG15: 387 | AH15: =SUM(C15:AG15) -> 12116
A16: 5 | B16: 总工时 | C16: 3895 | D16: 4096.5 | E16: 4160 | F16: 4172 | G16: 4148 | H16: 4179.5 | I16: 3942 | J16: 4632 | K16: 4475.5 | L16: 4497.5 | M16: 4408.5 | N16: 4136 | O16: 4266.5 | P16: 4034 | Q16: 4195.5 | R16: 4110.5 | S16: 4294.5 | T16: 4200.5 | U16: 4323 | V16: 4104 | W16: 4158 | X16: 4257.5 | Y16: 4326 | Z16: 4286 | AA16: 4282.5 | AB16: 4153 | AC16: 4125 | AD16: 4046 | AE16: 4056 | AF16: 4054.5 | AG16: 4105 | AH16: =SUM(C16:AG16) -> 130120.5
A17: 人均效能 | C17: 1887.9144 | D17: 1856.2982 | E17: 1806.5262 | F17: 1876.5733 | G17: 1951.5938 | H17: 1835.9663 | I17: 1928.783 | J17: 1760.9568 | K17: 1823.0777 | L17: 1720.6442 | M17: 1749.2122 | N17: 1830.527 | O17: 1679.6423 | P17: 1765.8862 | Q17: 1824.3974 | R17: 1829.1286 | S17: 1817.7387 | T17: 1822.8031 | U17: 1790 | V17: 1771.0911 | W17: 1788.1406 | X17: 1726.9671 | Y17: 1829.1496 | Z17: 1757.9343 | AA17: 1736.0551 | AB17: 1682.9415 | AC17: 1717.8165 | AD17: 1675.4319 | AE17: 1682.3307 | AF17: 1697.0885 | AG17: 1716.3023 | AH17: =AH5/AH15 -> 1784.2719
A18: 人均小时效能 | C18: 175.46213 | D18: 171.741 | E18: 165.88774 | F18: 174.97291 | G18: 180.66827 | H18: 169.56167 | I18: 178.10173 | J18: 158.53174 | K18: 167.82661 | L18: 159.15242 | M18: 162.6805 | N18: 172.16514 | O18: 156.29157 | P18: 165.46976 | Q18: 169.59004 | R18: 169.54093 | S18: 168.46199 | T18: 169.67409 | U18: 166.03979 | V18: 170.46321 | W18: 165.13853 | X18: 160.22361 | Y18: 169.55363 | Z18: 162.42231 | AA18: 161.74804 | AB18: 159.2574 | AC18: 161.16242 | AD18: 158.18463 | AE18: 160.51824 | AF18: 160.73055 | AG18: 161.80487 | AH18: =AH5/AH16 -> 166.14014
A19: 1 | B19: 自有员工工资 | C19: 59652.25 | D19: 61528.1 | E19: 59889.45 | F19: 56227.95 | G19: 56326.8 | H19: 58400.05 | I19: 55526.75 | J19: 59850 | K19: 57844 | L19: 60315.2 | M19: 60539.65 | N19: 57976.4 | O19: 59176.25 | P19: 57453.45 | Q19: 59159.25 | R19: 55455.9 | S19: 58798.8 | T19: 57169.45 | U19: 59593.7 | V19: 56528.35 | W19: 58453.15 | X19: 59473.7 | Y19: 60504.75 | Z19: 60355.8 | AA19: 60560.05 | AB19: 60111.8 | AC19: 61955.05 | AD19: 60504.75 | AE19: 60909.25 | AF19: 61667.45 | AG19: 63222.15 | AH19: =SUM(C19:AG19) -> 1835129.6
A20: 2 | B20: 员工宿舍费 | C20: 19500 | AH20: =SUM(C20:AG20) -> 19500
A21: 3 | B21: 意外险 | C21: 278.06 | D21: 284.86 | E21: 277.08 | F21: 262.5 | G21: 261.53 | H21: 270.28 | I21: 257.64 | J21: 270.28 | K21: 269.31 | L21: 280 | M21: 282.92 | N21: 273.19 | O21: 279.03 | P21: 271.25 | Q21: 277.08 | R21: 260.56 | S21: 275.14 | T21: 268.33 | U21: 278.06 | V21: 276.11 | W21: 272.22 | X21: 278.06 | Y21: 283.89 | Z21: 281.94 | AA21: 284.86 | AB21: 288.75 | AC21: 292.64 | AD21: 287.78 | AE21: 293.61 | AF21: 292.64 | AG21: 297.5 | AH21: =SUM(C21:AG21) -> 8607.1
A22: 4 | B22: 雇主险 | C22: 325.72 | D22: 333.69 | E22: 324.58 | F22: 307.5 | G22: 306.36 | H22: 316.61 | I22: 301.81 | J22: 316.61 | K22: 315.47 | L22: 328 | M22: 331.42 | N22: 320.03 | O22: 326.86 | P22: 317.75 | Q22: 324.58 | R22: 305.22 | S22: 322.31 | T22: 314.33 | U22: 325.72 | V22: 323.44 | W22: 318.89 | X22: 325.72 | Y22: 332.56 | Z22: 330.28 | AA22: 333.69 | AB22: 338.25 | AC22: 342.81 | AD22: 337.11 | AE22: 343.94 | AF22: 342.81 | AG22: 348.5 | AH22: =SUM(C22:AG22) -> 10082.57
A23: 5 | B23: 员工餐费 | C23: 2456 | D23: 2520 | E23: 2440 | F23: 2352 | G23: 2328 | H23: 2400 | I23: 2280 | J23: 2392 | K23: 2384 | L23: 2488 | M23: 2512 | N23: 2440 | O23: 2456 | P23: 2400 | Q23: 2448 | R23: 2296 | S23: 2432 | T23: 2376 | U23: 2464 | V23: 2448 | W23: 2400 | X23: 2456 | Y23: 2496 | Z23: 2480 | AA23: 2512 | AB23: 2536 | AC23: 2576 | AD23: 2536 | AE23: 2584 | AF23: 2592 | AG23: 2640 | AH23: =SUM(C23:AG23) -> 76120
A24: 6 | B24: 高温福利费用 | D24: 1200 | E24: 5114 | F24: 12120 | G24: 1120 | H24: 1120 | I24: 1120 | J24: 1120 | K24: 1120 | L24: 1120 | M24: 560 | P24: 1120 | Q24: 1120 | R24: 1120 | S24: 1120 | T24: 1120 | U24: 1120 | V24: 1120 | W24: 1120 | Y24: 1120 | Z24: 1120 | AA24: 1120 | AB24: 1120 | AC24: 1120 | AD24: 1120 | AE24: 1120 | AF24: 560 | AH24: =SUM(C24:AG24) -> 43074
A25: 7 | B25: 劳务人员工资 | C25: 14536 | D25: 16916.5 | E25: 20355 | F25: 25012.5 | G25: 24495 | H25: 22563 | I25: 20792 | J25: 30958 | K25: 29865.5 | L25: 27577 | M25: 25277 | N25: 22126 | O25: 23701.5 | P25: 20516 | Q25: 22103 | R25: 24679 | S25: 24713.5 | T25: 24656 | U25: 24414.5 | V25: 23402.5 | W25: 22091.5 | X25: 23161 | Y25: 23402.5 | Z25: 22620.5 | AA25: 22321.5 | AB25: 20033 | AC25: 17192.5 | AD25: 17192.5 | AE25: 16928 | AF25: 15870 | AG25: 15076.5 | AH25: =SUM(C25:AG25) -> 684549
A26: 8 | B26: 物料采购 | C26: 1964.06 | D26: 27100 | P26: 1777.2 | V26: 466 | AA26: 1020 | AC26: 4860 | AH26: =SUM(C26:AG26) -> 37187.26
A27: 9 | B27: 工单赔付 | C27: 3225.81 | D27: 3225.81 | E27: 3225.81 | F27: 3225.81 | G27: 3225.81 | H27: 3225.81 | I27: 3225.81 | J27: 3225.81 | K27: 3225.81 | L27: 3225.81 | M27: 3225.81 | N27: 3225.81 | O27: 3225.81 | P27: 3225.81 | Q27: 3225.81 | R27: 3225.81 | S27: 3225.81 | T27: 3225.81 | U27: 3225.81 | V27: 3225.81 | W27: 3225.81 | X27: 3225.81 | Y27: 3225.81 | Z27: 3225.81 | AA27: 3225.81 | AB27: 3225.81 | AC27: 3225.81 | AD27: 3225.81 | AE27: 3225.81 | AF27: 3225.81 | AG27: 3225.81 | AH27: =SUM(C27:AG27) -> 100000.11
A28: 10 | B28: 设备成本摊销 | C28: 33957.7 | D28: 33957.7 | E28: 33957.7 | F28: 33957.7 | G28: 33957.7 | H28: 33957.7 | I28: 33957.7 | J28: 33957.7 | K28: 33957.7 | L28: 33957.7 | M28: 33957.7 | N28: 33957.7 | O28: 33957.7 | P28: 33957.7 | Q28: 33957.7 | R28: 33957.7 | S28: 33957.7 | T28: 33957.7 | U28: 33957.7 | V28: 33957.7 | W28: 33957.7 | X28: 33957.7 | Y28: 33957.7 | Z28: 33957.7 | AA28: 33957.7 | AB28: 33957.7 | AC28: 33957.7 | AD28: 33957.7 | AE28: 33957.7 | AF28: 33957.7 | AG28: 33957.7 | AH28: =SUM(C28:AG28) -> 1052688.7
A29: 二、主营业务成本总计 | C29: 135895.6 | D29: 147066.66 | E29: 125583.62 | F29: 133465.96 | G29: 122021.2 | H29: 122253.45 | I29: 117461.71 | J29: 132090.4 | K29: 128981.79 | L29: 129291.71 | M29: 126686.5 | N29: 120319.13 | O29: 123123.15 | P29: 121039.16 | Q29: 122615.42 | R29: 121300.19 | S29: 124845.26 | T29: 123087.62 | U29: 125379.49 | V29: 121747.91 | W29: 121839.27 | X29: 122877.99 | Y29: 125323.21 | Z29: 124372.03 | AA29: 125335.61 | AB29: 121611.31 | AC29: 125522.51 | AD29: 119161.65 | AE29: 119362.31 | AF29: 118508.41 | AG29: 118768.16 | AH29: =SUM(AH19:AH28) -> 3866938.4
A30: 主营业务税金及附加 | C30: 753.47 | D30: 776.24 | E30: 761.02 | F30: 806.19 | G30: 828.18 | H30: 782.07 | I30: 774.59 | J30: 811.09 | K30: 830.1 | L30: 790.11 | M30: 791.68 | N30: 785.91 | O30: 734.66 | P30: 735.44 | Q30: 785.27 | R30: 768.72 | S30: 798.8 | T30: 786.63 | U30: 792.38 | V30: 771.76 | W30: 757.11 | X30: 752.02 | Y30: 810.15 | Z30: 767.87 | AA30: 763.95 | AB30: 728.52 | AC30: 732.37 | AD30: 704.31 | AE30: 716.82 | AF30: 717.52 | AG30: 731.71 | AH30: =SUM(C30:AG30) -> 23846.66
A31: 三、主营业务利润（亏损以“-”号填列) | C31: -32001 | D31: -40031.94 | E31: -20647.94 | F31: -22301.56 | G31: -7823.93 | H31: -14415.27 | I31: -10654.94 | J31: -20249.62 | K31: -14519.72 | L31: -20344.22 | M31: -17522.13 | N31: -11951.36 | O31: -21821.43 | P31: -19630.18 | Q31: -14335.08 | R31: -15302.02 | S31: -14699.93 | T31: -14619.76 | U31: -16119.43 | V31: -15330.85 | W31: -17441.77 | X31: -19182.14 | Y31: -13612.02 | Z31: -18491.91 | AA31: -19995.07 | AB31: -21156.14 | AC31: -24536.64 | AD31: -22044.73 | AE31: -20520.6 | AF31: -19569.9 | AG31: -17873.79 | AH31: =AH11-AH29-AH30 -> -578747.02
A32: 1 | B32: 管理人员工资 | C32: 9937.68 | D32: 9937.68 | E32: 9937.68 | F32: 9937.68 | G32: 9937.68 | H32: 9937.68 | I32: 9937.68 | J32: 9937.68 | K32: 9937.68 | L32: 9937.68 | M32: 9937.68 | N32: 9937.68 | O32: 9937.68 | P32: 9937.68 | Q32: 9937.68 | R32: 9937.68 | S32: 9937.68 | T32: 9937.68 | U32: 9937.68 | V32: 9937.68 | W32: 9937.68 | X32: 9937.68 | Y32: 9937.68 | Z32: 9937.68 | AA32: 9937.68 | AB32: 9937.68 | AC32: 9937.68 | AD32: 9937.68 | AE32: 9937.68 | AF32: 9937.68 | AG32: 9937.68 | AH32: =SUM(C32:AG32) -> 308068.08
A33: 2 | B33: 人事工资 | C33: 677.42 | D33: 677.42 | E33: 677.42 | F33: 677.42 | G33: 677.42 | H33: 677.42 | I33: 677.42 | J33: 677.42 | K33: 677.42 | L33: 677.42 | M33: 677.42 | N33: 677.42 | O33: 677.42 | P33: 677.42 | Q33: 677.42 | R33: 677.42 | S33: 677.42 | T33: 677.42 | U33: 677.42 | V33: 677.42 | W33: 677.42 | X33: 677.42 | Y33: 677.42 | Z33: 677.42 | AA33: 677.42 | AB33: 677.42 | AC33: 677.42 | AD33: 677.42 | AE33: 677.42 | AF33: 677.42 | AG33: 677.42 | AH33: =SUM(C33:AG33) -> 21000.02
A34: 3 | B34: 社会保险费 | C34: 1306.4516 | D34: 1306.4516 | E34: 1306.4516 | F34: 1306.4516 | G34: 1306.4516 | H34: 1306.4516 | I34: 1306.4516 | J34: 1306.4516 | K34: 1306.4516 | L34: 1306.4516 | M34: 1306.4516 | N34: 1306.4516 | O34: 1306.4516 | P34: 1306.4516 | Q34: 1306.4516 | R34: 1306.4516 | S34: 1306.4516 | T34: 1306.4516 | U34: 1306.4516 | V34: 1306.4516 | W34: 1306.4516 | X34: 1306.4516 | Y34: 1306.4516 | Z34: 1306.4516 | AA34: 1306.4516 | AB34: 1306.4516 | AC34: 1306.4516 | AD34: 1306.4516 | AE34: 1306.4516 | AF34: 1306.4516 | AG34: 1306.4516 | AH34: =SUM(C34:AG34) -> 40500
A35: 4 | B35: 意外险 | C35: 29.17 | D35: 29.17 | E35: 29.17 | F35: 29.17 | G35: 29.17 | H35: 29.17 | I35: 29.17 | J35: 29.17 | K35: 29.17 | L35: 29.17 | M35: 29.17 | N35: 29.17 | O35: 29.17 | P35: 29.17 | Q35: 29.17 | R35: 29.17 | S35: 29.17 | T35: 29.17 | U35: 29.17 | V35: 29.17 | W35: 29.17 | X35: 29.17 | Y35: 29.17 | Z35: 29.17 | AA35: 29.17 | AB35: 29.17 | AC35: 29.17 | AD35: 29.17 | AE35: 29.17 | AF35: 29.17 | AG35: 29.17 | AH35: =SUM(C35:AG35) -> 904.27
A36: 5 | B36: 雇主险 | C36: 34.17 | D36: 34.17 | E36: 34.17 | F36: 34.17 | G36: 34.17 | H36: 34.17 | I36: 34.17 | J36: 34.17 | K36: 34.17 | L36: 34.17 | M36: 34.17 | N36: 34.17 | O36: 34.17 | P36: 34.17 | Q36: 34.17 | R36: 34.17 | S36: 34.17 | T36: 34.17 | U36: 34.17 | V36: 34.17 | W36: 34.17 | X36: 34.17 | Y36: 34.17 | Z36: 34.17 | AA36: 34.17 | AB36: 34.17 | AC36: 34.17 | AD36: 34.17 | AE36: 34.17 | AF36: 34.17 | AG36: 34.17 | AH36: =SUM(C36:AG36) -> 1059.27
A37: 6 | B37: 福利费 | AH37: =SUM(C37:AG37) -> 0
A38: 7 | B38: 招聘费 | C38: 204880 | D38: 460 | E38: 440 | F38: 360 | G38: 340 | H38: 380 | I38: 340 | J38: 420 | K38: 380 | L38: 380 | M38: 300 | N38: 420 | O38: 300 | P38: 300 | Q38: 400 | R38: 360 | S38: 320 | T38: 280 | U38: 320 | V38: 280 | W38: 360 | X38: 340 | Y38: 420 | Z38: 340 | AA38: 360 | AB38: 380 | AC38: 380 | AD38: 340 | AE38: 360 | AF38: 380 | AG38: 360 | AH38: =SUM(C38:AG38) -> 215680
A39: 8 | B39: 招标代理费 | AH39: =SUM(C39:AG39) -> 0
A40: 9 | B40: 其他 | AH40: =SUM(C40:AG40) -> 0
A41: 10 | B41: 设备维修费 | AH41: =SUM(C41:AG41) -> 0
A42: 11 | B42: 人员差旅费 | C42: 205 | Q42: 350 | AH42: =SUM(C42:AG42) -> 555
A43: 13
A44: 14
A45: 四、管理费用合计 | C45: =SUM(C32:C44) -> 217069.89 | D45: =SUM(D32:D44) -> 12444.892 | E45: =SUM(E32:E44) -> 12424.892 | F45: =SUM(F32:F44) -> 12344.892 | G45: =SUM(G32:G44) -> 12324.892 | H45: =SUM(H32:H44) -> 12364.892 | I45: =SUM(I32:I44) -> 12324.892 | J45: =SUM(J32:J44) -> 12404.892 | ... AH45: =SUM(AH32:AH44) -> 587766.64
A46: 五、利润总额（亏损总额以“-”号填列） | C46: =ROUND(C31-C45,2) -> -249070.89 | D46: =D31-D45 -> -52476.832 | E46: =E31-E45 -> -33072.832 | F46: =F31-F45 -> -34646.452 | G46: =G31-G45 -> -20148.822 | H46: =H31-H45 -> -26780.162 | I46: =I31-I45 -> -22979.832 | J46: =J31-J45 -> -32654.512 | K46: =K31-K45 -> -26884.612 | ... AG46: =AG31-AG45 -> -30218.682 | AH46: =ROUND(AH31-AH45,2) -> -1166513.7
A47: 六、亏损分析 | C47: 粗分十拆解维修，单班增投8人，全天共增投16人应急分流操作 | D47: 粗分十拆解维修，单班增投8人，全天共增投16人应急分流操作 | E47: 粗分十拆解维修，白班增投8人，晚班开拆循环线拐弯机脱轨未维修增投8人人工拉包，全天共增投16人应急分流操作 | F47: 白班开拆循环线拐弯机脱轨未维修增投8人人工拉包应急拉包 | G47: 晚班卸车17、18垛口伸缩机电机烧毁，增投5人应急生产 | J47: 省公司及集团公司领导现场参观，白班增投人员进行打扫整理 | X47: 细分五摆轮故障15：15-22：50维修，现场应急操作增投8人 | AD47: 粗分十单件分离前端传输线联动故障，增投4人辅助操作
A48: 注：请注意业务量跳档时单价的变化
AA51: 南京项目人效
AA52: 部门 | AC52: 南京进口
AA53: 日期 | AC53: 45869
AA54: 管理人数 | AC54: 24
AA55: 自有员工 | AC55: 306
AA56: 劳务人员 | AC56: 57
AA57: 总人数 | AC57: 387
AA58: 散件处理量 | AC58: 664209
AA59: 总工时 | AC59: 4105
AA60: 人均小时效能 | AC60: 161.80487

Sheet 7月处理量
A1: 日 | B1: 新一代查询业务量 （散件外走） | C1: 新一代查询业务量 （分拣封发） | D1: 新一代查询业务量 （总包经转） | E1: 平刷件量(剔除） | F1: 合计
A2: 45839 | B2: 273309 | C2: 434710 | D2: 29670 | E2: 54264 | F2: =SUM(B2:D2)-E2 -> 683425
A3: =A2+1 -> 45840 | B3: 272222 | C3: 452733 | D3: 29157 | E3: 50575 | F3: =SUM(B3:D3)-E3 -> 703537
A4: =A3+1 -> 45841 | B4: 257205 | C4: 461131 | D4: 27925 | E4: 56168 | F4: =SUM(B4:D4)-E4 -> 690093
A5: =A4+1 -> 45842 | B5: 276720 | C5: 488345 | D5: 30491 | E5: 65569 | F5: =SUM(B5:D5)-E5 -> 729987
A6: =A5+1 -> 45843 | B6: 285230 | C6: 484235 | D6: 27547 | E6: 47600 | F6: =SUM(B6:D6)-E6 -> 749412
A7: =A6+1 -> 45844 | B7: 292697 | C7: 477917 | D7: 21964 | E7: 83895 | F7: =SUM(B7:D7)-E7 -> 708683
A8: =A7+1 -> 45845 | B8: 272889 | C8: 460241 | D8: 24996 | E8: 56049 | F8: =SUM(B8:D8)-E8 -> 702077
A9: =A8+1 -> 45846 | B9: 281580 | C9: 492283 | D9: 28167 | E9: 67711 | F9: =SUM(B9:D9)-E9 -> 734319
A10: =A9+1 -> 45847 | B10: 292358 | C10: 499517 | D10: 28253 | E10: 69020 | F10: =SUM(B10:D10)-E10 -> 751108
A11: =A10+1 -> 45848 | B11: 277205 | C11: 483220 | D11: 28072 | E11: 72709 | F11: =SUM(B11:D11)-E11 -> 715788
A12: =A11+1 -> 45849 | B12: 294003 | C12: 477121 | D12: 30543 | E12: 84490 | F12: =SUM(B12:D12)-E12 -> 717177
A13: =A12+1 -> 45850 | B13: 289464 | C13: 471614 | D13: 24777 | E13: 73780 | F13: =SUM(B13:D13)-E13 -> 712075
A14: =A13+1 -> 45851 | B14: 272432 | C14: 440130 | D14: 20896 | E14: 66640 | F14: =SUM(B14:D14)-E14 -> 666818
... A32: =A31+1 -> 45869 | B32: 273807 | C32: 420393 | D32: 27367 | E32: 57358 | F32: =SUM(B32:D32)-E32 -> 664209
A33: 合计 | B33: =SUM(B2:B32) -> 8798741 | C33: =SUM(C2:C32) -> 13962355 | D33: =SUM(D2:D32) -> 837421 | E33: =SUM(E2:E32) -> 1980279 | F33: =SUM(F2:F32) -> 21618238

Sheet 8月日经营数据
A1: 2025年南京项目处理经营情况（8月）
A3: 科目 | C3: 45870 | D3: =C3+1 -> 45871 | E3: =D3+1 -> 45872 | F3: =E3+1 -> 45873 | G3: =F3+1 -> 45874 | H3: =G3+1 -> 45875 | I3: =H3+1 -> 45876 | J3: =I3+1 -> 45877 | K3: =J3+1 -> 45878 | ... AG3: =AF3+1 -> 45900 | AH3: 月度合计
C4: 进口处理 | D4: 进口处理 | E4: 进口处理 | F4: 进口处理 | G4: 进口处理 | H4: 进口处理 | I4: 进口处理 | J4: 进口处理 | K4: 进口处理 | L4: 进口处理 | M4: 进口处理 | N4: 进口处理 | O4: 进口处理 | P4: 进口处理 | Q4: 进口处理 | R4: 进口处理 | S4: 进口处理 | T4: 进口处理 | U4: 进口处理 | V4: 进口处理 | W4: 进口处理 | X4: 进口处理 | Y4: 进口处理 | Z4: 进口处理 | AA4: 进口处理 | AB4: 进口处理 | AC4: 进口处理 | AD4: 进口处理 | AE4: 进口处理 | AF4: 进口处理 | AG4: 进口处理 | AH4: 进口处理
A5: 1 | B5: 散件处理量 | C5: =SUMIFS('8月处理量'!$F:$F,'8月处理量'!$A:$A,C3) -> 650583 | D5: =SUMIFS('8月处理量'!$F:$F,'8月处理量'!$A:$A,D3) -> 676353 | E5: =SUMIFS('8月处理量'!$F:$F,'8月处理量'!$A:$A,E3) -> 672508 | F5: =SUMIFS('8月处理量'!$F:$F,'8月处理量'!$A:$A,F3) -> 650310 | G5: =SUMIFS('8月处理量'!$F:$F,'8月处理量'!$A:$A,G3) -> 665521 | H5: =SUMIFS('8月处理量'!$F:$F,'8月处理量'!$A:$A,H3) -> 673181 | I5: =SUMIFS('8月处理量'!$F:$F,'8月处理量'!$A:$A,I3) -> 696859 | J5: =SUMIFS('8月处理量'!$F:$F,'8月处理量'!$A:$A,J3) -> 719725 | ... AG5: =SUMIFS('8月处理量'!$F:$F,'8月处理量'!$A:$A,AG3) -> 814355 | AH5: =SUM(C5:AG5) -> 23084927
A6: 2 | B6: 散件处理单价 | C6: 0.1667 | D6: 0.1667 | E6: 0.1667 | F6: 0.1667 | G6: 0.1667 | H6: 0.1667 | I6: 0.1667 | J6: 0.1667 | K6: 0.1667 | L6: 0.1667 | M6: 0.1667 | N6: 0.1667 | O6: 0.1667 | P6: 0.1667 | Q6: 0.1667 | R6: 0.1667 | S6: 0.1667 | T6: 0.1667 | U6: 0.1667 | V6: 0.1667 | W6: 0.1667 | X6: 0.1667 | Y6: 0.1667 | Z6: 0.1667 | AA6: 0.1667 | AB6: 0.1667 | AC6: 0.1667 | AD6: 0.1667 | AE6: 0.1667 | AF6: 0.1667 | AG6: 0.1667 | AH6: 0.1667
A7: 3 | B7: 散件处理收入 | C7: 108452.19 | D7: 112748.05 | E7: 112107.08 | F7: 108406.68 | G7: 110942.35 | H7: 112219.27 | I7: 116166.4 | J7: 119978.16 | K7: 121927.05 | L7: 120215.54 | M7: 116337.1 | N7: 124153.66 | O7: 126516.8 | P7: 125182.36 | Q7: 129195.33 | R7: 123420.01 | S7: 122304.12 | T7: 120253.71 | U7: 120605.12 | V7: 129143.66 | W7: 129437.72 | X7: 128388.01 | Y7: 134371.7 | Z7: 131346.6 | AA7: 125043.5 | AB7: 133961.79 | AC7: 134925.48 | AD7: 138534.7 | AE7: 138236.64 | AF7: 137983.59 | AG7: 135752.98 | AH7: =SUM(C7:AG7) -> 3848257.4
A8: 4 | B8: 考核扣款 | C8: 3000 | D8: 3000 | E8: 3000 | F8: 3000 | G8: 3000 | H8: 3000 | I8: 3000 | J8: 3000 | K8: 3000 | L8: 3000 | M8: 3000 | N8: 3000 | O8: 3000 | P8: 3000 | Q8: 3000 | R8: 3000 | S8: 3000 | T8: 3000 | U8: 3000 | V8: 3000 | W8: 3000 | X8: 3000 | Y8: 3000 | Z8: 3000 | AA8: 3000 | AB8: 3000 | AC8: 3000 | AD8: 3000 | AE8: 3000 | AF8: 3000 | AG8: 3000 | AH8: =SUM(C8:AG8) -> 93000
A9: 5 | B9: 补贴费用 | AH9: =SUM(C9:AG9) -> 0
A10: 6 | B10: 开票金额 | C10: 105452.19 | D10: 109748.05 | E10: 109107.08 | F10: 105406.68 | G10: 107942.35 | H10: 109219.27 | I10: 113166.4 | J10: 116978.16 | K10: 118927.05 | L10: 117215.54 | M10: 113337.1 | N10: 121153.66 | O10: 123516.8 | P10: 122182.36 | Q10: 126195.33 | R10: 120420.01 | S10: 119304.12 | T10: 117253.71 | U10: 117605.12 | V10: 126143.66 | W10: 126437.72 | X10: 125388.01 | Y10: 131371.7 | Z10: 128346.6 | AA10: 122043.5 | AB10: 130961.79 | AC10: 131925.48 | AD10: 135534.7 | AE10: 135236.64 | AF10: 134983.59 | AG10: 132752.98 | AH10: =SUM(C10:AG10) -> 3755257.4
A11: 一、主营业务收入总计 | C11: 99483.2 | D11: 103535.9 | E11: 102931.21 | F11: 99440.26 | G11: 101832.41 | H11: 103037.05 | I11: 106760.75 | J11: 110356.75 | K11: 112195.33 | L11: 110580.7 | M11: 106921.79 | N11: 114295.91 | O11: 116525.28 | P11: 115266.38 | Q11: 119052.2 | R11: 113603.78 | S11: 112551.06 | T11: 110616.71 | U11: 110948.23 | V11: 119003.45 | W11: 119280.87 | X11: 118290.58 | Y11: 123935.57 | Z11: 121081.7 | AA11: 115135.38 | AB11: 123548.86 | AC11: 124458 | AD11: 127862.92 | AE11: 127581.74 | AF11: 127343.01 | AG11: 125238.66 | AH11: =SUM(C11:AG11) -> 3542695.6
A12: 1 | B12: 管理人员数量 | C12: 23 | D12: 23 | E12: 23 | F12: 23 | G12: 20 | H12: 22 | I12: 22 | J12: 23 | K12: 22 | L12: 24 | M12: 21 | N12: 20 | O12: 20 | P12: 21 | Q12: 21 | R12: 23 | S12: 24 | T12: 25 | U12: 25 | V12: 21 | W12: 21 | X12: 23 | Y12: 22 | Z12: 19 | AA12: 19 | AB12: 22 | AC12: 20 | AD12: 21 | AE12: 21 | AF12: 22 | AG12: 23 | AH12: =SUM(C12:AG12) -> 679
A13: 2 | B13: 自有员工数量 | C13: 296 | D13: 294 | E13: 294 | F13: 291 | G13: 299 | H13: 292 | I13: 290 | J13: 300 | K13: 299 | L13: 291 | M13: 301 | N13: 304 | O13: 308 | P13: 298 | Q13: 294 | R13: 283 | S13: 290 | T13: 287 | U13: 293 | V13: 294 | W13: 292 | X13: 283 | Y13: 292 | Z13: 283 | AA13: 284 | AB13: 295 | AC13: 300 | AD13: 305 | AE13: 290 | AF13: 289 | AG13: 281 | AH13: =SUM(C13:AG13) -> 9092
A14: 3 | B14: 劳务人员数量 | C14: 63 | D14: 65 | E14: 64 | F14: 65 | G14: 63 | H14: 57 | I14: 64 | J14: 58 | K14: 61 | L14: 58 | M14: 60 | N14: 63 | O14: 60 | P14: 65 | Q14: 65 | R14: 63 | S14: 63 | T14: 71 | U14: 67 | V14: 67 | W14: 61 | X14: 58 | Y14: 80 | Z14: 86 | AA14: 76 | AB14: 74 | AC14: 66 | AD14: 70 | AE14: 74 | AF14: 69 | AG14: 75 | AH14: =SUM(C14:AG14) -> 2051
A15: 4 | B15: 总人数 | C15: 382 | D15: 382 | E15: 381 | F15: 379 | G15: 382 | H15: 371 | I15: 376 | J15: 381 | K15: 382 | L15: 373 | M15: 382 | N15: 387 | O15: 388 | P15: 384 | Q15: 380 | R15: 369 | S15: 377 | T15: 383 | U15: 385 | V15: 382 | W15: 374 | X15: 364 | Y15: 394 | Z15: 388 | AA15: 379 | AB15: 391 | AC15: 386 | AD15: 396 | AE15: 385 | AF15: 380 | AG15: 379 | AH15: =SUM(C15:AG15) -> 11822
A16: 5 | B16: 总工时 | C16: 3975.5 | D16: 3991 | E16: 3950.5 | F16: 3928.5 | G16: 4008.5 | H16: 3875.5 | I16: 3912 | J16: 3986 | K16: 3999 | L16: 3868.5 | M16: 4008.5 | N16: 4071.5 | O16: 4115.5 | P16: 4032 | Q16: 3988 | R16: 3840.5 | S16: 3951.5 | T16: 3971.5 | U16: 4053.5 | V16: 4032.5 | W16: 3956.5 | X16: 3834 | Y16: 4174.5 | Z16: 4150.5 | AA16: 4062 | AB16: 4156 | AC16: 4099.5 | AD16: 4190.5 | AE16: 4084.5 | AF16: 4058 | AG16: 4049 | AH16: =SUM(C16:AG16) -> 124375
A17: 人均效能 | C17: 1703.0969 | D17: 1770.5576 | E17: 1765.1129 | F17: 1715.8575 | G17: 1742.2016 | H17: 1814.504 | I17: 1853.3484 | J17: 1889.042 | K17: 1914.7016 | L17: 1933.3753 | M17: 1826.9188 | N17: 1924.478 | O17: 1956.0541 | P17: 1955.5833 | Q17: 2039.5184 | R17: 2006.4282 | S17: 1946.0955 | T17: 1883.4935 | U17: 1879.1844 | V17: 2028.0288 | W17: 2076.1257 | X17: 2115.8626 | Y17: 2045.8604 | Z17: 2030.7268 | AA17: 1979.1847 | AB17: 2055.2685 | AC17: 2096.8679 | AD17: 2098.5909 | AE17: 2153.9065 | AF17: 2178.2526 | AG17: 2148.6939 | AH17: =AH5/AH15 -> 1952.7091
A18: 人均小时效能 | C18: 163.64809 | D18: 169.46956 | E18: 170.23364 | F18: 165.53646 | G18: 166.02744 | H18: 173.70172 | I18: 178.13369 | J18: 180.56322 | K18: 182.89972 | L18: 186.41566 | M18: 174.10079 | N18: 182.92349 | O18: 184.41234 | P18: 186.24603 | Q18: 194.33726 | R18: 192.78011 | S18: 185.67076 | T18: 181.63868 | U18: 178.48427 | V18: 192.11581 | W18: 196.25199 | X18: 200.88002 | Y18: 193.09354 | Z18: 189.83785 | AA18: 184.66544 | AB18: 193.36141 | AC18: 197.43652 | AD18: 198.31571 | AE18: 203.02461 | AF18: 203.97634 | AG18: 201.12497 | AH18: =AH5/AH16 -> 185.60745
A19: 1 | B19: 自有员工工资 | C19: 59439.6 | D19: 59480.7 | E19: 59509.1 | F19: 58681.75 | G19: 60596.55 | H19: 59274.5 | I19: 58584.85 | J19: 61183.55 | K19: 60814.5 | L19: 58973.7 | M19: 61263.3 | N19: 61787.65 | O19: 63130.85 | P19: 60574 | Q19: 59685 | R19: 57288.45 | S19: 59408.75 | T19: 58230.25 | U19: 60568.2 | V19: 60085.75 | W19: 60023.25 | X19: 58364.55 | Y19: 59934.5 | Z19: 58262.6 | AA19: 58803.7 | AB19: 60932.65 | AC19: 61615.4 | AD19: 62458.45 | AE19: 59526.9 | AF19: 60064.65 | AG19: 58731.15 | AH19: =SUM(C19:AG19) -> 1857278.8
A20: 2 | B20: 员工宿舍费 | AH20: =SUM(C20:AG20) -> 0
A21: 3 | B21: 意外险 | C21: 287.78 | D21: 285.83 | E21: 285.83 | F21: 282.92 | G21: 290.69 | H21: 283.89 | I21: 281.94 | J21: 291.67 | K21: 290.69 | L21: 282.92 | M21: 292.64 | N21: 295.56 | O21: 299.44 | P21: 289.72 | Q21: 285.83 | R21: 275.14 | S21: 281.94 | T21: 279.03 | U21: 284.86 | V21: 285.83 | W21: 283.89 | X21: 275.14 | Y21: 283.89 | Z21: 275.14 | AA21: 276.11 | AB21: 286.81 | AC21: 291.67 | AD21: 296.53 | AE21: 281.94 | AF21: 280.97 | AG21: 273.19 | AH21: =SUM(C21:AG21) -> 8839.43
A22: 4 | B22: 雇主险 | C22: 337.11 | D22: 334.83 | E22: 334.83 | F22: 331.42 | G22: 340.53 | H22: 332.56 | I22: 330.28 | J22: 341.67 | K22: 340.53 | L22: 331.42 | M22: 342.81 | N22: 346.22 | O22: 350.78 | P22: 339.39 | Q22: 334.83 | R22: 322.31 | S22: 330.28 | T22: 326.86 | U22: 333.69 | V22: 334.83 | W22: 332.56 | X22: 322.31 | Y22: 332.56 | Z22: 322.31 | AA22: 323.44 | AB22: 335.97 | AC22: 341.67 | AD22: 347.36 | AE22: 330.28 | AF22: 329.14 | AG22: 320.03 | AH22: =SUM(C22:AG22) -> 10354.81
A23: 5 | B23: 员工餐费 | C23: 2576 | D23: 2560 | E23: 2560 | F23: 2536 | G23: 2576 | H23: 2536 | I23: 2520 | J23: 2608 | K23: 2592 | L23: 2544 | M23: 2600 | N23: 2616 | O23: 2648 | P23: 2576 | Q23: 2544 | R23: 2472 | S23: 2536 | T23: 2520 | U23: 2568 | V23: 2544 | W23: 2528 | X23: 2472 | Y23: 2536 | Z23: 2440 | AA23: 2448 | AB23: 2560 | AC23: 2584 | AD23: 2632 | AE23: 2512 | AF23: 2512 | AG23: 2456 | AH23: =SUM(C23:AG23) -> 78912
A24: 6 | B24: 高温福利费用 | F24: 575 | G24: 575 | H24: 575 | I24: 575 | J24: 575 | K24: 575 | L24: 575 | M24: 575 | N24: 575 | O24: 575 | T24: 560 | U24: 1120 | V24: 1120 | W24: 1120 | X24: 1120 | Y24: 1120 | Z24: 1120 | AA24: 560 | AB24: 1120 | AC24: 1120 | AD24: 1120 | AE24: 1120 | AF24: 1120 | AH24: =SUM(C24:AG24) -> 19190
A25: 7 | B25: 劳务人员工资 | C25: 16893.5 | D25: 17388 | E25: 16617.5 | F25: 17192.5 | G25: 16617.5 | H25: 15030.5 | I25: 16882 | J25: 15295 | K25: 16088.5 | L25: 15295 | M25: 15824 | N25: 16617.5 | O25: 15824 | P25: 17146.5 | Q25: 17146.5 | R25: 16617.5 | S25: 16617.5 | T25: 18710.5 | U25: 17641 | V25: 17652.5 | W25: 16065.5 | X25: 15272 | Y25: 21079.5 | Z25: 22609 | AA25: 19975.5 | AB25: 19458 | AC25: 17376.5 | AD25: 18434.5 | AE25: 19538.5 | AF25: 18216 | AG25: 19803 | AH25: =SUM(C25:AG25) -> 540925.5
A26: 8 | B26: 物料采购 | C26: 3110.4 | D26: 3110.4 | E26: 3110.4 | F26: 3110.4 | G26: 3110.4 | H26: 3110.4 | I26: 3110.4 | J26: 3110.4 | K26: 3110.4 | L26: 3110.4 | M26: 49700 | AH26: =SUM(C26:AG26) -> 80804
A27: 9 | B27: 工单赔付 | C27: 2096.77 | D27: 2096.77 | E27: 2096.77 | F27: 2096.77 | G27: 2096.77 | H27: 2096.77 | I27: 2096.77 | J27: 2096.77 | K27: 2096.77 | L27: 2096.77 | M27: 2096.77 | N27: 2096.77 | O27: 2096.77 | P27: 2096.77 | Q27: 2096.77 | R27: 2096.77 | S27: 2096.77 | T27: 2096.77 | U27: 2096.77 | V27: 2096.77 | W27: 2096.77 | X27: 2096.77 | Y27: 2096.77 | Z27: 2096.77 | AA27: 2096.77 | AB27: 2096.77 | AC27: 2096.77 | AD27: 2096.77 | AE27: 2096.77 | AF27: 2096.77 | AG27: 2096.77 | AH27: =SUM(C27:AG27) -> 64999.87
A28: 10 | B28: 设备成本摊销 | C28: 33651.84 | D28: 33651.84 | E28: 33651.84 | F28: 33651.84 | G28: 33651.84 | H28: 33651.84 | I28: 33651.84 | J28: 33651.84 | K28: 33651.84 | L28: 33651.84 | M28: 33651.84 | N28: 33651.84 | O28: 33651.84 | P28: 33651.84 | Q28: 33651.84 | R28: 33651.84 | S28: 33651.84 | T28: 33651.84 | U28: 33651.84 | V28: 33651.84 | W28: 33651.84 | X28: 33651.84 | Y28: 33651.84 | Z28: 33651.84 | AA28: 33651.84 | AB28: 33651.84 | AC28: 33651.84 | AD28: 33651.84 | AE28: 33651.84 | AF28: 33651.84 | AG28: 33651.84 | AH28: =SUM(C28:AG28) -> 1043207
A29: 二、主营业务成本总计 | C29: 118393 | D29: 118908.37 | E29: 118166.27 | F29: 118458.6 | G29: 119855.28 | H29: 116891.46 | I29: 118033.08 | J29: 119153.9 | K29: 119560.23 | L29: 116861.05 | M29: 166346.36 | N29: 117986.54 | O29: 118576.68 | P29: 116674.22 | Q29: 115744.77 | R29: 112724.01 | S29: 114923.08 | T29: 116375.25 | U29: 118264.36 | V29: 117771.52 | W29: 116101.81 | X29: 113574.61 | Y29: 121035.06 | Z29: 120777.66 | AA29: 118135.36 | AB29: 120442.04 | AC29: 119077.85 | AD29: 121037.45 | AE29: 119058.23 | AF29: 118271.37 | AG29: 117331.98 | AH29: =SUM(AH19:AH28) -> 3704511.5
A30: 主营业务税金及附加 | C30: 716.28 | D30: 745.46 | E30: 741.1 | F30: 715.97 | G30: 733.19 | H30: 741.87 | I30: 768.68 | J30: 794.57 | K30: 807.81 | L30: 796.18 | M30: 769.84 | N30: 822.93 | O30: 838.98 | P30: 829.92 | Q30: 857.18 | R30: 817.95 | S30: 810.37 | T30: 796.44 | U30: 798.83 | V30: 856.82 | W30: 858.82 | X30: 851.69 | Y30: 892.34 | Z30: 871.79 | AA30: 828.97 | AB30: 889.55 | AC30: 896.1 | AD30: 920.61 | AE30: 918.59 | AF30: 916.87 | AG30: 901.72 | AH30: =SUM(C30:AG30) -> 25507.42
A31: 三、主营业务利润（亏损以“-”号填列) | C31: -19626.08 | D31: -16117.93 | E31: -15976.16 | F31: -19734.31 | G31: -18756.06 | H31: -14596.28 | I31: -12041.01 | J31: -9591.72 | K31: -8172.71 | L31: -7076.53 | M31: -60194.41 | N31: -4513.56 | O31: -2890.38 | P31: -2237.76 | Q31: 2450.25 | R31: 61.82 | S31: -3182.39 | T31: -6554.98 | U31: -8114.96 | V31: 375.11 | W31: 2320.24 | X31: 3864.28 | Y31: 2008.17 | Z31: -567.75 | AA31: -3828.95 | AB31: 2217.27 | AC31: 4484.05 | AD31: 5904.86 | AE31: 7604.92 | AF31: 8154.77 | AG31: 7004.96 | AH31: =AH11-AH29-AH30 -> -187323.23
A32: 1 | B32: 管理人员工资 | C32: 10686.37 | D32: 10686.37 | E32: 10686.37 | F32: 10686.37 | G32: 10686.37 | H32: 10686.37 | I32: 10686.37 | J32: 10686.37 | K32: 10686.37 | L32: 10686.37 | M32: 10686.37 | N32: 10686.37 | O32: 10686.37 | P32: 10686.37 | Q32: 10686.37 | R32: 10686.37 | S32: 10686.37 | T32: 10686.37 | U32: 10686.37 | V32: 10686.37 | W32: 10686.37 | X32: 10686.37 | Y32: 10686.37 | Z32: 10686.37 | AA32: 10686.37 | AB32: 10686.37 | AC32: 10686.37 | AD32: 10686.37 | AE32: 10686.37 | AF32: 10686.37 | AG32: 10686.37 | AH32: =SUM(C32:AG32) -> 331277.47
A33: 2 | B33: 人事工资 | C33: 680.65 | D33: 680.65 | E33: 680.65 | F33: 680.65 | G33: 680.65 | H33: 680.65 | I33: 680.65 | J33: 680.65 | K33: 680.65 | L33: 680.65 | M33: 680.65 | N33: 680.65 | O33: 680.65 | P33: 680.65 | Q33: 680.65 | R33: 680.65 | S33: 680.65 | T33: 680.65 | U33: 680.65 | V33: 680.65 | W33: 680.65 | X33: 680.65 | Y33: 680.65 | Z33: 680.65 | AA33: 680.65 | AB33: 680.65 | AC33: 680.65 | AD33: 680.65 | AE33: 680.65 | AF33: 680.65 | AG33: 680.65 | AH33: =SUM(C33:AG33) -> 21100.15
A34: 3 | B34: 社会保险费 | C34: 1262.9032 | D34: 1262.9032 | E34: 1262.9032 | F34: 1262.9032 | G34: 1262.9032 | H34: 1262.9032 | I34: 1262.9032 | J34: 1262.9032 | K34: 1262.9032 | L34: 1262.9032 | M34: 1262.9032 | N34: 1262.9032 | O34: 1262.9032 | P34: 1262.9032 | Q34: 1262.9032 | R34: 1262.9032 | S34: 1262.9032 | T34: 1262.9032 | U34: 1262.9032 | V34: 1262.9032 | W34: 1262.9032 | X34: 1262.9032 | Y34: 1262.9032 | Z34: 1262.9032 | AA34: 1262.9032 | AB34: 1262.9032 | AC34: 1262.9032 | AD34: 1262.9032 | AE34: 1262.9032 | AF34: 1262.9032 | AG34: 1262.9032 | AH34: =ROUND(SUM(C34:AG34),2) -> 39150
A35: 4 | B35: 意外险 | C35: 29.17 | D35: 29.17 | E35: 29.17 | F35: 29.17 | G35: 29.17 | H35: 29.17 | I35: 29.17 | J35: 29.17 | K35: 29.17 | L35: 29.17 | M35: 29.17 | N35: 29.17 | O35: 29.17 | P35: 29.17 | Q35: 29.17 | R35: 29.17 | S35: 29.17 | T35: 29.17 | U35: 29.17 | V35: 29.17 | W35: 29.17 | X35: 29.17 | Y35: 29.17 | Z35: 29.17 | AA35: 29.17 | AB35: 29.17 | AC35: 29.17 | AD35: 29.17 | AE35: 29.17 | AF35: 29.17 | AG35: 29.17 | AH35: =SUM(C35:AG35) -> 904.27
A36: 5 | B36: 雇主险 | C36: 34.17 | D36: 34.17 | E36: 34.17 | F36: 34.17 | G36: 34.17 | H36: 34.17 | I36: 34.17 | J36: 34.17 | K36: 34.17 | L36: 34.17 | M36: 34.17 | N36: 34.17 | O36: 34.17 | P36: 34.17 | Q36: 34.17 | R36: 34.17 | S36: 34.17 | T36: 34.17 | U36: 34.17 | V36: 34.17 | W36: 34.17 | X36: 34.17 | Y36: 34.17 | Z36: 34.17 | AA36: 34.17 | AB36: 34.17 | AC36: 34.17 | AD36: 34.17 | AE36: 34.17 | AF36: 34.17 | AG36: 34.17 | AH36: =SUM(C36:AG36) -> 1059.27
A37: 6 | B37: 福利费 | AH37: =SUM(C37:AG37) -> 0
A38: 7 | B38: 招聘费 | C38: 620 | D38: 560 | E38: 580 | F38: 520 | G38: 540 | H38: 560 | I38: 500 | J38: 580 | K38: 540 | L38: 420 | M38: 520 | N38: 560 | O38: 520 | P38: 480 | Q38: 480 | R38: 460 | S38: 500 | T38: 480 | U38: 460 | V38: 480 | W38: 480 | X38: 420 | Y38: 400 | Z38: 380 | AA38: 340 | AB38: 360 | AC38: 300 | AD38: 280 | AE38: 320 | AF38: 320 | AG38: 280 | AH38: =SUM(C38:AG38) -> 14240
A39: 8 | B39: 招标代理费 | AH39: =SUM(C39:AG39) -> 0
A40: 9 | B40: 其他 | D40: 233004.05 | AH40: =SUM(C40:AG40) -> 233004.05
A41: 10 | B41: 设备维修费 | AH41: =SUM(C41:AG41) -> 0
A42: 11 | B42: 人员差旅费 | C42: 634 | AH42: =SUM(C42:AG42) -> 634
A43: 13
A44: 14
A45: 四、管理费用合计 | C45: =SUM(C32:C44) -> 13947.263 | D45: =SUM(D32:D44) -> 246257.31 | E45: =SUM(E32:E44) -> 13273.263 | F45: =SUM(F32:F44) -> 13213.263 | G45: =SUM(G32:G44) -> 13233.263 | H45: =SUM(H32:H44) -> 13253.263 | I45: =SUM(I32:I44) -> 13193.263 | J45: =SUM(J32:J44) -> 13273.263 | ... AH45: =SUM(AH32:AH44) -> 641369.21
A46: 五、利润总额（亏损总额以“-”号填列） | C46: =ROUND(C31-C45,2) -> -33573.34 | D46: =D31-D45 -> -262375.24 | E46: =E31-E45 -> -29249.423 | F46: =F31-F45 -> -32947.573 | G46: =G31-G45 -> -31989.323 | H46: =H31-H45 -> -27849.543 | I46: =I31-I45 -> -25234.273 | J46: =J31-J45 -> -22864.983 | K46: =K31-K45 -> -21405.973 | ... AG46: =AG31-AG45 -> -5968.3032 | AH46: =ROUND(AH31-AH45,2) -> -828692.44
A47: 六、亏损分析 | C47: 细分三高速拐弯机故障，维修9点-12点，增投6人手工应急操作 | Q47: 装车三区37号门洞电机支架断裂未修复，单班增投3人，全天增投6人 | R47: 装车三区37号门洞电机支架断裂未修复，单班增投3人，全天增投6人 | S47: 装车三区37号门洞电机支架断裂未修复，单班增投3人，全天增投6人 | T47: 装车三区37号门洞电机支架断裂未修复，单班增投3人，全天增投6人 | U47: 装车三区37号门洞电机支架断裂未修复，单班增投3人，全天增投6人 | V47: 装车三区37号门洞电机支架断裂未修复，单班增投3人，全天增投6人 | W47: 装车三区37号门洞电机支架断裂未修复，单班增投3人，全天增投6人 | X47: 装车三区37号门洞电机支架断裂白班未修复，增投3人 | AB47: 晚班20:00-02:00点细分二摆轮故障6小时影响整体操作进度，破损、遗失件增加
A48: 注：请注意业务量跳档时单价的变化
Y51: 南京项目人效
Y52: 部门 | AA52: 南京进口
Y53: 日期 | AA53: 45900
Y54: 管理人数 | AA54: 23
Y55: 自有员工 | AA55: 281
Y56: 劳务人员 | AA56: 75
Y57: 总人数 | AA57: 379
Y58: 散件处理量 | AA58: 814355
Y59: 总工时 | AA59: 4049
Y60: 人均小时效能 | AA60: 201.12497

Sheet 8月处理量
A1: 日 | B1: 新一代查询业务量 （散件外走） | C1: 新一代查询业务量 （分拣封发） | D1: 新一代查询业务量 （总包经转） | E1: 平刷件量(剔除） | F1: 合计
A2: 45870 | B2: 265918 | C2: 420926 | D2: 28237 | E2: 64498 | F2: =SUM(B2:D2)-E2 -> 650583
A3: =A2+1 -> 45871 | B3: 268929 | C3: 454959 | D3: 23151 | E3: 70686 | F3: =SUM(B3:D3)-E3 -> 676353
A4: =A3+1 -> 45872 | B4: 278901 | C4: 439012 | D4: 21473 | E4: 66878 | F4: =SUM(B4:D4)-E4 -> 672508
A5: =A4+1 -> 45873 | B5: 255750 | C5: 429140 | D5: 24325 | E5: 58905 | F5: =SUM(B5:D5)-E5 -> 650310
A6: =A5+1 -> 45874 | B6: 263565 | C6: 430762 | D6: 26767 | E6: 55573 | F6: =SUM(B6:D6)-E6 -> 665521
A7: =A6+1 -> 45875 | B7: 260161 | C7: 442334 | D7: 31614 | E7: 60928 | F7: =SUM(B7:D7)-E7 -> 673181
A8: =A7+1 -> 45876 | B8: 265972 | C8: 493373 | D8: 27835 | E8: 90321 | F8: =SUM(B8:D8)-E8 -> 696859
A9: =A8+1 -> 45877 | B9: 270233 | C9: 477225 | D9: 29268 | E9: 57001 | F9: =SUM(B9:D9)-E9 -> 719725
A10: =A9+1 -> 45878 | B10: 283386 | C10: 480012 | D10: 26328 | E10: 58310 | F10: =SUM(B10:D10)-E10 -> 731416
A11: =A10+1 -> 45879 | B11: 268084 | C11: 513384 | D11: 21672 | E11: 81991 | F11: =SUM(B11:D11)-E11 -> 721149
A12: =A11+1 -> 45880 | B12: 245764 | C12: 485640 | D12: 26098 | E12: 59619 | F12: =SUM(B12:D12)-E12 -> 697883
A13: =A12+1 -> 45881 | B13: 269576 | C13: 507623 | D13: 28264 | E13: 60690 | F13: =SUM(B13:D13)-E13 -> 744773
A14: =A13+1 -> 45882 | B14: 286425 | C14: 498912 | D14: 28709 | E14: 55097 | F14: =SUM(B14:D14)-E14 -> 758949
... A32: =A31+1 -> 45900 | B32: 304900 | C32: 765662 | D32: 22729 | E32: 278936 | F32: =SUM(B32:D32)-E32 -> 814355
A33: 合计 | B33: =SUM(B2:B32) -> 8697170 | C33: =SUM(C2:C32) -> 15754159 | D33: =SUM(D2:D32) -> 836883 | E33: =SUM(E2:E32) -> 2203285 | F33: =SUM(F2:F32) -> 23084927

Sheet 25年9月日经营数据
A1: 2025年南京项目处理经营情况（9月）
A3: 科目 | C3: 45901 | D3: =C3+1 -> 45902 | E3: =D3+1 -> 45903 | F3: =E3+1 -> 45904 | G3: =F3+1 -> 45905 | H3: =G3+1 -> 45906 | I3: =H3+1 -> 45907 | J3: =I3+1 -> 45908 | K3: =J3+1 -> 45909 | ... AG3: =AF3+1 -> 45931 | AH3: 月度合计
C4: 进口处理 | D4: 进口处理 | E4: 进口处理 | F4: 进口处理 | G4: 进口处理 | H4: 进口处理 | I4: 进口处理 | J4: 进口处理 | K4: 进口处理 | L4: 进口处理 | M4: 进口处理 | N4: 进口处理 | O4: 进口处理 | P4: 进口处理 | Q4: 进口处理 | R4: 进口处理 | S4: 进口处理 | T4: 进口处理 | U4: 进口处理 | V4: 进口处理 | W4: 进口处理 | X4: 进口处理 | Y4: 进口处理 | Z4: 进口处理 | AA4: 进口处理 | AB4: 进口处理 | AC4: 进口处理 | AD4: 进口处理 | AE4: 进口处理 | AF4: 进口处理 | AG4: 进口处理 | AH4: 进口处理
A5: 1 | B5: 散件处理量 | C5: =SUMIFS('25年9月处理量'!$F:$F,'25年9月处理量'!$A:$A,C3) -> 834018 | D5: =SUMIFS('25年9月处理量'!$F:$F,'25年9月处理量'!$A:$A,D3) -> 873579 | E5: =SUMIFS('25年9月处理量'!$F:$F,'25年9月处理量'!$A:$A,E3) -> 938726 | F5: =SUMIFS('25年9月处理量'!$F:$F,'25年9月处理量'!$A:$A,F3) -> 934687 | G5: =SUMIFS('25年9月处理量'!$F:$F,'25年9月处理量'!$A:$A,G3) -> 976230 | H5: =SUMIFS('25年9月处理量'!$F:$F,'25年9月处理量'!$A:$A,H3) -> 892603 | I5: =SUMIFS('25年9月处理量'!$F:$F,'25年9月处理量'!$A:$A,I3) -> 893308 | J5: =SUMIFS('25年9月处理量'!$F:$F,'25年9月处理量'!$A:$A,J3) -> 897556 | ... AG5: =SUMIFS('25年9月处理量'!$F:$F,'25年9月处理量'!$A:$A,AG3) -> 0 | AH5: =SUM(C5:AG5) -> 27199706
A6: 2 | B6: 散件处理单价 | C6: 0.1667 | D6: 0.1667 | E6: 0.1667 | F6: 0.1667 | G6: 0.1667 | H6: 0.1667 | I6: 0.1667 | J6: 0.1667 | K6: 0.1667 | L6: 0.1667 | M6: 0.1667 | N6: 0.1667 | O6: 0.1667 | P6: 0.1667 | Q6: 0.1667 | R6: 0.1667 | S6: 0.1667 | T6: 0.1667 | U6: 0.1667 | V6: 0.1667 | W6: 0.1667 | X6: 0.1667 | Y6: 0.1667 | Z6: 0.1667 | AA6: 0.1667 | AB6: 0.1667 | AC6: 0.1667 | AD6: 0.1667 | AE6: 0.1667 | AF6: 0.1667 | AH6: 0.1667
A7: 3 | B7: 散件处理收入 | C7: 139030.8 | D7: 145625.62 | E7: 156485.62 | F7: 155812.32 | G7: 162737.54 | H7: 148796.92 | I7: 148914.44 | J7: 149622.59 | K7: 154351.7 | L7: 153784.75 | M7: 158537.7 | N7: 149847.8 | O7: 157890.74 | P7: 144718.44 | Q7: 142077.24 | R7: 144449.72 | S7: 151507.3 | T7: 163190.63 | U7: 151643.16 | V7: 149619.42 | W7: 141761.01 | X7: 145759.31 | Y7: 150032.17 | Z7: 154268.68 | AA7: 148896.61 | AB7: 153474.52 | AC7: 157544 | AD7: 153933.61 | AE7: 158569.54 | AF7: 141307.09 | AH7: =SUM(C7:AG7) -> 4534191
A8: 4 | B8: 考核扣款 | C8: 3000 | D8: 3000 | E8: 3000 | F8: 3000 | G8: 3000 | H8: 3000 | I8: 3000 | J8: 3000 | K8: 3000 | L8: 3000 | M8: 3000 | N8: 3000 | O8: 3000 | P8: 3000 | Q8: 3000 | R8: 3000 | S8: 3000 | T8: 3000 | U8: 3000 | V8: 3000 | W8: 3000 | X8: 3000 | Y8: 3000 | Z8: 3000 | AA8: 3000 | AB8: 3000 | AC8: 3000 | AD8: 3000 | AE8: 3000 | AF8: 3000 | AH8: =SUM(C8:AG8) -> 90000
A9: 5 | B9: 补贴费用 | AH9: =SUM(C9:AG9) -> 0
A10: 6 | B10: 开票金额 | C10: 136030.8 | D10: 142625.62 | E10: 153485.62 | F10: 152812.32 | G10: 159737.54 | H10: 145796.92 | I10: 145914.44 | J10: 146622.59 | K10: 151351.7 | L10: 150784.75 | M10: 155537.7 | N10: 146847.8 | O10: 154890.74 | P10: 141718.44 | Q10: 139077.24 | R10: 141449.72 | S10: 148507.3 | T10: 160190.63 | U10: 148643.16 | V10: 146619.42 | W10: 138761.01 | X10: 142759.31 | Y10: 147032.17 | Z10: 151268.68 | AA10: 145896.61 | AB10: 150474.52 | AC10: 154544 | AD10: 150933.61 | AE10: 155569.54 | AF10: 138307.09 | AH10: =SUM(C10:AG10) -> 4444191
A11: 一、主营业务收入总计 | C11: 128330.94 | D11: 134552.47 | E11: 144797.75 | F11: 144162.57 | G11: 150695.79 | H11: 137544.26 | I11: 137655.13 | J11: 138323.2 | K11: 142784.62 | L11: 142249.76 | M11: 146733.68 | N11: 138535.66 | O11: 146123.34 | P11: 133696.64 | Q11: 131204.94 | R11: 133443.13 | S11: 140101.23 | T11: 151123.24 | U11: 140229.4 | V11: 138320.21 | W11: 130906.61 | X11: 134678.59 | Y11: 138709.59 | Z11: 142706.3 | AA11: 137638.31 | AB11: 141957.09 | AC11: 145796.23 | AD11: 142390.2 | AE11: 146763.72 | AF11: 130478.39 | AH11: =SUM(C11:AG11) -> 4192633
A12: 1 | B12: 管理人员数量 | C12: 22 | D12: 20 | E12: 21 | F12: 21 | G12: 22 | H12: 21 | I12: 22 | J12: 20 | K12: 22 | L12: 21 | M12: 21 | N12: 22 | O12: 22 | P12: 24 | Q12: 24 | R12: 21 | S12: 22 | T12: 22 | U12: 20 | V12: 18 | W12: 21 | X12: 20 | Y12: 21 | Z12: 20 | AA12: 17 | AB12: 17 | AC12: 20 | AD12: 18 | AE12: 19 | AF12: 21 | AH12: =SUM(C12:AG12) -> 622
A13: 2 | B13: 自有员工数量 | C13: 281 | D13: 279 | E13: 292 | F13: 293 | G13: 292 | H13: 284 | I13: 282 | J13: 279 | K13: 277 | L13: 290 | M13: 290 | N13: 287 | O13: 297 | P13: 299 | Q13: 276 | R13: 275 | S13: 268 | T13: 281 | U13: 295 | V13: 298 | W13: 301 | X13: 295 | Y13: 282 | Z13: 289 | AA13: 287 | AB13: 286 | AC13: 281 | AD13: 287 | AE13: 273 | AF13: 263 | AH13: =SUM(C13:AG13) -> 8559
A14: 3 | B14: 劳务人员数量 | C14: 72 | D14: 83 | E14: 90 | F14: 85 | G14: 94 | H14: 92 | I14: 89 | J14: 72 | K14: 91 | L14: 102 | M14: 103 | N14: 109 | O14: 107 | P14: 90 | Q14: 89 | R14: 96 | S14: 115 | T14: 126 | U14: 104 | V14: 99 | W14: 82 | X14: 84 | Y14: 90 | Z14: 80 | AA14: 102 | AB14: 103 | AC14: 119 | AD14: 114 | AE14: 105 | AF14: 98 | AH14: =SUM(C14:AG14) -> 2885
A15: 4 | B15: 总人数 | C15: 375 | D15: 382 | E15: 403 | F15: 399 | G15: 408 | H15: 397 | I15: 393 | J15: 371 | K15: 390 | L15: 413 | M15: 414 | N15: 418 | O15: 426 | P15: 413 | Q15: 389 | R15: 392 | S15: 405 | T15: 429 | U15: 419 | V15: 415 | W15: 404 | X15: 399 | Y15: 393 | Z15: 389 | AA15: 406 | AB15: 406 | AC15: 420 | AD15: 419 | AE15: 397 | AF15: 382 | AH15: =SUM(C15:AG15) -> 12066
A16: 5 | B16: 总工时 | C16: 4039.5 | D16: 4148.5 | E16: 4381.5 | F16: 4322.5 | G16: 4408 | H16: 4298.5 | I16: 4186.5 | J16: 3995 | K16: 4214.5 | L16: 4496.5 | M16: 4475.5 | N16: 4536 | O16: 4574 | P16: 4443 | Q16: 4181.5 | R16: 4251.5 | S16: 4393 | T16: 4692 | U16: 4586.5 | V16: 4556 | W16: 4365 | X16: 4301.5 | Y16: 4253.5 | Z16: 4241 | AA16: 4473.5 | AB16: 4466 | AC16: 4599 | AD16: 4609.5 | AE16: 4339.5 | AF16: 4102 | AH16: =SUM(C16:AG16) -> 130930.5
A17: 人均效能 | C17: 2224.048 | D17: 2286.856 | E17: 2329.3449 | F17: 2342.5739 | G17: 2392.7206 | H17: 2248.3703 | I17: 2273.0483 | J17: 2419.2884 | K17: 2374.1667 | L17: 2233.7143 | M17: 2297.1884 | N17: 2150.4952 | O17: 2223.3685 | P17: 2102.0266 | Q17: 2190.9846 | R17: 2210.523 | S17: 2244.1037 | T17: 2281.9301 | U17: 2171.0668 | V17: 2162.7398 | W17: 2104.9406 | X17: 2191.4311 | Y17: 2290.1094 | Z17: 2378.9897 | AA17: 2200.0025 | AB17: 2267.6429 | AC17: 2250.1786 | AD17: 2203.8592 | AE17: 2396.0378 | AF17: 2219.0393 | AH17: =AH5/AH15 -> 2254.2438
A18: 人均小时效能 | C18: 206.46565 | D18: 210.57708 | E18: 214.24763 | F18: 216.23759 | G18: 221.46779 | H18: 207.65453 | I18: 213.37824 | J18: 224.66984 | K18: 219.69985 | L18: 205.16491 | M18: 212.49827 | N18: 198.17174 | O18: 207.07368 | P18: 195.39433 | Q18: 203.8247 | R18: 203.8163 | S18: 206.88869 | T18: 208.64194 | U18: 198.33795 | V18: 197.0011 | W18: 194.82153 | X18: 203.27351 | Y18: 211.59351 | Z18: 218.20962 | AA18: 199.66492 | AB18: 206.14935 | AC18: 205.49576 | AD18: 200.3291 | AE18: 219.20198 | AF18: 206.64871 | AH18: =AH5/AH16 -> 207.74156
A19: 1 | B19: 自有员工工资 | C19: 59222.15 | D19: 58876.8 | E19: 61695.5 | F19: 61657.45 | G19: 61397.45 | H19: 59729.55 | I19: 58279.85 | J19: 58377.85 | K19: 58372.55 | L19: 61216.6 | M19: 60661.55 | N19: 60524 | O19: 61636.8 | P19: 62832.85 | Q19: 58216.3 | R19: 57848.2 | S19: 56711 | T19: 59259.2 | U19: 62211.6 | V19: 62707.15 | W19: 62834.75 | X19: 61272.3 | Y19: 59101.85 | Z19: 60996.85 | AA19: 60589.7 | AB19: 60239.1 | AC19: 59263.5 | AD19: 60577.85 | AE19: 57497.6 | AF19: 54609.05 | AH19: =SUM(C19:AG19) -> 1798416.9
A20: 2 | B20: 员工宿舍费 | AH20: =SUM(C20:AG20) -> 0
A21: 3 | B21: 意外险 | C21: 273.19 | D21: 271.25 | E21: 283.89 | F21: 284.86 | G21: 283.89 | H21: 276.11 | I21: 274.17 | J21: 271.25 | K21: 269.31 | L21: 281.94 | M21: 281.94 | N21: 279.03 | O21: 288.75 | P21: 290.69 | Q21: 268.33 | R21: 267.36 | S21: 260.56 | T21: 273.19 | U21: 286.81 | V21: 289.72 | W21: 292.64 | X21: 286.81 | Y21: 274.17 | Z21: 280.97 | AA21: 279.03 | AB21: 278.06 | AC21: 273.19 | AD21: 279.03 | AE21: 265.42 | AF21: 255.69 | AH21: =SUM(C21:AG21) -> 8321.25
A22: 4 | B22: 雇主险 | C22: 320.03 | D22: 317.75 | E22: 332.56 | F22: 333.69 | G22: 332.56 | H22: 323.44 | I22: 321.17 | J22: 317.75 | K22: 315.47 | L22: 330.28 | M22: 330.28 | N22: 326.86 | O22: 338.25 | P22: 340.53 | Q22: 314.33 | R22: 313.19 | S22: 305.22 | T22: 320.03 | U22: 335.97 | V22: 339.39 | W22: 342.81 | X22: 335.97 | Y22: 321.17 | Z22: 329.14 | AA22: 326.86 | AB22: 325.72 | AC22: 320.03 | AD22: 326.86 | AE22: 310.92 | AF22: 299.53 | AH22: =SUM(C22:AG22) -> 9747.76
A23: 5 | B23: 员工餐费 | C23: 2448 | D23: 2416 | E23: 2528 | F23: 2536 | G23: 2536 | H23: 2464 | I23: 2456 | J23: 2416 | K23: 2416 | L23: 2512 | M23: 2512 | N23: 2496 | O23: 2576 | P23: 2608 | Q23: 2424 | R23: 2392 | S23: 2344 | T23: 2448 | U23: 2544 | V23: 2552 | W23: 2600 | X23: 2544 | Y23: 2448 | Z23: 2496 | AA23: 2456 | AB23: 2448 | AC23: 2432 | AD23: 2464 | AE23: 2360 | AF23: 2296 | AH23: =SUM(C23:AG23) -> 74168
A24: 6 | B24: 高温福利费用 | AH24: =SUM(C24:AG24) -> 0
A25: 7 | B25: 劳务人员工资 | C25: 19009.5 | D25: 21919 | E25: 23724.5 | F25: 22413.5 | G25: 24782.5 | H25: 24253.5 | I25: 23425.5 | J25: 18975 | K25: 23943 | L25: 26910 | M25: 28945.5 | N25: 30521 | O25: 28083 | P25: 23690 | Q25: 23437 | R25: 25265.5 | S25: 30176 | T25: 33016.5 | U25: 27289.5 | V25: 25898 | W25: 21539.5 | X25: 22103 | Y25: 23667 | Z25: 21022 | AA25: 26795 | AB25: 27059.5 | AC25: 31234 | AD25: 29911.5 | AE25: 27600 | AF25: 25760 | AH25: =SUM(C25:AG25) -> 762369.5
A26: 8 | B26: 物料采购 | C26: 7969 | AH26: =SUM(C26:AG26) -> 7969
A27: 9 | B27: 工单赔付 | C27: 2000 | D27: 2000 | E27: 2000 | F27: 2000 | G27: 2000 | H27: 2000 | I27: 2000 | J27: 2000 | K27: 2000 | L27: 2000 | M27: 2000 | N27: 2000 | O27: 2000 | P27: 2000 | Q27: 2000 | R27: 2000 | S27: 2000 | T27: 2000 | U27: 2000 | V27: 2000 | W27: 2000 | X27: 2000 | Y27: 2000 | Z27: 2000 | AA27: 2000 | AB27: 2000 | AC27: 2000 | AD27: 2000 | AE27: 2000 | AF27: 2000 | AH27: =SUM(C27:AG27) -> 60000
A28: 10 | B28: 设备成本摊销 | C28: 34694.903 | D28: 34694.903 | E28: 34694.903 | F28: 34694.903 | G28: 34694.903 | H28: 34694.903 | I28: 34694.903 | J28: 34694.903 | K28: 34694.903 | L28: 34694.903 | M28: 34694.903 | N28: 34694.903 | O28: 34694.903 | P28: 34694.903 | Q28: 34694.903 | R28: 34694.903 | S28: 34694.903 | T28: 34694.903 | U28: 34694.903 | V28: 34694.903 | W28: 34694.903 | X28: 34694.903 | Y28: 34694.903 | Z28: 34694.903 | AA28: 34694.903 | AB28: 34694.903 | AC28: 34694.903 | AD28: 34694.903 | AE28: 34694.903 | AF28: 34694.903 | AH28: =SUM(C28:AG28) -> 1040847.1
A29: 二、主营业务成本总计 | C29: 125936.77 | D29: 120495.7 | E29: 125259.35 | F29: 123920.4 | G29: 126027.3 | H29: 123741.5 | I29: 121451.59 | J29: 117052.75 | K29: 122011.23 | L29: 127945.72 | M29: 129426.17 | N29: 130841.79 | O29: 129617.7 | P29: 126456.97 | Q29: 121354.86 | R29: 122781.15 | S29: 126491.68 | T29: 132011.82 | U29: 129362.78 | V29: 128481.16 | W29: 124304.6 | X29: 123236.98 | Y29: 122507.09 | Z29: 121819.86 | AA29: 127141.49 | AB29: 127045.28 | AC29: 130217.62 | AD29: 130254.14 | AE29: 124728.84 | AF29: 119915.17 | AH29: =SUM(AH19:AH28) -> 3761839.5
A30: 主营业务税金及附加 | C30: 923.98 | D30: 968.78 | E30: 1042.54 | F30: 1037.97 | G30: 1085.01 | H30: 990.32 | I30: 991.12 | J30: 995.93 | K30: 1028.05 | L30: 1024.2 | M30: 1056.48 | N30: 997.46 | O30: 1052.09 | P30: 962.62 | Q30: 944.68 | R30: 960.79 | S30: 1008.73 | T30: 1088.09 | U30: 1009.65 | V30: 995.91 | W30: 942.53 | X30: 969.69 | Y30: 998.71 | Z30: 1027.49 | AA30: 991 | AB30: 1022.09 | AC30: 1049.73 | AD30: 1025.21 | AE30: 1056.7 | AF30: 939.44 | AH30: =SUM(C30:AG30) -> 30186.99
A31: 三、主营业务利润（亏损以“-”号填列) | C31: 1470.19 | D31: 13087.99 | E31: 18495.86 | F31: 19204.2 | G31: 23583.48 | H31: 12812.44 | I31: 15212.42 | J31: 20274.52 | K31: 19745.34 | L31: 13279.84 | M31: 16251.03 | N31: 6696.41 | O31: 15453.55 | P31: 6277.05 | Q31: 8905.4 | R31: 9701.19 | S31: 12600.82 | T31: 18023.33 | U31: 9856.97 | V31: 8843.14 | W31: 5659.48 | X31: 10471.92 | Y31: 15203.79 | Z31: 19858.95 | AA31: 9505.82 | AB31: 13889.72 | AC31: 14528.88 | AD31: 11110.85 | AE31: 20978.18 | AF31: 9623.78 | AH31: =AH11-AH29-AH30 -> 400606.46
A32: 1 | B32: 管理人员工资 | C32: 11312.58 | D32: 11312.58 | E32: 11312.58 | F32: 11312.58 | G32: 11312.58 | H32: 11312.58 | I32: 11312.58 | J32: 11312.58 | K32: 11312.58 | L32: 11312.58 | M32: 11312.58 | N32: 11312.58 | O32: 11312.58 | P32: 11312.58 | Q32: 11312.58 | R32: 11312.58 | S32: 11312.58 | T32: 11312.58 | U32: 11312.58 | V32: 11312.58 | W32: 11312.58 | X32: 11312.58 | Y32: 11312.58 | Z32: 11312.58 | AA32: 11312.58 | AB32: 11312.58 | AC32: 11312.58 | AD32: 11312.58 | AE32: 11312.58 | AF32: 11312.58 | AH32: =SUM(C32:AG32) -> 339377.4
A33: 2 | B33: 人事工资 | C33: 703.33 | D33: 703.33 | E33: 703.33 | F33: 703.33 | G33: 703.33 | H33: 703.33 | I33: 703.33 | J33: 703.33 | K33: 703.33 | L33: 703.33 | M33: 703.33 | N33: 703.33 | O33: 703.33 | P33: 703.33 | Q33: 703.33 | R33: 703.33 | S33: 703.33 | T33: 703.33 | U33: 703.33 | V33: 703.33 | W33: 703.33 | X33: 703.33 | Y33: 703.33 | Z33: 703.33 | AA33: 703.33 | AB33: 703.33 | AC33: 703.33 | AD33: 703.33 | AE33: 703.33 | AF33: 703.33 | AH33: =SUM(C33:AG33) -> 21099.9
A34: 3 | B34: 社会保险费 | C34: 1350 | D34: 1350 | E34: 1350 | F34: 1350 | G34: 1350 | H34: 1350 | I34: 1350 | J34: 1350 | K34: 1350 | L34: 1350 | M34: 1350 | N34: 1350 | O34: 1350 | P34: 1350 | Q34: 1350 | R34: 1350 | S34: 1350 | T34: 1350 | U34: 1350 | V34: 1350 | W34: 1350 | X34: 1350 | Y34: 1350 | Z34: 1350 | AA34: 1350 | AB34: 1350 | AC34: 1350 | AD34: 1350 | AE34: 1350 | AF34: 1350 | AH34: =ROUND(SUM(C34:AG34),2) -> 40500
A35: 4 | B35: 意外险 | C35: 29.17 | D35: 29.17 | E35: 29.17 | F35: 29.17 | G35: 29.17 | H35: 29.17 | I35: 29.17 | J35: 29.17 | K35: 29.17 | L35: 29.17 | M35: 29.17 | N35: 29.17 | O35: 29.17 | P35: 29.17 | Q35: 29.17 | R35: 29.17 | S35: 29.17 | T35: 29.17 | U35: 29.17 | V35: 29.17 | W35: 29.17 | X35: 29.17 | Y35: 29.17 | Z35: 29.17 | AA35: 29.17 | AB35: 29.17 | AC35: 29.17 | AD35: 29.17 | AE35: 29.17 | AF35: 29.17 | AH35: =SUM(C35:AG35) -> 875.1
A36: 5 | B36: 雇主险 | C36: 34.17 | D36: 34.17 | E36: 34.17 | F36: 34.17 | G36: 34.17 | H36: 34.17 | I36: 34.17 | J36: 34.17 | K36: 34.17 | L36: 34.17 | M36: 34.17 | N36: 34.17 | O36: 34.17 | P36: 34.17 | Q36: 34.17 | R36: 34.17 | S36: 34.17 | T36: 34.17 | U36: 34.17 | V36: 34.17 | W36: 34.17 | X36: 34.17 | Y36: 34.17 | Z36: 34.17 | AA36: 34.17 | AB36: 34.17 | AC36: 34.17 | AD36: 34.17 | AE36: 34.17 | AF36: 34.17 | AH36: =SUM(C36:AG36) -> 1025.1
A37: 6 | B37: 福利费 | V37: 866.81 | W37: 866.81 | X37: 866.81 | Y37: 866.81 | Z37: 866.81 | AA37: 866.81 | AB37: 866.81 | AC37: 866.81 | AD37: 866.81 | AE37: 866.81 | AH37: =SUM(C37:AG37) -> 8668.1
A38: 7 | B38: 招聘费 | C38: 220 | D38: 220 | E38: 200 | F38: 200 | G38: 160 | H38: 160 | I38: 180 | J38: 160 | K38: 180 | L38: 180 | M38: 160 | N38: 120 | O38: 300 | P38: 300 | Q38: 180 | R38: 200 | S38: 220 | T38: 200 | U38: 260 | V38: 260 | W38: 220 | X38: 220 | Y38: 220 | Z38: 200 | AA38: 200 | AB38: 300 | AC38: 280 | AD38: 280 | AE38: 260 | AF38: 200 | AH38: =SUM(C38:AG38) -> 6440
A39: 8 | B39: 招标代理费 | AH39: =SUM(C39:AG39) -> 0
A40: 9 | B40: 其他 | AH40: =SUM(C40:AG40) -> 0
A41: 10 | B41: 设备维修费 | T41: 600 | AH41: =SUM(C41:AG41) -> 600
A42: 11 | B42: 人员差旅费 | AH42: =SUM(C42:AG42) -> 0
A43: 13
A44: 14
A45: 四、管理费用合计 | C45: =SUM(C32:C44) -> 13649.25 | D45: =SUM(D32:D44) -> 13649.25 | E45: =SUM(E32:E44) -> 13629.25 | F45: =SUM(F32:F44) -> 13629.25 | G45: =SUM(G32:G44) -> 13589.25 | H45: =SUM(H32:H44) -> 13589.25 | I45: =SUM(I32:I44) -> 13609.25 | J45: =SUM(J32:J44) -> 13589.25 | ... AH45: =SUM(AH32:AH44) -> 418585.6
A46: 五、利润总额（亏损总额以“-”号填列） | C46: =ROUND(C31-C45,2) -> -12179.06 | D46: =D31-D45 -> -561.26 | E46: =E31-E45 -> 4866.61 | F46: =F31-F45 -> 5574.95 | G46: =G31-G45 -> 9994.23 | H46: =H31-H45 -> -776.81 | I46: =I31-I45 -> 1603.17 | J46: =J31-J45 -> 6685.27 | K46: =K31-K45 -> 6136.09 | ... AG46: =AG31-AG45 -> 0 | AH46: =ROUND(AH31-AH45,2) -> -17979.14
A47: 六、亏损分析 | D47: 细分五摆轮故障1点50分开始，下午20点修复完成，导致回流加剧折算增投5人次处理 | H47: 内场清理、求是大刊包装灌袋赶发三频影响白班效率 | K47: 邮政集团规范化、巡检组现场检查，内场清理影响处理效率 | L47: 1、集团为无锡分流8辆车到南京接卸，车内异形件过多（案例：新疆乌市车长24米伸缩机伸入不足）影响效率达成； 2、中午停机时待卸车20辆，下午邮政政治任务无着库房清理抽调7人操作装车； 3、为加快处理晚班增加20人投入成本增加； | M47: 1、集团为无锡分流8辆车到南京接卸，车内异形件过多，影响效率达成； 2、邮政要求白班+晚班+中班共计460人配置生产，人员不足会下整改考核单，无法压缩人员投入； | N47: 1、集团为无锡分流8辆车到南京接卸，车内异形件过多，影响效率达成； 2、早上5:30开始小件机出包线3条皮带线故障，一条8点修复，两条12点才修复，导致内场小件积压，同步卸车操作效率下降，一频次8点逾限5.7W、二频次14点逾限9.1W，影响整体效率达成； 3、晚班为尽快清理内场人员增投15人； | O47: 1、集团为无锡分流8辆车到南京接卸，车内异形件过多，影响效率达成； 2、晚班22点40分细分四摆轮远程故障，截止0点40分才修复，强排口分流人工分拣导致粗分效率下降，严重影响效率达成； | P47: 1、集团为无锡分流8辆车到南京接卸，车内异形件过多，影响效率达成； 2、白班19点全场停机进行内场大清理，邮政领导现场督促检查，人员无法提前下班压缩工时； | Q47: 集团为无锡分流8辆车到南京接卸，车内异形件过多，影响效率达成； 下午包装求是大刊影响一小时效率； | R47: 集团为无锡分流8辆车到南京接卸，车内异形件过多，影响效率达成； | S47: 1、集团为无锡分流8辆车到南京接卸，车内异形件过多，影响效率达成； 2、小件机循环线皮带故障8：00-10：30共计2.5小时维修完成，导致小件机效率下降，粗分南京总包线堵住，下午进行补救操作，影响整体效率达成； | T47: 1、集团为无锡分流8辆车到南京接卸，车内异形件过多，影响效率达成； 2、小件机进包循环线11:30一条线电机损坏，17:50分才维修完成，用时5个多小时小件机南京总包操作受限同时导致粗分卸车效率下降，影响整体效率达成； 3、苹果手机首发，配合邮政增投6人处理苹果件卸车驳运赶发二号楼操作； | U47: 1、集团为无锡分流8辆车到南京接卸，车内异形件过多，影响效率达成； 2、设备侧软件升级故障，导致14点-16点30分共计2.5小时无法正常生产影响白班处理效率； 3、新员工补充技能不熟练影响效率； | V47: 1、集团为无锡分流8辆车到南京接卸，车内异形件过多，影响效率达成； 2、求实杂志包装影响1小时效率达成； 3、18点30分全场停机进行大清理，邮政安排人员监督，无法安排部分人员下班缩减上班时长； | W47: 1、集团为无锡分流8辆车到南京接卸，车内异形件过多，影响效率达成； 2、周一集团现场检查，18点30分停机清场影响处理效率； | X47: 1、集团为无锡分流8辆车到南京接卸，车内异形件过多，影响效率达成； 2、为迎接广东参观团，19点停机清场影响效率达成； | AA47: 受台风天气影响，广东路向进局车辆停运，导致25日凌晨夜班小件量对比日常下降3.5万件影响效率 | AB47: 黑龙江大米每天5车无法上矩阵分拣，增开落地窄带细分9进行分拣，每班次增投5人处理，全班次增投10人成本增加 | AC47: 黑龙江大米每天5车无法上矩阵分拣，增开落地窄带细分9进行分拣，每班次增投5人处理，全班次增投10人成本增加，白班下午小件机19点停机协助各区处理异形件清场影响小件处理效率达成 | AD47: 黑龙江大米每天5车无法上矩阵分拣，增开落地窄带细分9进行分拣，每班次增投5人处理，全班次增投10人成本增加，白班下午设备分拣软件故障14点50分-18点50分才恢复正常，严重影响生产进度，少处理5万件 | AF47: 受国庆长假影响，小件量环比下降15.5%影响处理量达成，粗分一12点50分停机检修，16点50分恢复使用，用时4小时，人工应急处理影响处理效率
A48: 注：请注意业务量跳档时单价的变化
X51: 南京项目人效
X52: 部门 | Z52: 南京进口
X53: 日期 | Z53: 45930
X54: 管理人数 | Z54: 21
X55: 自有员工 | Z55: 263
X56: 劳务人员 | Z56: 98
X57: 总人数 | Z57: 382
X58: 散件处理量 | Z58: 847673
X59: 总工时 | Z59: 4102
X60: 人均小时效能 | Z60: 206.64871

Sheet 25年9月处理量
A1: 日 | B1: 新一代查询业务量 （散件外走） | C1: 新一代查询业务量 （分拣封发） | D1: 新一代查询业务量 （总包经转） | E1: 平刷件量(剔除） | F1: 合计
A2: 45901 | B2: 303379 | C2: 592305 | D2: 29012 | E2: 90678 | F2: =SUM(B2:D2)-E2 -> 834018
A3: =A2+1 -> 45902 | B3: 306925 | C3: 599373 | D3: 29756 | E3: 62475 | F3: =SUM(B3:D3)-E3 -> 873579
A4: =A3+1 -> 45903 | B4: 357068 | C4: 595197 | D4: 33109 | E4: 46648 | F4: =SUM(B4:D4)-E4 -> 938726
A5: =A4+1 -> 45904 | B5: 336117 | C5: 645107 | D5: 32836 | E5: 79373 | F5: =SUM(B5:D5)-E5 -> 934687
A6: =A5+1 -> 45905 | B6: 354411 | C6: 665887 | D6: 35067 | E6: 79135 | F6: =SUM(B6:D6)-E6 -> 976230
A7: =A6+1 -> 45906 | B7: 339598 | C7: 736005 | D7: 30962 | E7: 213962 | F7: =SUM(B7:D7)-E7 -> 892603
A8: =A7+1 -> 45907 | B8: 351820 | C8: 667493 | D8: 24173 | E8: 150178 | F8: =SUM(B8:D8)-E8 -> 893308
A9: =A8+1 -> 45908 | B9: 338404 | C9: 606158 | D9: 30582 | E9: 77588 | F9: =SUM(B9:D9)-E9 -> 897556
A10: =A9+1 -> 45909 | B10: 344034 | C10: 607086 | D10: 31925 | E10: 57120 | F10: =SUM(B10:D10)-E10 -> 925925
A11: =A10+1 -> 45910 | B11: 336404 | C11: 613018 | D11: 32364 | E11: 59262 | F11: =SUM(B11:D11)-E11 -> 922524
A12: =A11+1 -> 45911 | B12: 356131 | C12: 657894 | D12: 31378 | E12: 94367 | F12: =SUM(B12:D12)-E12 -> 951036
A13: =A12+1 -> 45912 | B13: 344645 | C13: 604997 | D13: 31256 | E13: 81991 | F13: =SUM(B13:D13)-E13 -> 898907
A14: =A13+1 -> 45913 | B14: 351896 | C14: 770738 | D14: 28368 | E14: 203847 | F14: =SUM(B14:D14)-E14 -> 947155
... A31: =A30+1 -> 45930 | B31: 354583 | C31: 536350 | D31: 31829 | E31: 75089 | F31: =SUM(B31:D31)-E31 -> 847673
A32: =A31+1 -> 45931 | F32: =SUM(B32:D32)-E32 -> 0
A33: 合计 | B33: =SUM(B2:B32) -> 10468262 | C33: =SUM(C2:C32) -> 18821260 | D33: =SUM(D2:D32) -> 933744 | E33: =SUM(E2:E32) -> 3023560 | F33: =SUM(F2:F32) -> 27199706

Sheet 25年10月日经营数据
A1: 2025年南京项目处理经营情况（10月）
A3: 科目 | C3: 45931 | D3: =C3+1 -> 45932 | E3: =D3+1 -> 45933 | F3: =E3+1 -> 45934 | G3: =F3+1 -> 45935 | H3: =G3+1 -> 45936 | I3: =H3+1 -> 45937 | J3: =I3+1 -> 45938 | K3: =J3+1 -> 45939 | ... AG3: =AF3+1 -> 45961 | AH3: 月度合计
C4: 进口处理 | D4: 进口处理 | E4: 进口处理 | F4: 进口处理 | G4: 进口处理 | H4: 进口处理 | I4: 进口处理 | J4: 进口处理 | K4: 进口处理 | L4: 进口处理 | M4: 进口处理 | N4: 进口处理 | O4: 进口处理 | P4: 进口处理 | Q4: 进口处理 | R4: 进口处理 | S4: 进口处理 | T4: 进口处理 | U4: 进口处理 | V4: 进口处理 | W4: 进口处理 | X4: 进口处理 | Y4: 进口处理 | Z4: 进口处理 | AA4: 进口处理 | AB4: 进口处理 | AC4: 进口处理 | AD4: 进口处理 | AE4: 进口处理 | AF4: 进口处理 | AG4: 进口处理 | AH4: 进口处理
A5: 1 | B5: 散件处理量 | C5: =SUMIFS('25年10月处理量'!$F:$F,'25年10月处理量'!$A:$A,C3) -> 772285 | D5: =SUMIFS('25年10月处理量'!$F:$F,'25年10月处理量'!$A:$A,D3) -> 734868 | E5: =SUMIFS('25年10月处理量'!$F:$F,'25年10月处理量'!$A:$A,E3) -> 687613 | F5: =SUMIFS('25年10月处理量'!$F:$F,'25年10月处理量'!$A:$A,F3) -> 691253 | G5: =SUMIFS('25年10月处理量'!$F:$F,'25年10月处理量'!$A:$A,G3) -> 674798 | H5: =SUMIFS('25年10月处理量'!$F:$F,'25年10月处理量'!$A:$A,H3) -> 661851 | I5: =SUMIFS('25年10月处理量'!$F:$F,'25年10月处理量'!$A:$A,I3) -> 623862 | J5: =SUMIFS('25年10月处理量'!$F:$F,'25年10月处理量'!$A:$A,J3) -> 715598 | ... AG5: =SUMIFS('25年10月处理量'!$F:$F,'25年10月处理量'!$A:$A,AG3) -> 973133 | AH5: =SUM(C5:AG5) -> 27278795
A6: 2 | B6: 散件处理单价 | C6: 0.1667 | D6: 0.1667 | E6: 0.1667 | F6: 0.1667 | G6: 0.1667 | H6: 0.1667 | I6: 0.1667 | J6: 0.1667 | K6: 0.1667 | L6: 0.1667 | M6: 0.1667 | N6: 0.1667 | O6: 0.1667 | P6: 0.1667 | Q6: 0.1667 | R6: 0.1667 | S6: 0.1667 | T6: 0.1667 | U6: 0.1667 | V6: 0.1667 | W6: 0.1667 | X6: 0.1667 | Y6: 0.1667 | Z6: 0.1667 | AA6: 0.1667 | AB6: 0.1667 | AC6: 0.1667 | AD6: 0.1667 | AE6: 0.1667 | AF6: 0.1667 | AG6: 0.1667 | AH6: 0.1667
A7: 3 | B7: 散件处理收入 | C7: 128739.91 | D7: 122502.5 | E7: 114625.09 | F7: 115231.88 | G7: 112488.83 | H7: 110330.56 | I7: 103997.8 | J7: 119290.19 | K7: 130999.03 | L7: 142366.63 | M7: 151438.28 | N7: 149281.18 | O7: 151427.78 | P7: 149205.17 | Q7: 157958.42 | R7: 152850.56 | S7: 153382.67 | T7: 153024.43 | U7: 142802.72 | V7: 141164.23 | W7: 159956.15 | X7: 168667.06 | Y7: 180955.85 | Z7: 177036.9 | AA7: 175232.87 | AB7: 159213 | AC7: 158137.79 | AD7: 162369.63 | AE7: 172063.41 | AF7: 168413.34 | AG7: 162221.27 | AH7: =SUM(C7:AG7) -> 4547375.1
A8: 4 | B8: 考核扣款 | C8: 3000 | D8: 3000 | E8: 3000 | F8: 3000 | G8: 3000 | H8: 3000 | I8: 3000 | J8: 3000 | K8: 3000 | L8: 3000 | M8: 3000 | N8: 3000 | O8: 3000 | P8: 3000 | Q8: 3000 | R8: 3000 | S8: 3000 | T8: 3000 | U8: 3000 | V8: 3000 | W8: 3000 | X8: 3000 | Y8: 3000 | Z8: 3000 | AA8: 3000 | AB8: 3000 | AC8: 3000 | AD8: 3000 | AE8: 3000 | AF8: 3000 | AG8: 3000 | AH8: =SUM(C8:AG8) -> 93000
A9: 5 | B9: 补贴费用 | AH9: =SUM(C9:AG9) -> 0
A10: 6 | B10: 开票金额 | C10: 125739.91 | D10: 119502.5 | E10: 111625.09 | F10: 112231.88 | G10: 109488.83 | H10: 107330.56 | I10: 100997.8 | J10: 116290.19 | K10: 127999.03 | L10: 139366.63 | M10: 148438.28 | N10: 146281.18 | O10: 148427.78 | P10: 146205.17 | Q10: 154958.42 | R10: 149850.56 | S10: 150382.67 | T10: 150024.43 | U10: 139802.72 | V10: 138164.23 | W10: 156956.15 | X10: 165667.06 | Y10: 177955.85 | Z10: 174036.9 | AA10: 172232.87 | AB10: 156213 | AC10: 155137.79 | AD10: 159369.63 | AE10: 169063.41 | AF10: 165413.34 | AG10: 159221.27 | AH10: =SUM(C10:AG10) -> 4454375.1
A11: 一、主营业务收入总计 | C11: 118622.56 | D11: 112738.21 | E11: 105306.69 | F11: 105879.13 | G11: 103291.35 | H11: 101255.25 | I11: 95280.94 | J11: 109707.73 | K11: 120753.8 | L11: 131477.95 | M11: 140036.11 | N11: 138001.11 | O11: 140026.21 | P11: 137929.41 | Q11: 146187.19 | R11: 141368.45 | S11: 141870.44 | T11: 141532.48 | U11: 131889.36 | V11: 130343.61 | W11: 148071.84 | X11: 156289.68 | Y11: 167882.88 | Z11: 164185.75 | AA11: 162483.84 | AB11: 147370.75 | AC11: 146356.41 | AD11: 150348.71 | AE11: 159493.78 | AF11: 156050.32 | AG11: 150208.75 | AH11: =SUM(C11:AG11) -> 4202240.7
A12: 1 | B12: 管理人员数量 | C12: 22 | D12: 22 | E12: 23 | F12: 23 | G12: 17 | H12: 18 | I12: 19 | J12: 21 | K12: 20 | L12: 22 | M12: 23 | N12: 21 | O12: 18 | P12: 22 | Q12: 22 | R12: 23 | S12: 22 | T12: 24 | U12: 25 | V12: 25 | W12: 24 | X12: 24 | Y12: 24 | Z12: 22 | AA12: 23 | AB12: 22 | AC12: 22 | AD12: 23 | AE12: 24 | AF12: 24 | AG12: 23 | AH12: =SUM(C12:AG12) -> 687
A13: 2 | B13: 自有员工数量 | C13: 265 | D13: 253 | E13: 261 | F13: 266 | G13: 262 | H13: 246 | I13: 251 | J13: 268 | K13: 272 | L13: 273 | M13: 292 | N13: 283 | O13: 286 | P13: 285 | Q13: 283 | R13: 276 | S13: 294 | T13: 283 | U13: 295 | V13: 294 | W13: 292 | X13: 298 | Y13: 314 | Z13: 303 | AA13: 301 | AB13: 301 | AC13: 299 | AD13: 304 | AE13: 300 | AF13: 287 | AG13: 284 | AH13: =SUM(C13:AG13) -> 8771
A14: 3 | B14: 劳务人员数量 | C14: 92 | D14: 73 | E14: 69 | F14: 67 | G14: 63 | H14: 64 | I14: 60 | J14: 57 | K14: 78 | L14: 88 | M14: 79 | N14: 85 | O14: 86 | P14: 84 | Q14: 90 | R14: 96 | S14: 94 | T14: 92 | U14: 81 | V14: 81 | W14: 87 | X14: 90 | Y14: 101 | Z14: 108 | AA14: 106 | AB14: 84 | AC14: 83 | AD14: 75 | AE14: 86 | AF14: 90 | AG14: 83 | AH14: =SUM(C14:AG14) -> 2572
A15: 4 | B15: 总人数 | C15: 379 | D15: 348 | E15: 353 | F15: 356 | G15: 342 | H15: 328 | I15: 330 | J15: 346 | K15: 370 | L15: 383 | M15: 394 | N15: 389 | O15: 390 | P15: 391 | Q15: 395 | R15: 395 | S15: 410 | T15: 399 | U15: 401 | V15: 400 | W15: 403 | X15: 412 | Y15: 439 | Z15: 433 | AA15: 430 | AB15: 407 | AC15: 404 | AD15: 402 | AE15: 410 | AF15: 401 | AG15: 390 | AH15: =SUM(C15:AG15) -> 12030
A16: 5 | B16: 总工时 | C16: 4101.5 | D16: 3671 | E16: 3653 | F16: 3680 | G16: 3509 | H16: 3407 | I16: 3376.5 | J16: 3520 | K16: 3926 | L16: 4044 | M16: 4158.5 | N16: 4155 | O16: 4135 | P16: 4036.5 | Q16: 4185.5 | R16: 4096.5 | S16: 4271 | T16: 4093.5 | U16: 4093.5 | V16: 4103.5 | W16: 4331 | X16: 4453.5 | Y16: 4757.5 | Z16: 4707 | AA16: 4571.5 | AB16: 4297 | AC16: 4215.5 | AD16: 4241 | AE16: 4432.5 | AF16: 4316 | AG16: 4189 | AH16: =SUM(C16:AG16) -> 126728
A17: 人均效能 | C17: 2037.6913 | D17: 2111.6897 | E17: 1947.9122 | F17: 1941.7219 | G17: 1973.0936 | H17: 2017.8384 | I17: 1890.4909 | J17: 2068.2023 | K17: 2123.8838 | L17: 2229.8407 | M17: 2305.7056 | N17: 2302.0771 | O17: 2329.1923 | P17: 2289.1355 | Q17: 2398.8886 | R17: 2321.3165 | S17: 2244.1756 | T17: 2300.6591 | U17: 2136.2718 | V17: 2117.04 | W17: 2381.005 | X17: 2455.8252 | Y17: 2472.7062 | Z17: 2452.6767 | AA17: 2444.6209 | AB17: 2346.6511 | AC17: 2348.1114 | AD17: 2422.9428 | AE17: 2517.4976 | AF17: 2519.3965 | AG17: 2495.2128 | AH17: =AH5/AH15 -> 2267.564
A18: 人均小时效能 | C18: 188.29331 | D18: 200.18197 | E18: 188.23241 | F18: 187.84049 | G18: 192.30493 | H18: 194.26211 | I18: 184.76588 | J18: 203.29489 | K18: 200.16225 | L18: 211.18422 | M18: 218.45569 | N18: 215.52539 | O18: 219.68198 | P18: 221.73963 | Q18: 226.39135 | R18: 223.8301 | S18: 215.43245 | T18: 224.24893 | U18: 209.26957 | V18: 206.36432 | W18: 221.55276 | X18: 227.1921 | Y18: 228.16984 | Z18: 225.62333 | AA18: 229.94356 | AB18: 222.26833 | AC18: 225.03546 | AD18: 229.66824 | AE18: 232.86497 | AF18: 234.07739 | AG18: 232.30676 | AH18: =AH5/AH16 -> 215.25468
A19: 1 | B19: 自有员工工资 | C19: 55881.8 | D19: 51967.6 | E19: 52576.2 | F19: 53426.15 | G19: 51150.55 | H19: 49100.65 | I19: 49357.35 | J19: 52642.55 | K19: 55543.55 | L19: 55699 | M19: 59622.95 | N19: 58284.45 | O19: 57799.25 | P19: 56445.5 | Q19: 59334.2 | R19: 55678.35 | S19: 58726.4 | T19: 56837.8 | U19: 58682.1 | V19: 58411.15 | W19: 62462.95 | X19: 64352.9 | Y19: 66960.85 | Z19: 64553.25 | AA19: 62509.85 | AB19: 61844.15 | AC19: 60710.2 | AD19: 63040.7 | AE19: 64212.8 | AF19: 61237.55 | AG19: 60438.05 | AH19: =SUM(C19:AG19) -> 1799490.8
A20: 2 | B20: 员工宿舍费 | D20: 26100 | AH20: =SUM(C20:AG20) -> 26100
A21: 3 | B21: 意外险 | C21: 257.64 | D21: 245.97 | E21: 253.75 | F21: 258.61 | G21: 254.72 | H21: 239.17 | I21: 244.03 | J21: 260.56 | K21: 264.44 | L21: 265.42 | M21: 283.89 | N21: 275.14 | O21: 278.06 | P21: 277.08 | Q21: 275.14 | R21: 268.33 | S21: 285.83 | T21: 275.14 | U21: 286.81 | V21: 285.83 | W21: 283.89 | X21: 289.72 | Y21: 305.28 | Z21: 294.58 | AA21: 292.64 | AB21: 292.64 | AC21: 290.69 | AD21: 295.56 | AE21: 291.67 | AF21: 279.03 | AG21: 276.11 | AH21: =SUM(C21:AG21) -> 8527.37
A22: 4 | B22: 雇主险 | C22: 301.81 | D22: 288.14 | E22: 297.25 | F22: 302.94 | G22: 298.39 | H22: 280.17 | I22: 285.86 | J22: 305.22 | K22: 309.78 | L22: 310.92 | M22: 332.56 | N22: 322.31 | O22: 325.72 | P22: 324.58 | Q22: 322.31 | R22: 314.33 | S22: 334.83 | T22: 322.31 | U22: 335.97 | V22: 334.83 | W22: 332.56 | X22: 339.39 | Y22: 357.61 | Z22: 345.08 | AA22: 342.81 | AB22: 342.81 | AC22: 340.53 | AD22: 346.22 | AE22: 341.67 | AF22: 326.86 | AG22: 323.44 | AH22: =SUM(C22:AG22) -> 9989.21
A23: 5 | B23: 员工餐费 | C23: 2320 | D23: 2224 | E23: 2296 | F23: 2336 | G23: 2256 | H23: 2136 | I23: 2184 | J23: 2336 | K23: 2360 | L23: 2384 | M23: 2544 | N23: 2456 | O23: 2456 | P23: 2480 | Q23: 2464 | R23: 2416 | S23: 2552 | T23: 2480 | U23: 2584 | V23: 2576 | W23: 2552 | X23: 2600 | Y23: 2728 | Z23: 2624 | AA23: 2616 | AB23: 2608 | AC23: 2592 | AD23: 2640 | AE23: 2616 | AF23: 2512 | AG23: 2480 | AH23: =SUM(C23:AG23) -> 76408
A24: 6 | B24: 高温福利费用 | AH24: =SUM(C24:AG24) -> 0
A25: 7 | B25: 劳务人员工资 | C25: 24196 | D25: 19308.5 | E25: 18250.5 | F25: 17721.5 | G25: 16663.5 | H25: 16928 | I25: 15870 | J25: 15076.5 | K25: 20631 | L25: 23218.5 | M25: 20838 | N25: 22390.5 | O25: 22666.5 | P25: 22149 | Q25: 23724.5 | R25: 25300 | S25: 24771 | T25: 24253.5 | U25: 21367 | V25: 21355.5 | W25: 22919.5 | X25: 23713 | Y25: 26576.5 | Z25: 28428 | AA25: 27933.5 | AB25: 22126 | AC25: 21896 | AD25: 19768.5 | AE25: 22632 | AF25: 23724.5 | AG25: 21827 | AH25: =SUM(C25:AG25) -> 678224
A26: 8 | B26: 物料采购 | E26: 15552 | F26: 69000 | AH26: =SUM(C26:AG26) -> 84552
A27: 9 | B27: 工单赔付 | C27: 1935.48 | D27: 1935.48 | E27: 1935.48 | F27: 1935.48 | G27: 1935.48 | H27: 1935.48 | I27: 1935.48 | J27: 1935.48 | K27: 1935.48 | L27: 1935.48 | M27: 1935.48 | N27: 1935.48 | O27: 1935.48 | P27: 1935.48 | Q27: 1935.48 | R27: 1935.48 | S27: 1935.48 | T27: 1935.48 | U27: 1935.48 | V27: 1935.48 | W27: 1935.48 | X27: 1935.48 | Y27: 1935.48 | Z27: 1935.48 | AA27: 1935.48 | AB27: 1935.48 | AC27: 1935.48 | AD27: 1935.48 | AE27: 1935.48 | AF27: 1935.48 | AG27: 1935.48 | AH27: =SUM(C27:AG27) -> 59999.88
A28: 10 | B28: 设备成本摊销 | C28: 33651.837 | D28: 33651.837 | E28: 33651.837 | F28: 33651.837 | G28: 33651.837 | H28: 33651.837 | I28: 33651.837 | J28: 33651.837 | K28: 33651.837 | L28: 33651.837 | M28: 33651.837 | N28: 33651.837 | O28: 33651.837 | P28: 33651.837 | Q28: 33651.837 | R28: 33651.837 | S28: 33651.837 | T28: 33651.837 | U28: 33651.837 | V28: 33651.837 | W28: 33651.837 | X28: 33651.837 | Y28: 33651.837 | Z28: 33651.837 | AA28: 33651.837 | AB28: 33651.837 | AC28: 33651.837 | AD28: 33651.837 | AE28: 33651.837 | AF28: 33651.837 | AG28: 33651.837 | AH28: =SUM(C28:AG28) -> 1043207
A29: 二、主营业务成本总计 | C29: 118544.57 | D29: 135721.53 | E29: 124813.02 | F29: 178632.52 | G29: 106210.48 | H29: 104271.31 | I29: 103528.56 | J29: 106208.15 | K29: 114696.09 | L29: 117465.16 | M29: 119208.72 | N29: 119315.72 | O29: 119112.85 | P29: 117263.48 | Q29: 121707.47 | R29: 119564.33 | S29: 122257.38 | T29: 119756.07 | U29: 118843.2 | V29: 118550.63 | W29: 124138.22 | X29: 126882.33 | Y29: 132515.56 | Z29: 131832.23 | AA29: 129282.12 | AB29: 122800.92 | AC29: 121416.74 | AD29: 121678.3 | AE29: 125681.46 | AF29: 123667.26 | AG29: 120931.92 | AH29: =SUM(AH19:AH28) -> 3786498.2
A30: 主营业务税金及附加 | C30: 854.08 | D30: 811.72 | E30: 758.21 | F30: 762.33 | G30: 743.7 | H30: 729.04 | I30: 686.02 | J30: 789.9 | K30: 869.43 | L30: 946.64 | M30: 1008.26 | N30: 993.61 | O30: 1008.19 | P30: 993.09 | Q30: 1052.55 | R30: 1017.85 | S30: 1021.47 | T30: 1019.03 | U30: 949.6 | V30: 938.47 | W30: 1066.12 | X30: 1125.29 | Y30: 1208.76 | Z30: 1182.14 | AA30: 1169.88 | AB30: 1061.07 | AC30: 1053.77 | AD30: 1082.51 | AE30: 1148.36 | AF30: 1123.56 | AG30: 1081.5 | AH30: =SUM(C30:AG30) -> 30256.15
A31: 三、主营业务利润（亏损以“-”号填列) | C31: -776.09 | D31: -23795.04 | E31: -20264.54 | F31: -73515.72 | G31: -3662.83 | H31: -3745.1 | I31: -8933.64 | J31: 2709.68 | K31: 5188.28 | L31: 13066.15 | M31: 19819.13 | N31: 17691.78 | O31: 19905.17 | P31: 19672.84 | Q31: 23427.17 | R31: 20786.27 | S31: 18591.59 | T31: 20757.38 | U31: 12096.56 | V31: 10854.51 | W31: 22867.5 | X31: 28282.06 | Y31: 34158.56 | Z31: 31171.38 | AA31: 32031.84 | AB31: 23508.76 | AC31: 23885.9 | AD31: 27587.9 | AE31: 32663.96 | AF31: 31259.5 | AG31: 28195.33 | AH31: =AH11-AH29-AH30 -> 385486.32
A32: 1 | B32: 管理人员工资 | C32: 10947.66 | D32: 10947.66 | E32: 10947.66 | F32: 10947.66 | G32: 10947.66 | H32: 10947.66 | I32: 10947.66 | J32: 10947.66 | K32: 10947.66 | L32: 10947.66 | M32: 10947.66 | N32: 10947.66 | O32: 10947.66 | P32: 10947.66 | Q32: 10947.66 | R32: 10947.66 | S32: 10947.66 | T32: 10947.66 | U32: 10947.66 | V32: 10947.66 | W32: 10947.66 | X32: 10947.66 | Y32: 10947.66 | Z32: 10947.66 | AA32: 10947.66 | AB32: 10947.66 | AC32: 10947.66 | AD32: 10947.66 | AE32: 10947.66 | AF32: 10947.66 | AG32: 10947.66 | AH32: =SUM(C32:AG32) -> 339377.46
A33: 2 | B33: 人事工资 | C33: 680.65 | D33: 680.65 | E33: 680.65 | F33: 680.65 | G33: 680.65 | H33: 680.65 | I33: 680.65 | J33: 680.65 | K33: 680.65 | L33: 680.65 | M33: 680.65 | N33: 680.65 | O33: 680.65 | P33: 680.65 | Q33: 680.65 | R33: 680.65 | S33: 680.65 | T33: 680.65 | U33: 680.65 | V33: 680.65 | W33: 680.65 | X33: 680.65 | Y33: 680.65 | Z33: 680.65 | AA33: 680.65 | AB33: 680.65 | AC33: 680.65 | AD33: 680.65 | AE33: 680.65 | AF33: 680.65 | AG33: 680.65 | AH33: =SUM(C33:AG33) -> 21100.15
A34: 3 | B34: 社会保险费 | C34: 1306.4516 | D34: 1306.4516 | E34: 1306.4516 | F34: 1306.4516 | G34: 1306.4516 | H34: 1306.4516 | I34: 1306.4516 | J34: 1306.4516 | K34: 1306.4516 | L34: 1306.4516 | M34: 1306.4516 | N34: 1306.4516 | O34: 1306.4516 | P34: 1306.4516 | Q34: 1306.4516 | R34: 1306.4516 | S34: 1306.4516 | T34: 1306.4516 | U34: 1306.4516 | V34: 1306.4516 | W34: 1306.4516 | X34: 1306.4516 | Y34: 1306.4516 | Z34: 1306.4516 | AA34: 1306.4516 | AB34: 1306.4516 | AC34: 1306.4516 | AD34: 1306.4516 | AE34: 1306.4516 | AF34: 1306.4516 | AG34: 1306.4516 | AH34: =ROUND(SUM(C34:AG34),2) -> 40500
A35: 4 | B35: 意外险 | C35: 29.17 | D35: 29.17 | E35: 29.17 | F35: 29.17 | G35: 29.17 | H35: 29.17 | I35: 29.17 | J35: 29.17 | K35: 29.17 | L35: 29.17 | M35: 29.17 | N35: 29.17 | O35: 29.17 | P35: 29.17 | Q35: 29.17 | R35: 29.17 | S35: 29.17 | T35: 29.17 | U35: 29.17 | V35: 29.17 | W35: 29.17 | X35: 29.17 | Y35: 29.17 | Z35: 29.17 | AA35: 29.17 | AB35: 29.17 | AC35: 29.17 | AD35: 29.17 | AE35: 29.17 | AF35: 29.17 | AG35: 29.17 | AH35: =SUM(C35:AG35) -> 904.27
A36: 5 | B36: 雇主险 | C36: 34.17 | D36: 34.17 | E36: 34.17 | F36: 34.17 | G36: 34.17 | H36: 34.17 | I36: 34.17 | J36: 34.17 | K36: 34.17 | L36: 34.17 | M36: 34.17 | N36: 34.17 | O36: 34.17 | P36: 34.17 | Q36: 34.17 | R36: 34.17 | S36: 34.17 | T36: 34.17 | U36: 34.17 | V36: 34.17 | W36: 34.17 | X36: 34.17 | Y36: 34.17 | Z36: 34.17 | AA36: 34.17 | AB36: 34.17 | AC36: 34.17 | AD36: 34.17 | AE36: 34.17 | AF36: 34.17 | AG36: 34.17 | AH36: =SUM(C36:AG36) -> 1059.27
A37: 6 | B37: 福利费 | AH37: =SUM(C37:AG37) -> 0
A38: 7 | B38: 招聘费 | C38: 200 | D38: 180 | E38: 220 | F38: 220 | G38: 240 | H38: 240 | I38: 160 | J38: 220 | K38: 280 | L38: 300 | M38: 340 | N38: 300 | O38: 280 | P38: 340 | Q38: 420 | R38: 340 | S38: 520 | T38: 410 | U38: 440 | V38: 480 | W38: 360 | X38: 460 | Y38: 540 | Z38: 560 | AA38: 420 | AB38: 480 | AC38: 500 | AD38: 480 | AE38: 480 | AF38: 400 | AG38: 400 | AH38: =SUM(C38:AG38) -> 11210
A39: 8 | B39: 招标代理费 | AH39: =SUM(C39:AG39) -> 0
A40: 9 | B40: 其他 | C40: 19500 | D40: 1135.42 | X40: 534.5 | AH40: =SUM(C40:AG40) -> 21169.92
A41: 10 | B41: 设备维修费 | D41: 4060 | AH41: =SUM(C41:AG41) -> 4060
A42: 11 | B42: 人员差旅费 | AH42: =SUM(C42:AG42) -> 0
A43: 13
A44: 14
A45: 四、管理费用合计 | C45: =SUM(C32:C44) -> 32698.102 | D45: =SUM(D32:D44) -> 18373.522 | E45: =SUM(E32:E44) -> 13218.102 | F45: =SUM(F32:F44) -> 13218.102 | G45: =SUM(G32:G44) -> 13238.102 | H45: =SUM(H32:H44) -> 13238.102 | I45: =SUM(I32:I44) -> 13158.102 | J45: =SUM(J32:J44) -> 13218.102 | ... AD45: =SUM(AD32:AD44) -> 13478.102 | AE45: 13478.102 | AF45: =SUM(AF32:AF44) -> 13398.102 | AG45: =SUM(AG32:AG44) -> 13398.102 | AH45: =SUM(AH32:AH44) -> 439381.07
A46: 五、利润总额（亏损总额以“-”号填列） | C46: =ROUND(C31-C45,2) -> -33474.19 | D46: =D31-D45 -> -42168.562 | E46: =E31-E45 -> -33482.642 | F46: =F31-F45 -> -86733.822 | G46: =G31-G45 -> -16900.932 | H46: =H31-H45 -> -16983.202 | I46: =I31-I45 -> -22091.742 | J46: =J31-J45 -> -10508.422 | K46: =K31-K45 -> -8089.8216 | ... AG46: =AG31-AG45 -> 14797.228 | AH46: =ROUND(AH31-AH45,2) -> -53894.75
A47: 六、亏损分析 | C47: 受国庆假期影响，高速堵车车辆到达晚点，车载小件量下降影响处理效率，2号开始对人员进一步压缩降低亏损； 食堂3季度卫生保洁费用支付； | F47: 细分五滚筒损坏3点停线维修用时2.5小时，临时开启细分九窄带机处理五区快件赶发； | U47: 白班下午车次下降，处理量环比前日下降4.5万袋件，为赶发二干三频次无法在18点前进行人员收缩，处理量下降影响效率达成 | V47: 白班下午为赶发二干三频次无法在18点前进行人员收缩，同时求是杂志包装、处理量下降影响效率达成 | Z47: 小件机中午13点开始下层线100多个小车故障未修复，等待软件工程师到现场处理，修复时间待定 | AA47: 康奋威工程师下午16点到达现场，23点基本恢复使用，剩余几个待修的26日中午停机时间再处理
A48: 注：请注意业务量跳档时单价的变化
AB50: 南京项目人效
AB51: 部门 | AD51: 南京进口
AB52: 日期 | AD52: 45961
AB53: 管理人数 | AD53: 23
AB54: 自有员工 | AD54: 284
AB55: 劳务人员 | AD55: 83
AB56: 总人数 | AD56: 390
AB57: 散件处理量 | AD57: 973133
AB58: 总工时 | AD58: 4189
AB59: 人均小时效能 | AD59: 232.30676

Sheet 25年10月处理量
A1: 日 | B1: 新一代查询业务量 （散件外走） | C1: 新一代查询业务量 （分拣封发） | D1: 新一代查询业务量 （总包经转） | E1: 平刷件量(剔除） | F1: 合计
A2: 45931 | B2: 309441 | C2: 497649 | D2: 25885 | E2: 60690 | F2: =SUM(B2:D2)-E2 -> 772285
A3: =A2+1 -> 45932 | B3: 301206 | C3: 456701 | D3: 21824 | E3: 44863 | F3: =SUM(B3:D3)-E3 -> 734868
A4: =A3+1 -> 45933 | B4: 283644 | C4: 417045 | D4: 21315 | E4: 34391 | F4: =SUM(B4:D4)-E4 -> 687613
A5: =A4+1 -> 45934 | B5: 277536 | C5: 525677 | D5: 19773 | E5: 131733 | F5: =SUM(B5:D5)-E5 -> 691253
A6: =A5+1 -> 45935 | B6: 263347 | C6: 485457 | D6: 18933 | E6: 92939 | F6: =SUM(B6:D6)-E6 -> 674798
A7: =A6+1 -> 45936 | B7: 253920 | C7: 413029 | D7: 19297 | E7: 24395 | F7: =SUM(B7:D7)-E7 -> 661851
A8: =A7+1 -> 45937 | B8: 245630 | C8: 391136 | D8: 21130 | E8: 34034 | F8: =SUM(B8:D8)-E8 -> 623862
A9: =A8+1 -> 45938 | B9: 285295 | C9: 426596 | D9: 21676 | E9: 17969 | F9: =SUM(B9:D9)-E9 -> 715598
A10: =A9+1 -> 45939 | B10: 304168 | C10: 479039 | D10: 27382 | E10: 24752 | F10: =SUM(B10:D10)-E10 -> 785837
A11: =A10+1 -> 45940 | B11: 329484 | C11: 551571 | D11: 34021 | E11: 61047 | F11: =SUM(B11:D11)-E11 -> 854029
A12: =A11+1 -> 45941 | B12: 361460 | C12: 693595 | D12: 29156 | E12: 175763 | F12: =SUM(B12:D12)-E12 -> 908448
A13: =A12+1 -> 45942 | B13: 344457 | C13: 655668 | D13: 25569 | E13: 130186 | F13: =SUM(B13:D13)-E13 -> 895508
A14: =A13+1 -> 45943 | B14: 351272 | C14: 657966 | D14: 30761 | E14: 131614 | F14: =SUM(B14:D14)-E14 -> 908385
... A32: =A31+1 -> 45961 | B32: 399192 | C32: 611959 | D32: 35762 | E32: 73780 | F32: =SUM(B32:D32)-E32 -> 973133
A33: 合计 | B33: =SUM(B2:B32) -> 10789465 | C33: =SUM(C2:C32) -> 18120641 | D33: =SUM(D2:D32) -> 924063 | E33: =SUM(E2:E32) -> 2555374 | F33: =SUM(F2:F32) -> 27278795

Sheet 25年11月日经营数据
A1: 2025年南京项目处理经营情况（11月）
A3: 科目 | C3: 45962 | D3: =C3+1 -> 45963 | E3: =D3+1 -> 45964 | F3: =E3+1 -> 45965 | G3: =F3+1 -> 45966 | H3: =G3+1 -> 45967 | I3: =H3+1 -> 45968 | J3: =I3+1 -> 45969 | K3: =J3+1 -> 45970 | ... AG3: =AF3+1 -> 45992 | AH3: 月度合计
C4: 进口处理 | D4: 进口处理 | E4: 进口处理 | F4: 进口处理 | G4: 进口处理 | H4: 进口处理 | I4: 进口处理 | J4: 进口处理 | K4: 进口处理 | L4: 进口处理 | M4: 进口处理 | N4: 进口处理 | O4: 进口处理 | P4: 进口处理 | Q4: 进口处理 | R4: 进口处理 | S4: 进口处理 | T4: 进口处理 | U4: 进口处理 | V4: 进口处理 | W4: 进口处理 | X4: 进口处理 | Y4: 进口处理 | Z4: 进口处理 | AA4: 进口处理 | AB4: 进口处理 | AC4: 进口处理 | AD4: 进口处理 | AE4: 进口处理 | AF4: 进口处理 | AG4: 进口处理 | AH4: 进口处理
A5: 1 | B5: 散件处理量 | C5: =SUMIFS('25年11月处理量'!$F:$F,'25年11月处理量'!$A:$A,C3) -> 940289 | D5: =SUMIFS('25年11月处理量'!$F:$F,'25年11月处理量'!$A:$A,D3) -> 989117 | E5: =SUMIFS('25年11月处理量'!$F:$F,'25年11月处理量'!$A:$A,E3) -> 930157 | F5: =SUMIFS('25年11月处理量'!$F:$F,'25年11月处理量'!$A:$A,F3) -> 967438 | G5: =SUMIFS('25年11月处理量'!$F:$F,'25年11月处理量'!$A:$A,G3) -> 985855 | H5: =SUMIFS('25年11月处理量'!$F:$F,'25年11月处理量'!$A:$A,H3) -> 1003059 | I5: =SUMIFS('25年11月处理量'!$F:$F,'25年11月处理量'!$A:$A,I3) -> 987677 | J5: =SUMIFS('25年11月处理量'!$F:$F,'25年11月处理量'!$A:$A,J3) -> 965339 | ... AG5: =SUMIFS('25年11月处理量'!$F:$F,'25年11月处理量'!$A:$A,AG3) -> 0 | AH5: =SUM(C5:AG5) -> 28966016
A6: 2 | B6: 散件处理单价 | C6: 0.1667 | D6: 0.1667 | E6: 0.1667 | F6: 0.1667 | G6: 0.1667 | H6: 0.1667 | I6: 0.1667 | J6: 0.1667 | K6: 0.1667 | L6: 0.1667 | M6: 0.1667 | N6: 0.1667 | O6: 0.1667 | P6: 0.1667 | Q6: 0.1667 | R6: 0.1667 | S6: 0.1667 | T6: 0.1667 | U6: 0.1667 | V6: 0.1667 | W6: 0.1667 | X6: 0.1667 | Y6: 0.1667 | Z6: 0.1667 | AA6: 0.1667 | AB6: 0.1667 | AC6: 0.1667 | AD6: 0.1667 | AE6: 0.1667 | AF6: 0.1667 | AH6: 0.1667
A7: 3 | B7: 散件处理收入 | C7: 156746.18 | D7: 164885.8 | E7: 155057.17 | F7: 161271.91 | G7: 164342.03 | H7: 167209.94 | I7: 164645.76 | J7: 160922.01 | K7: 152665.36 | L7: 161669.83 | M7: 160149.19 | N7: 176065.87 | O7: 175419.74 | P7: 176781.68 | Q7: 161287.92 | R7: 150433.25 | S7: 146336.09 | T7: 152610.02 | U7: 164920.81 | V7: 169371.87 | W7: 166423.11 | X7: 165744.31 | Y7: 153560.71 | Z7: 148170.96 | AA7: 157396.97 | AB7: 159234.67 | AC7: 161594.98 | AD7: 163408.34 | AE7: 159114.82 | AF7: 151193.57 | AH7: =SUM(C7:AG7) -> 4828634.9
A8: 4 | B8: 考核扣款 | C8: 3000 | D8: 3000 | E8: 3000 | F8: 3000 | G8: 3000 | H8: 3000 | I8: 3000 | J8: 3000 | K8: 3000 | L8: 3000 | M8: 3000 | N8: 3000 | O8: 3000 | P8: 3000 | Q8: 3000 | R8: 3000 | S8: 3000 | T8: 3000 | U8: 3000 | V8: 3000 | W8: 3000 | X8: 3000 | Y8: 3000 | Z8: 3000 | AA8: 3000 | AB8: 3000 | AC8: 3000 | AD8: 3000 | AE8: 3000 | AF8: 3000 | AH8: =SUM(C8:AG8) -> 90000
A9: 5 | B9: 补贴费用 | AH9: =SUM(C9:AG9) -> 0
A10: 6 | B10: 开票金额 | C10: 153746.18 | D10: 161885.8 | E10: 152057.17 | F10: 158271.91 | G10: 161342.03 | H10: 164209.94 | I10: 161645.76 | J10: 157922.01 | K10: 149665.36 | L10: 158669.83 | M10: 157149.19 | N10: 173065.87 | O10: 172419.74 | P10: 173781.68 | Q10: 158287.92 | R10: 147433.25 | S10: 143336.09 | T10: 149610.02 | U10: 161920.81 | V10: 166371.87 | W10: 163423.11 | X10: 162744.31 | Y10: 150560.71 | Z10: 145170.96 | AA10: 154396.97 | AB10: 156234.67 | AC10: 158594.98 | AD10: 160408.34 | AE10: 156114.82 | AF10: 148193.57 | AH10: =SUM(C10:AG10) -> 4738634.9
A11: 一、主营业务收入总计 | C11: 145043.57 | D11: 152722.45 | E11: 143450.16 | F11: 149313.12 | G11: 152209.46 | H11: 154915.04 | I11: 152496 | J11: 148983.03 | K11: 141193.74 | L11: 149688.52 | M11: 148253.95 | N11: 163269.69 | O11: 162660.13 | P11: 163944.98 | Q11: 149328.23 | R11: 139087.97 | S11: 135222.73 | T11: 141141.53 | U11: 152755.48 | V11: 156954.59 | W11: 154172.75 | X11: 153532.37 | Y11: 142038.41 | Z11: 136953.74 | AA11: 145657.52 | AB11: 147391.2 | AC11: 149617.91 | AD11: 151328.62 | AE11: 147278.13 | AF11: 139805.25 | AH11: =SUM(C11:AG11) -> 4470410.3
A12: 1 | B12: 管理人员数量 | C12: 25 | D12: 24 | E12: 23 | F12: 23 | G12: 24 | H12: 22 | I12: 25 | J12: 22 | K12: 22 | L12: 22 | M12: 23 | N12: 24 | O12: 24 | P12: 22 | Q12: 24 | R12: 24 | S12: 20 | T12: 21 | U12: 21 | V12: 21 | W12: 21 | X12: 21 | Y12: 23 | Z12: 20 | AA12: 22 | AB12: 18 | AC12: 24 | AD12: 24 | AE12: 22 | AF12: 24 | AH12: =SUM(C12:AG12) -> 675
A13: 2 | B13: 自有员工数量 | C13: 292 | D13: 288 | E13: 296 | F13: 295 | G13: 289 | H13: 295 | I13: 290 | J13: 293 | K13: 297 | L13: 298 | M13: 302 | N13: 301 | O13: 292 | P13: 299 | Q13: 295 | R13: 291 | S13: 291 | T13: 300 | U13: 297 | V13: 298 | W13: 300 | X13: 296 | Y13: 296 | Z13: 300 | AA13: 314 | AB13: 310 | AC13: 312 | AD13: 311 | AE13: 305 | AF13: 298 | AH13: =SUM(C13:AG13) -> 8941
A14: 3 | B14: 劳务人员数量 | C14: 96 | D14: 101 | E14: 94 | F14: 95 | G14: 101 | H14: 95 | I14: 95 | J14: 100 | K14: 94 | L14: 96 | M14: 88 | N14: 103 | O14: 110 | P14: 103 | Q14: 95 | R14: 83 | S14: 81 | T14: 84 | U14: 86 | V14: 86 | W14: 88 | X14: 84 | Y14: 78 | Z14: 75 | AA14: 71 | AB14: 67 | AC14: 69 | AD14: 68 | AE14: 70 | AF14: 69 | AH14: =SUM(C14:AG14) -> 2625
A15: 4 | B15: 总人数 | C15: 413 | D15: 413 | E15: 413 | F15: 413 | G15: 414 | H15: 412 | I15: 410 | J15: 415 | K15: 413 | L15: 416 | M15: 413 | N15: 428 | O15: 426 | P15: 424 | Q15: 414 | R15: 398 | S15: 392 | T15: 405 | U15: 404 | V15: 405 | W15: 409 | X15: 401 | Y15: 397 | Z15: 395 | AA15: 407 | AB15: 395 | AC15: 405 | AD15: 403 | AE15: 397 | AF15: 391 | AH15: =SUM(C15:AG15) -> 12241
A16: 5 | B16: 总工时 | C16: 4281 | D16: 4322 | E16: 4304 | F16: 4336 | G16: 4308.5 | H16: 4369 | I16: 4364.5 | J16: 4381.5 | K16: 4351 | L16: 4375 | M16: 4321 | N16: 4547 | O16: 4506.5 | P16: 4588.5 | Q16: 4293 | R16: 4005 | S16: 4036.5 | T16: 4309 | U16: 4313.5 | V16: 4482.5 | W16: 4448.5 | X16: 4241.5 | Y16: 4089.5 | Z16: 4102 | AA16: 4253.5 | AB16: 4172.5 | AC16: 4263.5 | AD16: 4202 | AE16: 4142 | AF16: 3998.5 | AH16: =SUM(C16:AG16) -> 128708.5
A17: 人均效能 | C17: 2276.7288 | D17: 2394.9564 | E17: 2252.1961 | F17: 2342.4649 | G17: 2381.2923 | H17: 2434.6092 | I17: 2408.9683 | J17: 2326.1181 | K17: 2217.4552 | L17: 2331.3101 | M17: 2326.1574 | N17: 2467.7196 | O17: 2470.2066 | P17: 2501.1274 | Q17: 2337.0386 | R17: 2267.3844 | S17: 2239.3903 | T17: 2260.437 | U17: 2448.8292 | V17: 2508.7111 | W17: 2440.9267 | X17: 2479.4688 | Y17: 2320.3526 | Z17: 2250.2481 | AA17: 2319.8845 | AB17: 2418.2709 | AC17: 2393.521 | AD17: 2432.3921 | AE17: 2404.2771 | AF17: 2319.6419 | AH17: =AH5/AH15 -> 2366.3112
A18: 人均小时效能 | C18: 219.64237 | D18: 228.85632 | E18: 216.11454 | F18: 223.11762 | G18: 228.81629 | H18: 229.58549 | I18: 226.29786 | J18: 220.32158 | K18: 210.48242 | L18: 221.67429 | M18: 222.33349 | N18: 232.2815 | O18: 233.50893 | P18: 231.11649 | Q18: 225.3748 | R18: 225.3231 | S18: 217.47578 | T18: 212.45695 | U18: 229.35598 | V18: 226.66548 | W18: 224.42149 | X18: 234.414 | Y18: 225.25492 | Z18: 216.68649 | AA18: 221.98025 | AB18: 228.93158 | AC18: 227.36625 | AD18: 233.28272 | AE18: 230.44375 | AF18: 226.83006 | AH18: =AH5/AH16 -> 225.05131
A19: 件均成本 | C19: 0.090101448 | D19: 0.086470205 | E19: 0.090290618 | F19: 0.087997836 | G19: 0.086610708 | H19: 0.086187652 | I19: 0.087447009 | J19: 0.090152268 | K19: 0.093642342 | L19: 0.089445828 | M19: 0.088797578 | N19: 0.08548662 | O19: 0.085342124 | P19: 0.085772076 | Q19: 0.088021403 | R19: 0.087853868 | S19: 0.090701619 | T19: 0.091712954 | U19: 0.086033031 | V19: 0.086800462 | W19: 0.087812356 | X19: 0.084209573 | Y19: 0.087635316 | Z19: 0.090204624 | AA19: 0.088104868 | AB19: 0.08533014 | AC19: 0.085777345 | AD19: 0.084306721 | AE19: 0.085533967 | AF19: 0.087090675 | AH19: =(AH20+AH26)/AH5 -> 0.087627651
A20: 1 | B20: 自有员工工资 | C20: 59501.9 | D20: 58941.15 | E20: 59282.45 | F20: 60165.95 | G20: 58820.6 | H20: 61438.8 | I20: 61333.9 | J20: 60658 | K20: 60999 | L20: 61458.3 | M20: 62101.1 | N20: 63149.6 | O20: 60860.7 | P20: 63830.9 | Q20: 60151.2 | R20: 57396.5 | S20: 58266.1 | T20: 61800.6 | U20: 62436.8 | V20: 65548.2 | W20: 64517 | X20: 61635.3 | Y20: 60188.9 | Z20: 60409.7 | AA20: 64489 | AB20: 63856.3 | AC20: 64969 | AD20: 64725 | AE20: 63184.5 | AF20: 60808 | AH20: =SUM(C20:AG20) -> 1846924.4
A21: 2 | B21: 员工宿舍费 | AH21: =SUM(C21:AG21) -> 0
A22: 3 | B22: 意外险 | C22: 370 | D22: 370 | E22: 370 | F22: 370 | G22: 370 | H22: 370 | I22: 370 | J22: 370 | K22: 370 | L22: 370 | M22: 370 | N22: 370 | O22: 370 | P22: 370 | Q22: 370 | R22: 370 | S22: 370 | T22: 370 | U22: 370 | V22: 370 | W22: 370 | X22: 370 | Y22: 370 | Z22: 370 | AA22: 370 | AB22: 370 | AC22: 370 | AD22: 370 | AE22: 370 | AF22: 370 | AH22: =SUM(C22:AG22) -> 11100
A23: 4 | B23: 雇主险 | C23: 555 | D23: 555 | E23: 555 | F23: 555 | G23: 555 | H23: 555 | I23: 555 | J23: 555 | K23: 555 | L23: 555 | M23: 555 | N23: 555 | O23: 555 | P23: 555 | Q23: 555 | R23: 555 | S23: 555 | T23: 555 | U23: 555 | V23: 555 | W23: 555 | X23: 555 | Y23: 555 | Z23: 555 | AA23: 555 | AB23: 555 | AC23: 555 | AD23: 555 | AE23: 555 | AF23: 555 | AH23: =SUM(C23:AG23) -> 16650
A24: 5 | B24: 员工餐费 | C24: 2776 | D24: 2736 | E24: 2792 | F24: 2784 | G24: 2744 | H24: 2776 | I24: 2760 | J24: 2760 | K24: 2792 | L24: 2800 | M24: 2840 | N24: 2840 | O24: 2768 | P24: 2808 | Q24: 2792 | R24: 2760 | S24: 2728 | T24: 2808 | U24: 2784 | V24: 2792 | W24: 2808 | X24: 2776 | Y24: 2792 | Z24: 2800 | AA24: 2928 | AB24: 2864 | AC24: 2928 | AD24: 2920 | AE24: 2856 | AF24: 2816 | AH24: =SUM(C24:AG24) -> 84128
A25: 6 | B25: 高温福利费用 | AH25: =SUM(C25:AG25) -> 0
A26: 7 | B26: 劳务人员工资 | C26: 25219.5 | D26: 26588 | E26: 24702 | F26: 24966.5 | G26: 26565 | H26: 25012.5 | I26: 25035.5 | J26: 26369.5 | K26: 24759.5 | L26: 25288.5 | M26: 23207 | N26: 27140 | O26: 28945.5 | P26: 27128.5 | Q26: 25012.5 | R26: 21884.5 | S26: 21355.5 | T26: 22160.5 | U26: 22678 | V26: 22643.5 | W26: 23149.5 | X26: 22091.5 | Y26: 20539 | Z26: 19768.5 | AA26: 18699 | AB26: 17652.5 | AC26: 18181.5 | AD26: 17917 | AE26: 18457.5 | AF26: 18181.5 | AH26: =SUM(C26:AG26) -> 691299.5
A27: 8 | B27: 物料采购 | E27: 3699.8 | F27: 3699.8 | G27: 3699.8 | H27: 3699.8 | I27: 3699.8 | AB27: 580 | AH27: =SUM(C27:AG27) -> 19079
A28: 9 | B28: 工单赔付 | C28: 2000 | D28: 2000 | E28: 2000 | F28: 2000 | G28: 2000 | H28: 2000 | I28: 2000 | J28: 2000 | K28: 2000 | L28: 2000 | M28: 2000 | N28: 2000 | O28: 2000 | P28: 2000 | Q28: 2000 | R28: 2000 | S28: 2000 | T28: 2000 | U28: 2000 | V28: 2000 | W28: 2000 | X28: 2000 | Y28: 2000 | Z28: 2000 | AA28: 2000 | AB28: 2000 | AC28: 2000 | AD28: 2000 | AE28: 2000 | AF28: 2000 | AH28: =SUM(C28:AG28) -> 60000
A29: 10 | B29: 设备成本摊销 | C29: 34945.131 | D29: 34945.131 | E29: 34945.131 | F29: 34945.131 | G29: 34945.131 | H29: 34945.131 | I29: 34945.131 | J29: 34945.131 | K29: 34945.131 | L29: 34945.131 | M29: 34945.131 | N29: 34945.131 | O29: 34945.131 | P29: 34945.131 | Q29: 34945.131 | R29: 34945.131 | S29: 34945.131 | T29: 34945.131 | U29: 34945.131 | V29: 34945.131 | W29: 34945.131 | X29: 34945.131 | Y29: 34945.131 | Z29: 34945.131 | AA29: 34945.131 | AB29: 34945.131 | AC29: 34945.131 | AD29: 34945.131 | AE29: 34945.131 | AF29: 34945.131 | AH29: =SUM(C29:AG29) -> 1048353.9
A30: 二、主营业务成本总计 | C30: 125367.53 | D30: 126135.28 | E30: 128346.38 | F30: 129486.38 | G30: 129699.53 | H30: 130797.23 | I30: 130699.33 | J30: 127657.63 | K30: 126420.63 | L30: 127416.93 | M30: 126018.23 | N30: 130999.73 | O30: 130444.33 | P30: 131637.53 | Q30: 125825.83 | R30: 119911.13 | S30: 120219.73 | T30: 124639.23 | U30: 125768.93 | V30: 128853.83 | W30: 128344.63 | X30: 124372.93 | Y30: 121390.03 | Z30: 120848.33 | AA30: 123986.13 | AB30: 122822.93 | AC30: 123948.63 | AD30: 123432.13 | AE30: 122368.13 | AF30: 119675.63 | AH30: =SUM(AH20:AH29) -> 3777534.9
A31: 主营业务税金及附加 | C31: 1044.31 | D31: 1099.6 | E31: 1032.84 | F31: 1075.05 | G31: 1095.91 | H31: 1115.39 | I31: 1097.97 | J31: 1072.68 | K31: 1016.59 | L31: 1077.76 | M31: 1067.43 | N31: 1175.54 | O31: 1171.15 | P31: 1180.4 | Q31: 1075.16 | R31: 1001.43 | S31: 973.6 | T31: 1016.22 | U31: 1099.84 | V31: 1130.07 | W31: 1110.04 | X31: 1105.43 | Y31: 1022.68 | Z31: 986.07 | AA31: 1048.73 | AB31: 1061.22 | AC31: 1077.25 | AD31: 1089.57 | AE31: 1060.4 | AF31: 1006.6 | AH31: =SUM(C31:AG31) -> 32186.93
A32: 三、主营业务利润（亏损以“-”号填列) | C32: 18631.73 | D32: 25487.57 | E32: 14070.94 | F32: 18751.69 | G32: 21414.02 | H32: 23002.42 | I32: 20698.7 | J32: 20252.72 | K32: 13756.52 | L32: 21193.83 | M32: 21168.29 | N32: 31094.42 | O32: 31044.65 | P32: 31127.05 | Q32: 22427.24 | R32: 18175.41 | S32: 14029.4 | T32: 15486.08 | U32: 25886.71 | V32: 26970.69 | W32: 24718.08 | X32: 28054.01 | Y32: 19625.7 | Z32: 15119.34 | AA32: 20622.66 | AB32: 23507.05 | AC32: 24592.03 | AD32: 26806.92 | AE32: 23849.6 | AF32: 19123.02 | AH32: =AH11-AH30-AH31 -> 660688.45
A33: 1 | B33: 管理人员工资 | C33: 11612.58 | D33: 11612.58 | E33: 11612.58 | F33: 11612.58 | G33: 11612.58 | H33: 11612.58 | I33: 11612.58 | J33: 11612.58 | K33: 11612.58 | L33: 11612.58 | M33: 11612.58 | N33: 11612.58 | O33: 11612.58 | P33: 11612.58 | Q33: 11612.58 | R33: 11612.58 | S33: 11612.58 | T33: 11612.58 | U33: 11612.58 | V33: 11612.58 | W33: 11612.58 | X33: 11612.58 | Y33: 11612.58 | Z33: 11612.58 | AA33: 11612.58 | AB33: 11612.58 | AC33: 11612.58 | AD33: 11612.58 | AE33: 11612.58 | AF33: 11612.58 | AH33: =SUM(C33:AG33) -> 348377.4
A34: 2 | B34: 人事工资 | C34: 703.33 | D34: 703.33 | E34: 703.33 | F34: 703.33 | G34: 703.33 | H34: 703.33 | I34: 703.33 | J34: 703.33 | K34: 703.33 | L34: 703.33 | M34: 703.33 | N34: 703.33 | O34: 703.33 | P34: 703.33 | Q34: 703.33 | R34: 703.33 | S34: 703.33 | T34: 703.33 | U34: 703.33 | V34: 703.33 | W34: 703.33 | X34: 703.33 | Y34: 703.33 | Z34: 703.33 | AA34: 703.33 | AB34: 703.33 | AC34: 703.33 | AD34: 703.33 | AE34: 703.33 | AF34: 703.33 | AH34: =SUM(C34:AG34) -> 21099.9
A35: 3 | B35: 社会保险费 | C35: 1350 | D35: 1350 | E35: 1350 | F35: 1350 | G35: 1350 | H35: 1350 | I35: 1350 | J35: 1350 | K35: 1350 | L35: 1350 | M35: 1350 | N35: 1350 | O35: 1350 | P35: 1350 | Q35: 1350 | R35: 1350 | S35: 1350 | T35: 1350 | U35: 1350 | V35: 1350 | W35: 1350 | X35: 1350 | Y35: 1350 | Z35: 1350 | AA35: 1350 | AB35: 1350 | AC35: 1350 | AD35: 1350 | AE35: 1350 | AF35: 1350 | AH35: =ROUND(SUM(C35:AG35),2) -> 40500
A36: 4 | B36: 意外险 | C36: 5 | D36: 5 | E36: 5 | F36: 5 | G36: 5 | H36: 5 | I36: 5 | J36: 5 | K36: 5 | L36: 5 | M36: 5 | N36: 5 | O36: 5 | P36: 5 | Q36: 5 | R36: 5 | S36: 5 | T36: 5 | U36: 5 | V36: 5 | W36: 5 | X36: 5 | Y36: 5 | Z36: 5 | AA36: 5 | AB36: 5 | AC36: 5 | AD36: 5 | AE36: 5 | AF36: 5 | AH36: =SUM(C36:AG36) -> 150
A37: 5 | B37: 雇主险 | C37: 7.5 | D37: 7.5 | E37: 7.5 | F37: 7.5 | G37: 7.5 | H37: 7.5 | I37: 7.5 | J37: 7.5 | K37: 7.5 | L37: 7.5 | M37: 7.5 | N37: 7.5 | O37: 7.5 | P37: 7.5 | Q37: 7.5 | R37: 7.5 | S37: 7.5 | T37: 7.5 | U37: 7.5 | V37: 7.5 | W37: 7.5 | X37: 7.5 | Y37: 7.5 | Z37: 7.5 | AA37: 7.5 | AB37: 7.5 | AC37: 7.5 | AD37: 7.5 | AE37: 7.5 | AF37: 7.5 | AH37: =SUM(C37:AG37) -> 225
A38: 6 | B38: 福利费 | AH38: =SUM(C38:AG38) -> 0
A39: 7 | B39: 招聘费 | C39: 240 | D39: 280 | E39: 300 | F39: 320 | G39: 360 | H39: 340 | I39: 320 | J39: 360 | K39: 420 | L39: 380 | M39: 360 | N39: 380 | O39: 300 | P39: 340 | Q39: 320 | R39: 280 | S39: 340 | T39: 360 | U39: 360 | V39: 400 | W39: 420 | X39: 340 | Y39: 420 | Z39: 380 | AA39: 340 | AB39: 340 | AC39: 360 | AD39: 360 | AE39: 380 | AF39: 320 | AH39: =SUM(C39:AG39) -> 10420
A40: 8 | B40: 招标代理费 | AH40: =SUM(C40:AG40) -> 0
A41: 9 | B41: 其他 | C41: 375.7 | D41: 1136 | AF41: 269 | AH41: =SUM(C41:AG41) -> 1780.7
A42: 10 | B42: 设备维修费 | AH42: =SUM(C42:AG42) -> 0
A43: 11 | B43: 人员差旅费 | AH43: =SUM(C43:AG43) -> 0
A44: 13
A45: 14
A46: 四、管理费用合计 | C46: =SUM(C33:C45) -> 14294.11 | D46: =SUM(D33:D45) -> 15094.41 | E46: =SUM(E33:E45) -> 13978.41 | F46: =SUM(F33:F45) -> 13998.41 | G46: =SUM(G33:G45) -> 14038.41 | H46: =SUM(H33:H45) -> 14018.41 | I46: =SUM(I33:I45) -> 13998.41 | J46: =SUM(J33:J45) -> 14038.41 | ... AH46: =SUM(AH33:AH45) -> 422553
A47: 五、利润总额（亏损总额以“-”号填列） | C47: =ROUND(C32-C46,2) -> 4337.62 | D47: =D32-D46 -> 10393.16 | E47: =E32-E46 -> 92.53 | F47: =F32-F46 -> 4753.28 | G47: =G32-G46 -> 7375.61 | H47: =H32-H46 -> 8984.01 | I47: =I32-I46 -> 6700.29 | J47: =J32-J46 -> 6214.31 | K47: =K32-K46 -> -341.89 | ... AG47: =AG32-AG46 -> 0 | AH47: =ROUND(AH32-AH46,2) -> 238135.45
A48: 六、亏损分析 | C48: 受大雾天气高速堵路，车辆晚点到达效率下降 | E48: 车辆集中上午进局，白班下午车辆进局不足卸车存在空门洞影响效率，三频次二干18点发车，为保障频次无法在过程中进行人员收缩，18点后已进行分批下工压降成本支出 | F48: 车辆集中上午进局，白班下午车辆进局不足卸车存在空门洞影响效率，三频次二干18点发车，为保障频次无法在过程中进行人员收缩，18点后已进行分批下工压降成本支出 | I48: 邮政集团开始为期三天的视频规范化检查&通报考核，分时段抽检南京现场操作监控，影响整体处理效率达成，处理中心开始介入人员投入 | J48: 邮政集团开始为期三天的视频规范化检查&通报考核，分时段抽检现场操作监控，影响整体处理效率达成，处理中心介入人员投入 | K48: 邮政集团开始为期三天的视频规范化检查&通报考核，分时段抽检现场操作监控，影响整体处理效率达成，处理中心介入人员投入 | L48: 邮政集团今日全网视频会议验收现场规范化操作监控抽查，影响整体处理效率达成，处理中心介入人员投入 | M48: 邮政集团对江苏省转运中心进行现场规范化操作监控抽查，08:00-09:00、17:00-18:00两个时段查看现场作业实时监控，影响整体处理效率达成，处理中心介入人员投入 | N48: 邮政集团对江苏省转运中心进行现场规范化操作监控抽查，08:00-09:00、17:00-18:00两个时段查看现场作业实时监控，影响整体处理效率达成，处理中心介入人员投入 | O48: 为应对邮政集团监控抽检规范作业，07：20停止卸车全场进行地堆整理、笼车规整，影响处理效率 | P48: 为应对邮政集团监控抽检规范作业，07：20停止卸车全场进行地堆整理、笼车规整，影响处理效率，江宁场地白班进口作业关闭分流回调，白班18:00后未停机阶梯下班继续生产影响效能达成 | Q48: 为应对邮政集团监控抽检规范作业，07：10停止卸车全场进行地堆整理、笼车规整，影响处理效率 | R48: 白班下午进局车辆不足，影响效率达成，17:30开始安排阶梯下班降低用工成本 | S48: 白班中午调试粗分2-9的条码优先级落格程序测试到14:30分，下午进局车辆不足，影响效率达成，18:00三频次结束已开始安排阶梯下班降低用工成本 | T48: 宿迁高峰临时场地关停尾量车回调10路向11辆车，异形件增加影响处理效率达成，白班19点开始安排阶梯下班降低用工成本 | W48: 党刊纪检、求是杂志灌袋、包装、粘贴面单发运，影响处理效率达成 | Y48: 白班下午进局车次不足，1800三频次结束后阶梯下班缩短出勤工时，降低人工成本支出 | Z48: 小件量占比下降，白班下午进局车次不足，1800三频次结束后阶梯下班缩短出勤工时，降低人工成本支出 | AA48: 白班下午进局车次不足，1800三频次结束后阶梯下班缩短出勤工时，降低人工成本支出 | AB48: 白班下午进局车次不足，1800三频次结束后阶梯下班缩短出勤工时，降低人工成本支出 | AC48: 白班下午进局车次不足，1800三频次结束后阶梯下班缩短出勤工时，降低人工成本支出 | AD48: 白班下午进局车次不足，1800三频次结束后阶梯下班缩短出勤工时，降低人工成本支出 | AE48: 白班下午进局车次不足，1800三频次结束后阶梯下班缩短出勤工时，降低人工成本支出 | AF48: 白班下午进局车次不足，1800三频次结束后阶梯下班缩短出勤工时，降低人工成本支出
A49: 注：请注意业务量跳档时单价的变化
X51: 南京项目人效
X52: 部门 | Z52: 南京进口
X53: 日期 | Z53: 45991
X54: 管理人数 | Z54: 24
X55: 自有员工 | Z55: 298
X56: 劳务人员 | Z56: 69
X57: 总人数 | Z57: 391
X58: 散件处理量 | Z58: 906980
X59: 总工时 | Z59: 3998.5
X60: 人均小时效能 | Z60: 226.83006

Sheet 25年11月处理量
A1: 日 | B1: 新一代查询业务量 （散件外走） | C1: 新一代查询业务量 （分拣封发） | D1: 新一代查询业务量 （总包经转） | E1: 平刷件量(剔除） | F1: 合计
A2: 45962 | B2: 384801 | C2: 858657 | D2: 30388 | E2: 333557 | F2: =SUM(B2:D2)-E2 -> 940289
A3: =A2+1 -> 45963 | B3: 418193 | C3: 672805 | D3: 30209 | E3: 132090 | F3: =SUM(B3:D3)-E3 -> 989117
A4: =A3+1 -> 45964 | B4: 384166 | C4: 603723 | D4: 33065 | E4: 90797 | F4: =SUM(B4:D4)-E4 -> 930157
A5: =A4+1 -> 45965 | B5: 392054 | C5: 585177 | D5: 35308 | E5: 45101 | F5: =SUM(B5:D5)-E5 -> 967438
A6: =A5+1 -> 45966 | B6: 401168 | C6: 607691 | D6: 35187 | E6: 58191 | F6: =SUM(B6:D6)-E6 -> 985855
A7: =A6+1 -> 45967 | B7: 411205 | C7: 624161 | D7: 35880 | E7: 68187 | F7: =SUM(B7:D7)-E7 -> 1003059
A8: =A7+1 -> 45968 | B8: 401598 | C8: 622484 | D8: 39517 | E8: 75922 | F8: =SUM(B8:D8)-E8 -> 987677
A9: =A8+1 -> 45969 | B9: 381131 | C9: 738028 | D9: 35033 | E9: 188853 | F9: =SUM(B9:D9)-E9 -> 965339
A10: =A9+1 -> 45970 | B10: 367018 | C10: 663690 | D10: 27068 | E10: 141967 | F10: =SUM(B10:D10)-E10 -> 915809
A11: =A10+1 -> 45971 | B11: 398014 | C11: 610304 | D11: 34811 | E11: 73304 | F11: =SUM(B11:D11)-E11 -> 969825
A12: =A11+1 -> 45972 | B12: 397323 | C12: 604493 | D12: 34928 | E12: 76041 | F12: =SUM(B12:D12)-E12 -> 960703
A13: =A12+1 -> 45973 | B13: 444999 | C13: 626550 | D13: 36995 | E13: 52360 | F13: =SUM(B13:D13)-E13 -> 1056184
A14: =A13+1 -> 45974 | B14: 430268 | C14: 649711 | D14: 34923 | E14: 62594 | F14: =SUM(B14:D14)-E14 -> 1052308
... A31: =A30+1 -> 45991 | B31: 381233 | C31: 629362 | D31: 28713 | E31: 132328 | F31: =SUM(B31:D31)-E31 -> 906980
A32: =A31+1 -> 45992 | F32: =SUM(B32:D32)-E32 -> 0
A33: 合计 | B33: =SUM(B2:B32) -> 11901618 | C33: =SUM(C2:C32) -> 19527315 | D33: =SUM(D2:D32) -> 1042347 | E33: =SUM(E2:E32) -> 3505264 | F33: =SUM(F2:F32) -> 28966016

Sheet 25年12月日经营数据
A1: 2025年南京项目处理经营情况（12月）
A3: 科目 | C3: 45992 | D3: =C3+1 -> 45993 | E3: =D3+1 -> 45994 | F3: =E3+1 -> 45995 | G3: =F3+1 -> 45996 | H3: =G3+1 -> 45997 | I3: =H3+1 -> 45998 | J3: =I3+1 -> 45999 | K3: =J3+1 -> 46000 | ... AG3: =AF3+1 -> 46022 | AH3: 月度合计
C4: 进口处理 | D4: 进口处理 | E4: 进口处理 | F4: 进口处理 | G4: 进口处理 | H4: 进口处理 | I4: 进口处理 | J4: 进口处理 | K4: 进口处理 | L4: 进口处理 | M4: 进口处理 | N4: 进口处理 | O4: 进口处理 | P4: 进口处理 | Q4: 进口处理 | R4: 进口处理 | S4: 进口处理 | T4: 进口处理 | U4: 进口处理 | V4: 进口处理 | W4: 进口处理 | X4: 进口处理 | Y4: 进口处理 | Z4: 进口处理 | AA4: 进口处理 | AB4: 进口处理 | AC4: 进口处理 | AD4: 进口处理 | AE4: 进口处理 | AF4: 进口处理 | AG4: 进口处理 | AH4: 进口处理
A5: 1 | B5: 散件处理量 | C5: =SUMIFS('25年12月处理量'!$F:$F,'25年12月处理量'!$A:$A,C3) -> 906218 | D5: =SUMIFS('25年12月处理量'!$F:$F,'25年12月处理量'!$A:$A,D3) -> 918302 | E5: =SUMIFS('25年12月处理量'!$F:$F,'25年12月处理量'!$A:$A,E3) -> 975475 | F5: =SUMIFS('25年12月处理量'!$F:$F,'25年12月处理量'!$A:$A,F3) -> 1003189 | G5: =SUMIFS('25年12月处理量'!$F:$F,'25年12月处理量'!$A:$A,G3) -> 1001950 | H5: =SUMIFS('25年12月处理量'!$F:$F,'25年12月处理量'!$A:$A,H3) -> 959395 | I5: =SUMIFS('25年12月处理量'!$F:$F,'25年12月处理量'!$A:$A,I3) -> 939991 | J5: =SUMIFS('25年12月处理量'!$F:$F,'25年12月处理量'!$A:$A,J3) -> 888761 | ... AG5: =SUMIFS('25年12月处理量'!$F:$F,'25年12月处理量'!$A:$A,AG3) -> 941382 | AH5: =SUM(C5:AG5) -> 29427078
A6: 2 | B6: 散件处理单价 | C6: 0.1667 | D6: 0.1667 | E6: 0.1667 | F6: 0.1667 | G6: 0.1667 | H6: 0.1667 | I6: 0.1667 | J6: 0.1667 | K6: 0.1667 | L6: 0.1667 | M6: 0.1667 | N6: 0.1667 | O6: 0.1667 | P6: 0.1667 | Q6: 0.1667 | R6: 0.1667 | S6: 0.1667 | T6: 0.1667 | U6: 0.1667 | V6: 0.1667 | W6: 0.1667 | X6: 0.1667 | Y6: 0.1667 | Z6: 0.1667 | AA6: 0.1667 | AB6: 0.1667 | AC6: 0.1667 | AD6: 0.1667 | AE6: 0.1667 | AF6: 0.1667 | AG6: 0.1667 | AH6: 0.1667
A7: 3 | B7: 散件处理收入 | C7: 151066.54 | D7: 153080.94 | E7: 162611.68 | F7: 167231.61 | G7: 167025.07 | H7: 159931.15 | I7: 156696.5 | J7: 148156.46 | K7: 152443.15 | L7: 163877.6 | M7: 171318.09 | N7: 162755.04 | O7: 154447.05 | P7: 158921.94 | Q7: 155415.58 | R7: 168670.23 | S7: 160931.18 | T7: 163791.25 | U7: 161420.28 | V7: 160542.44 | W7: 149591.91 | X7: 151510.46 | Y7: 157547.84 | Z7: 152218.44 | AA7: 172713.54 | AB7: 160729.31 | AC7: 149120.65 | AD7: 149994.99 | AE7: 153297.49 | AF7: 151507.13 | AG7: 156928.38 | AH7: =SUM(C7:AG7) -> 4905493.9
A8: 4 | B8: 考核扣款 | C8: 4000 | D8: 4000 | E8: 4000 | F8: 4000 | G8: 4000 | H8: 4000 | I8: 4000 | J8: 4000 | K8: 4000 | L8: 4000 | M8: 4000 | N8: 4000 | O8: 4000 | P8: 4000 | Q8: 4000 | R8: 4000 | S8: 4000 | T8: 4000 | U8: 4000 | V8: 4000 | W8: 4000 | X8: 4000 | Y8: 4000 | Z8: 4000 | AA8: 4000 | AB8: 4000 | AC8: 4000 | AD8: 4000 | AE8: 4000 | AF8: 4000 | AG8: 4000 | AH8: =SUM(C8:AG8) -> 124000
A9: 5 | B9: 补贴费用 | AH9: =SUM(C9:AG9) -> 0
A10: 6 | B10: 开票金额 | C10: 147066.54 | D10: 149080.94 | E10: 158611.68 | F10: 163231.61 | G10: 163025.07 | H10: 155931.15 | I10: 152696.5 | J10: 144156.46 | K10: 148443.15 | L10: 159877.6 | M10: 167318.09 | N10: 158755.04 | O10: 150447.05 | P10: 154921.94 | Q10: 151415.58 | R10: 164670.23 | S10: 156931.18 | T10: 159791.25 | U10: 157420.28 | V10: 156542.44 | W10: 145591.91 | X10: 147510.46 | Y10: 153547.84 | Z10: 148218.44 | AA10: 168713.54 | AB10: 156729.31 | AC10: 145120.65 | AD10: 145994.99 | AE10: 149297.49 | AF10: 147507.13 | AG10: 152928.38 | AH10: =SUM(C10:AG10) -> 4781493.9
A11: 一、主营业务收入总计 | C11: 138742.02 | D11: 140642.4 | E11: 149633.66 | F11: 153992.08 | G11: 153797.24 | H11: 147104.86 | I11: 144053.3 | J11: 135996.66 | K11: 140040.71 | L11: 150827.92 | M11: 157847.25 | N11: 149768.91 | O11: 141931.18 | P11: 146152.77 | Q11: 142844.89 | R11: 155349.27 | S11: 148048.28 | T11: 150746.46 | U11: 148509.7 | V11: 147681.55 | W11: 137350.86 | X11: 139160.81 | Y11: 144856.45 | Z11: 139828.72 | AA11: 159163.72 | AB11: 147857.84 | AC11: 136906.27 | AD11: 137731.12 | AE11: 140846.69 | AF11: 139157.67 | AG11: 144272.06 | AH11: =SUM(C11:AG11) -> 4510843.3
A12: 1 | B12: 管理人员数量 | C12: 23 | D12: 21 | E12: 23 | F12: 23 | G12: 22 | H12: 25 | I12: 25 | J12: 22 | K12: 22 | L12: 23 | M12: 22 | N12: 23 | O12: 24 | P12: 22 | Q12: 21 | R12: 21 | S12: 24 | T12: 22 | U12: 24 | V12: 24 | W12: 24 | X12: 21 | Y12: 21 | Z12: 21 | AA12: 22 | AB12: 21 | AC12: 23 | AD12: 23 | AE12: 23 | AF12: 23 | AG12: 20 | AH12: =SUM(C12:AG12) -> 698
A13: 2 | B13: 自有员工数量 | C13: 287 | D13: 291 | E13: 294 | F13: 290 | G13: 290 | H13: 292 | I13: 308 | J13: 307 | K13: 302 | L13: 296 | M13: 308 | N13: 299 | O13: 294 | P13: 299 | Q13: 293 | R13: 298 | S13: 299 | T13: 302 | U13: 297 | V13: 297 | W13: 301 | X13: 302 | Y13: 299 | Z13: 295 | AA13: 303 | AB13: 298 | AC13: 304 | AD13: 309 | AE13: 305 | AF13: 309 | AG13: 288 | AH13: =SUM(C13:AG13) -> 9256
A14: 3 | B14: 劳务人员数量 | C14: 75 | D14: 79 | E14: 82 | F14: 87 | G14: 91 | H14: 93 | I14: 83 | J14: 73 | K14: 77 | L14: 88 | M14: 86 | N14: 86 | O14: 80 | P14: 80 | Q14: 77 | R14: 89 | S14: 86 | T14: 83 | U14: 81 | V14: 78 | W14: 66 | X14: 68 | Y14: 76 | Z14: 81 | AA14: 85 | AB14: 74 | AC14: 68 | AD14: 66 | AE14: 63 | AF14: 66 | AG14: 81 | AH14: =SUM(C14:AG14) -> 2448
A15: 4 | B15: 总人数 | C15: 385 | D15: 391 | E15: 399 | F15: 400 | G15: 403 | H15: 410 | I15: 416 | J15: 402 | K15: 401 | L15: 407 | M15: 416 | N15: 408 | O15: 398 | P15: 401 | Q15: 391 | R15: 408 | S15: 409 | T15: 407 | U15: 402 | V15: 399 | W15: 391 | X15: 391 | Y15: 396 | Z15: 397 | AA15: 410 | AB15: 393 | AC15: 395 | AD15: 398 | AE15: 391 | AF15: 398 | AG15: 389 | AH15: =SUM(C15:AG15) -> 12402
A16: 5 | B16: 总工时 | C16: 3956 | D16: 4053 | E16: 4215 | F16: 4319 | G16: 4322 | H16: 4335 | I16: 4268.5 | J16: 4122 | K16: 4112.5 | L16: 4306 | M16: 4444 | N16: 4274.5 | O16: 4142 | P16: 4236 | Q16: 4053.5 | R16: 4348 | S16: 4348.5 | T16: 4318 | U16: 4193 | V16: 4148.5 | W16: 4064 | X16: 4134.5 | Y16: 4166.5 | Z16: 4169.5 | AA16: 4446 | AB16: 4170.5 | AC16: 4130.5 | AD16: 4165.5 | AE16: 4085 | AF16: 4169.5 | AG16: 4088.5 | AH16: =SUM(C16:AG16) -> 130305
A17: 人均效能 | C17: 2353.813 | D17: 2348.5985 | E17: 2444.7995 | F17: 2507.9725 | G17: 2486.2283 | H17: 2339.9878 | I17: 2259.5938 | J17: 2210.8483 | K17: 2280.4888 | L17: 2415.4029 | M17: 2470.4399 | N17: 2392.9779 | O17: 2327.8819 | P17: 2377.409 | Q17: 2384.4169 | R17: 2479.9485 | S17: 2360.3765 | T17: 2414.1302 | U17: 2408.7761 | V17: 2413.6892 | W17: 2295.0691 | X17: 2324.5038 | Y17: 2386.6111 | Z17: 2300.0705 | AA17: 2527.0098 | AB17: 2453.3919 | AC17: 2264.6709 | AD17: 2260.7789 | AE17: 2351.9207 | AF17: 2283.5704 | AG17: 2420.0051 | AH17: =AH5/AH15 -> 2372.7687
A18: 人均小时效能 | C18: 229.07432 | D18: 226.5734 | E18: 231.42942 | F18: 232.27344 | G18: 231.82554 | H18: 221.31373 | I18: 220.21577 | J18: 215.61402 | K18: 222.36498 | L18: 228.30214 | M18: 231.2563 | N18: 228.40917 | O18: 223.68349 | P18: 225.05689 | Q18: 230.00049 | R18: 232.70906 | S18: 222.00621 | T18: 227.54771 | U18: 230.93918 | V18: 232.14704 | W18: 220.81004 | X18: 219.82852 | Y18: 226.83259 | Z18: 219.0018 | AA18: 233.03509 | AB18: 231.19122 | AC18: 216.57063 | AD18: 216.01008 | AE18: 225.11652 | AF18: 217.97841 | AG18: 230.25119 | AH18: =AH5/AH16 -> 225.8323
A19: 工人件均成本 | C19: 0.086723614 | D19: 0.087589377 | E19: 0.085743868 | F19: 0.085490371 | G19: 0.085833125 | H19: 0.089977538 | I19: 0.090079586 | J19: 0.091652311 | K19: 0.089159803 | L19: 0.087081375 | M19: 0.085640015 | N19: 0.086987561 | O19: 0.088676488 | P19: 0.087946496 | Q19: 0.08617494 | R19: 0.085463902 | S19: 0.089396143 | T19: 0.087048408 | U19: 0.08587018 | V19: 0.085293055 | W19: 0.089138061 | X19: 0.089614042 | Y19: 0.087114775 | Z19: 0.090579853 | AA19: 0.084911406 | AB19: 0.085487402 | AC19: 0.090935056 | AD19: 0.091079585 | AE19: 0.087354189 | AF19: 0.090185408 | AG19: 0.086382574 | AH19: =(AH21+AH27)/AH5 -> 0.087698276
A20: 管理人员件均成本 | C20: 0.014362332 | D20: 0.014173337 | E20: 0.013342632 | F20: 0.012974029 | G20: 0.012990073 | H20: 0.013566262 | I20: 0.013846307 | J20: 0.014644436 | K20: 0.014232635 | L20: 0.013239563 | M20: 0.012664557 | N20: 0.013330879 | O20: 0.014047972 | P20: 0.013652411 | Q20: 0.013960427 | R20: 0.012863371 | S20: 0.01348196 | T20: 0.013246542 | U20: 0.01344111 | V20: 0.013514606 | W20: 0.014503911 | X20: 0.01432025 | Y20: 0.013771486 | Z20: 0.014253646 | AA20: 0.012562234 | AB20: 0.013498893 | AC20: 0.014549747 | AD20: 0.014464935 | AE20: 0.014153316 | AF20: 0.014320566 | AG20: 0.013825847 | AH20: =(AH34+AH36)/AH5 -> 0.013711097
A21: 1 | B21: 自有员工工资 | C21: 58822 | D21: 59607 | E21: 62009.5 | F21: 62843.5 | G21: 62057.5 | H21: 61863.5 | I21: 62858.5 | J21: 62298 | K21: 61271.5 | L21: 62423 | M21: 65392 | N21: 62308.5 | O21: 61113.5 | P21: 62786.5 | Q21: 60078.5 | R21: 63071.5 | S21: 63705 | T21: 63714 | U21: 61852.5 | V21: 61626.5 | W21: 62636.5 | X21: 63554.5 | Y21: 62345 | Z21: 61401.5 | AA21: 65630 | AB21: 62979 | AC21: 63486 | AD21: 64587.5 | AE21: 63748 | AF21: 64612.5 | AG21: 60009.5 | AH21: =SUM(C21:AG21) -> 1936692.5
A22: 2 | B22: 员工宿舍费 | AH22: =SUM(C22:AG22) -> 0
A23: 3 | B23: 意外险 | C23: 390 | D23: 390 | E23: 390 | F23: 390 | G23: 390 | H23: 390 | I23: 390 | J23: 390 | K23: 390 | L23: 390 | M23: 390 | N23: 390 | O23: 390 | P23: 390 | Q23: 390 | R23: 390 | S23: 390 | T23: 390 | U23: 390 | V23: 390 | W23: 390 | X23: 390 | Y23: 390 | Z23: 390 | AA23: 390 | AB23: 390 | AC23: 390 | AD23: 390 | AE23: 390 | AF23: 390 | AG23: 390 | AH23: =SUM(C23:AG23) -> 12090
A24: 4 | B24: 雇主险 | C24: 585 | D24: 585 | E24: 585 | F24: 585 | G24: 585 | H24: 585 | I24: 585 | J24: 585 | K24: 585 | L24: 585 | M24: 585 | N24: 585 | O24: 585 | P24: 585 | Q24: 585 | R24: 585 | S24: 585 | T24: 585 | U24: 585 | V24: 585 | W24: 585 | X24: 585 | Y24: 585 | Z24: 585 | AA24: 585 | AB24: 585 | AC24: 585 | AD24: 585 | AE24: 585 | AF24: 585 | AG24: 585 | AH24: =SUM(C24:AG24) -> 18135
A25: 5 | B25: 员工餐费 | C25: 2720 | D25: 2736 | E25: 2776 | F25: 2744 | G25: 2736 | H25: 2776 | I25: 2904 | J25: 2872 | K25: 2832 | L25: 2792 | M25: 2880 | N25: 2816 | O25: 2784 | P25: 2808 | Q25: 2752 | R25: 2792 | S25: 2824 | T25: 2832 | U25: 2808 | V25: 2808 | W25: 2840 | X25: 2824 | Y25: 2800 | Z25: 2768 | AA25: 2840 | AB25: 2792 | AC25: 2856 | AD25: 2896 | AE25: 2864 | AF25: 2896 | AG25: 2704 | AH25: =SUM(C25:AG25) -> 87072
A26: 6 | B26: 高温福利费用 | AH26: =SUM(C26:AG26) -> 0
A27: 7 | B27: 劳务人员工资 | C27: 19768.5 | D27: 20826.5 | E27: 21631.5 | F27: 22919.5 | G27: 23943 | H27: 24460.5 | I27: 21815.5 | J27: 19159 | K27: 20263 | L27: 23184 | M27: 22620.5 | N27: 22620.5 | O27: 21045 | P27: 21056.5 | Q27: 20263 | R27: 23402.5 | S27: 22597.5 | T27: 21815.5 | U27: 21298 | V27: 20516 | W27: 17353.5 | X27: 17894 | Y27: 19987 | Z27: 21309.5 | AA27: 22344.5 | AB27: 19446.5 | AC27: 17859.5 | AD27: 17365 | AE27: 16583 | AF27: 17353.5 | AG27: 21309.5 | AH27: =SUM(C27:AG27) -> 644011.5
A28: 8 | B28: 物料采购 | S28: 149.79 | AH28: =SUM(C28:AG28) -> 149.79
A29: 9 | B29: 工单赔付 | C29: 2000 | D29: 2000 | E29: 2000 | F29: 2000 | G29: 2000 | H29: 2000 | I29: 2000 | J29: 2000 | K29: 2000 | L29: 2000 | M29: 2000 | N29: 2000 | O29: 2000 | P29: 2000 | Q29: 2000 | R29: 2000 | S29: 2000 | T29: 2000 | U29: 2000 | V29: 2000 | W29: 2000 | X29: 2000 | Y29: 2000 | Z29: 2000 | AA29: 2000 | AB29: 2000 | AC29: 2000 | AD29: 2000 | AE29: 2000 | AF29: 2000 | AG29: 2000 | AH29: =SUM(C29:AG29) -> 62000
A30: 10 | B30: 设备成本摊销 | C30: 33651.837 | D30: 33651.837 | E30: 33651.837 | F30: 33651.837 | G30: 33651.837 | H30: 33651.837 | I30: 33651.837 | J30: 33651.837 | K30: 33651.837 | L30: 33651.837 | M30: 33651.837 | N30: 33651.837 | O30: 33651.837 | P30: 33651.837 | Q30: 33651.837 | R30: 33651.837 | S30: 33651.837 | T30: 33651.837 | U30: 33651.837 | V30: 33651.837 | W30: 33651.837 | X30: 33651.837 | Y30: 33651.837 | Z30: 33651.837 | AA30: 33651.837 | AB30: 33651.837 | AC30: 33651.837 | AD30: 33651.837 | AE30: 33651.837 | AF30: 33651.837 | AG30: 33651.837 | AH30: =SUM(C30:AG30) -> 1043207
A31: 二、主营业务成本总计 | C31: 117937.34 | D31: 119796.34 | E31: 123043.84 | F31: 125133.84 | G31: 125363.34 | H31: 125726.84 | I31: 124204.84 | J31: 120955.84 | K31: 120993.34 | L31: 125025.84 | M31: 127519.34 | N31: 124371.84 | O31: 121569.34 | P31: 123277.84 | Q31: 119720.34 | R31: 125892.84 | S31: 125903.13 | T31: 124988.34 | U31: 122585.34 | V31: 121577.34 | W31: 119456.84 | X31: 120899.34 | Y31: 121758.84 | Z31: 122105.84 | AA31: 127441.34 | AB31: 121844.34 | AC31: 120828.34 | AD31: 121475.34 | AE31: 119821.84 | AF31: 121488.84 | AG31: 120649.84 | AH31: =SUM(AH21:AH30) -> 3803357.8
A32: 主营业务税金及附加 | C32: 998.94 | D32: 1012.63 | E32: 1077.36 | F32: 1108.74 | G32: 1107.34 | H32: 1059.15 | I32: 1037.18 | J32: 979.18 | K32: 1008.29 | L32: 1085.96 | M32: 1136.5 | N32: 1078.34 | O32: 1021.9 | P32: 1052.3 | Q32: 1028.48 | R32: 1118.51 | S32: 1065.95 | T32: 1085.37 | U32: 1069.27 | V32: 1063.31 | W32: 988.93 | X32: 1001.96 | Y32: 1042.97 | Z32: 1006.77 | AA32: 1145.98 | AB32: 1064.58 | AC32: 985.73 | AD32: 991.66 | AE32: 1014.1 | AF32: 1001.94 | AG32: 1038.76 | AH32: =SUM(C32:AG32) -> 32478.08
A33: 三、主营业务利润（亏损以“-”号填列) | C33: 19805.74 | D33: 19833.43 | E33: 25512.46 | F33: 27749.5 | G33: 27326.56 | H33: 20318.87 | I33: 18811.28 | J33: 14061.64 | K33: 18039.08 | L33: 24716.12 | M33: 29191.41 | N33: 24318.73 | O33: 19339.94 | P33: 21822.63 | Q33: 22096.07 | R33: 28337.92 | S33: 21079.2 | T33: 24672.75 | U33: 24855.09 | V33: 25040.9 | W33: 16905.09 | X33: 17259.51 | Y33: 22054.64 | Z33: 16716.11 | AA33: 30576.4 | AB33: 24948.92 | AC33: 15092.2 | AD33: 15264.12 | AE33: 20010.75 | AF33: 16666.89 | AG33: 22583.46 | AH33: =AH11-AH31-AH32 -> 675007.49
A34: 1 | B34: 管理人员工资 | C34: 11831.71 | D34: 11831.71 | E34: 11831.71 | F34: 11831.71 | G34: 11831.71 | H34: 11831.71 | I34: 11831.71 | J34: 11831.71 | K34: 11831.71 | L34: 11831.71 | M34: 11831.71 | N34: 11831.71 | O34: 11831.71 | P34: 11831.71 | Q34: 11831.71 | R34: 11831.71 | S34: 11831.71 | T34: 11831.71 | U34: 11831.71 | V34: 11831.71 | W34: 11831.71 | X34: 11831.71 | Y34: 11831.71 | Z34: 11831.71 | AA34: 11831.71 | AB34: 11831.71 | AC34: 11831.71 | AD34: 11831.71 | AE34: 11831.71 | AF34: 11831.71 | AG34: 11831.71 | AH34: =SUM(C34:AG34) -> 366783.01
A35: 2 | B35: 人事工资 | C35: 680.65 | D35: 680.65 | E35: 680.65 | F35: 680.65 | G35: 680.65 | H35: 680.65 | I35: 680.65 | J35: 680.65 | K35: 680.65 | L35: 680.65 | M35: 680.65 | N35: 680.65 | O35: 680.65 | P35: 680.65 | Q35: 680.65 | R35: 680.65 | S35: 680.65 | T35: 680.65 | U35: 680.65 | V35: 680.65 | W35: 680.65 | X35: 680.65 | Y35: 680.65 | Z35: 680.65 | AA35: 680.65 | AB35: 680.65 | AC35: 680.65 | AD35: 680.65 | AE35: 680.65 | AF35: 680.65 | AG35: 680.65 | AH35: =SUM(C35:AG35) -> 21100.15
A36: 3 | B36: 社会保险费 | C36: 1183.6935 | D36: 1183.6935 | E36: 1183.6935 | F36: 1183.6935 | G36: 1183.6935 | H36: 1183.6935 | I36: 1183.6935 | J36: 1183.6935 | K36: 1183.6935 | L36: 1183.6935 | M36: 1183.6935 | N36: 1183.6935 | O36: 1183.6935 | P36: 1183.6935 | Q36: 1183.6935 | R36: 1183.6935 | S36: 1183.6935 | T36: 1183.6935 | U36: 1183.6935 | V36: 1183.6935 | W36: 1183.6935 | X36: 1183.6935 | Y36: 1183.6935 | Z36: 1183.6935 | AA36: 1183.6935 | AB36: 1183.6935 | AC36: 1183.6935 | AD36: 1183.6935 | AE36: 1183.6935 | AF36: 1183.6935 | AG36: 1183.6935 | AH36: =ROUND(SUM(C36:AG36),2) -> 36694.5
A37: 4 | B37: 意外险 | C37: 5 | D37: 5 | E37: 5 | F37: 5 | G37: 5 | H37: 5 | I37: 5 | J37: 5 | K37: 5 | L37: 5 | M37: 5 | N37: 5 | O37: 5 | P37: 5 | Q37: 5 | R37: 5 | S37: 5 | T37: 5 | U37: 5 | V37: 5 | W37: 5 | X37: 5 | Y37: 5 | Z37: 5 | AA37: 5 | AB37: 5 | AC37: 5 | AD37: 5 | AE37: 5 | AF37: 5 | AG37: 5 | AH37: =SUM(C37:AG37) -> 155
A38: 5 | B38: 雇主险 | C38: 7.5 | D38: 7.5 | E38: 7.5 | F38: 7.5 | G38: 7.5 | H38: 7.5 | I38: 7.5 | J38: 7.5 | K38: 7.5 | L38: 7.5 | M38: 7.5 | N38: 7.5 | O38: 7.5 | P38: 7.5 | Q38: 7.5 | R38: 7.5 | S38: 7.5 | T38: 7.5 | U38: 7.5 | V38: 7.5 | W38: 7.5 | X38: 7.5 | Y38: 7.5 | Z38: 7.5 | AA38: 7.5 | AB38: 7.5 | AC38: 7.5 | AD38: 7.5 | AE38: 7.5 | AF38: 7.5 | AG38: 7.5 | AH38: =SUM(C38:AG38) -> 232.5
A39: 6 | B39: 福利费 | AH39: =SUM(C39:AG39) -> 0
A40: 7 | B40: 招聘费 | C40: 180 | D40: 100 | E40: 200 | F40: 180 | G40: 160 | H40: 240 | I40: 140 | J40: 160 | K40: 160 | L40: 180 | M40: 200 | N40: 210 | O40: 180 | P40: 260 | Q40: 180 | R40: 260 | S40: 180 | T40: 240 | U40: 220 | V40: 240 | W40: 220 | X40: 200 | Y40: 220 | Z40: 200 | AA40: 260 | AB40: 280 | AC40: 260 | AD40: 240 | AE40: 280 | AF40: 240 | AG40: 240 | AH40: =SUM(C40:AG40) -> 6510
A41: 8 | B41: 招标代理费 | AH41: =SUM(C41:AG41) -> 0
A42: 9 | B42: 其他 | AH42: =SUM(C42:AG42) -> 0
A43: 10 | B43: 设备维修费 | AH43: =SUM(C43:AG43) -> 0
A44: 11 | B44: 人员差旅费 | AH44: =SUM(C44:AG44) -> 0
A45: 13
A46: 14
A47: 四、管理费用合计 | C47: =SUM(C34:C46) -> 13888.554 | D47: =SUM(D34:D46) -> 13808.554 | E47: =SUM(E34:E46) -> 13908.554 | F47: =SUM(F34:F46) -> 13888.554 | G47: =SUM(G34:G46) -> 13868.554 | H47: =SUM(H34:H46) -> 13948.554 | I47: =SUM(I34:I46) -> 13848.554 | J47: =SUM(J34:J46) -> 13868.554 | ... AH47: =SUM(AH34:AH46) -> 431475.16
A48: 五、利润总额（亏损总额以“-”号填列） | C48: =ROUND(C33-C47,2) -> 5917.19 | D48: =D33-D47 -> 6024.8765 | E48: =E33-E47 -> 11603.906 | F48: =F33-F47 -> 13860.946 | G48: =G33-G47 -> 13458.006 | H48: =H33-H47 -> 6370.3165 | I48: =I33-I47 -> 4962.7265 | J48: =J33-J47 -> 193.08645 | K48: =K33-K47 -> 4170.5265 | ... AG48: =AG33-AG47 -> 8634.9065 | AH48: =ROUND(AH33-AH47,2) -> 243532.33
A49: 六、亏损分析 | C49: 白班下午进局车次不足，1800三频次结束后阶梯下班缩短出勤工时，降低人工成本支出 管理人员单件成本包含社保 | D49: 白班下午进局车次不足，1800三频次结束后阶梯下班缩短出勤工时，降低人工成本支出 管理人员单件成本包含社保 | F49: 流感爆发，自有员工感冒请假增多，劳务用工增加 | H49: 白班8点开始进行粗分一检修保养（12月6日-7日停机开拆设备），增投人员进行应急分流保障作业，人工成本增加 | I49: 粗分一检修保养（12月6日-7日停机开拆设备），增投人员进行应急分流保障作业，人工成本增加 | J49: 1、白班下午13点停机更换1号垛口伸缩机两个班次不能使用，增投人员应急操作； 2、白班下午进局车次不足，1800三频次结束后阶梯下班缩短出勤工时，降低人工成本支出 | K49: 白班下午进局车次不足，1800三频次结束后阶梯下班缩短出勤工时，降低人工成本支出 | L49: 1、因无锡中心设备维修分流4路向5辆车进局接卸，异形件增加影响处理效率 2、为缓解夜班上半夜集中到车待卸压力，白班下午1800频次结束后继续作业至19点，处理效率下降 | O49: 1、受雨雪天气影响高速缓行，一干部分车辆晚点进局，影响处理效率达成； 2、夜班细分五20点居中机皮带损坏更换耗时40分钟影响效率； | S49: 1、粗分三居中机12点故障开始维修用时1小时30分钟，影响效率达成； 2、15点30分细分三第一组摆轮控制器螺丝损坏开始维修用时1小时40分钟，影响效率达成； 3、细分三拐弯机故障19点开始维修用时1小时50分钟，影响效率达成； | T49: 细分三第一组摆轮故障凌晨01点开始维修用时3小时10分钟，增开落地窄带机应急生产，影响效率达成 | W49: 1、纪检、求是大刊包装发运影响效率达成； 2、白班下午进局车次不足，1800三频次结束后阶梯下班缩短出勤工时，降低人工成本支出； | X49: 白班下午进局车次不足，1800三频次结束后阶梯下班缩短出勤工时，降低人工成本支出； | Y49: 白班下午进局车次不足，1800三频次结束后阶梯下班缩短出勤工时，降低人工成本支出； | Z49: 白班下午进局车次不足，1800三频次结束后阶梯下班缩短出勤工时，降低人工成本支出； | AC49: 白班下午进局车次不足，1800三频次结束后阶梯下班缩短出勤工时，降低人工成本支出； | AD49: 1、白班下午进局车次不足，1800三频次结束后阶梯下班缩短出勤工时，降低人工成本支出； 2、晚班20:50开始粗分十窄带机故障检修，02：15才维护完成，影响效率达成； | AE49: 白班下午进局车次不足，1800三频次结束后阶梯下班缩短出勤工时，降低人工成本支出； | AF49: 白班下午进局车次不足，1800三频次结束后阶梯下班缩短出勤工时，降低人工成本支出； | AG49: 白班下午进局车次不足，1800三频次结束后阶梯下班缩短出勤工时，降低人工成本支出；
A50: 注：请注意业务量跳档时单价的变化
Y52: 南京项目人效
Y53: 部门 | AA53: 南京进口
Y54: 日期 | AA54: 46022
Y55: 管理人数 | AA55: 20
Y56: 自有员工 | AA56: 288
Y57: 劳务人员 | AA57: 81
Y58: 总人数 | AA58: 389
Y59: 散件处理量 | AA59: 941382
Y60: 总工时 | AA60: 4088.5
Y61: 人均小时效能 | AA61: 230.25119

Sheet 25年12月处理量
A1: 日 | B1: 新一代查询业务量 （散件外走） | C1: 新一代查询业务量 （分拣封发） | D1: 新一代查询业务量 （总包经转） | E1: 平刷件量(剔除） | F1: 合计
A2: 45992 | B2: 381060 | C2: 553654 | D2: 32908 | E2: 61404 | F2: =SUM(B2:D2)-E2 -> 906218
A3: =A2+1 -> 45993 | B3: 386741 | C3: 547727 | D3: 34409 | E3: 50575 | F3: =SUM(B3:D3)-E3 -> 918302
A4: =A3+1 -> 45994 | B4: 410480 | C4: 586194 | D4: 37111 | E4: 58310 | F4: =SUM(B4:D4)-E4 -> 975475
A5: =A4+1 -> 45995 | B5: 429043 | C5: 594720 | D5: 38093 | E5: 58667 | F5: =SUM(B5:D5)-E5 -> 1003189
A6: =A5+1 -> 45996 | B6: 415044 | C6: 620822 | D6: 42720 | E6: 76636 | F6: =SUM(B6:D6)-E6 -> 1001950
A7: =A6+1 -> 45997 | B7: 392108 | C7: 730638 | D7: 37997 | E7: 201348 | F7: =SUM(B7:D7)-E7 -> 959395
A8: =A7+1 -> 45998 | B8: 386877 | C8: 666009 | D8: 29905 | E8: 142800 | F8: =SUM(B8:D8)-E8 -> 939991
A9: =A8+1 -> 45999 | B9: 377486 | C9: 539229 | D9: 33688 | E9: 61642 | F9: =SUM(B9:D9)-E9 -> 888761
A10: =A9+1 -> 46000 | B10: 375948 | C10: 537566 | D10: 36206 | E10: 35244 | F10: =SUM(B10:D10)-E10 -> 914476
A11: =A10+1 -> 46001 | B11: 412152 | C11: 573724 | D11: 38367 | E11: 41174 | F11: =SUM(B11:D11)-E11 -> 983069
A12: =A11+1 -> 46002 | B12: 433954 | C12: 618264 | D12: 37008 | E12: 61523 | F12: =SUM(B12:D12)-E12 -> 1027703
A13: =A12+1 -> 46003 | B13: 408055 | C13: 612576 | D13: 39123 | E13: 83419 | F13: =SUM(B13:D13)-E13 -> 976335
A14: =A13+1 -> 46004 | B14: 389690 | C14: 804845 | D14: 31961 | E14: 299999 | F14: =SUM(B14:D14)-E14 -> 926497
... A32: =A31+1 -> 46022 | B32: 393628 | C32: 563544 | D32: 37879 | E32: 53669 | F32: =SUM(B32:D32)-E32 -> 941382
A33: 合计 | B33: =SUM(B2:B32) -> 12357597 | C33: =SUM(C2:C32) -> 19048238 | D33: =SUM(D2:D32) -> 1095866 | E33: =SUM(E2:E32) -> 3074623 | F33: =SUM(F2:F32) -> 29427078

Sheet 26年4月日经营数据
A1: 2026年南京项目处理经营情况（4月）
A3: 科目 | C3: 46113 | D3: 46114 | E3: 46115 | F3: 46116 | G3: 46117 | H3: 46118 | I3: 46119 | J3: 46120 | K3: 46121 | L3: 46122 | M3: 46123 | N3: 46124 | O3: 46125 | P3: 46126 | Q3: 46127 | R3: 46128 | S3: 46129 | T3: 46130 | U3: 46131 | V3: 46132 | W3: 46133 | X3: 46134 | Y3: 46135 | Z3: 46136 | AA3: 46137 | AB3: 46138 | AC3: 46139 | AD3: 46140 | AE3: 46141 | AF3: 46142 | AG3: 月度合计
C4: 进口处理 | D4: 进口处理 | E4: 进口处理 | F4: 进口处理 | G4: 进口处理 | H4: 进口处理 | I4: 进口处理 | J4: 进口处理 | K4: 进口处理 | L4: 进口处理 | M4: 进口处理 | N4: 进口处理 | O4: 进口处理 | P4: 进口处理 | Q4: 进口处理 | R4: 进口处理 | S4: 进口处理 | T4: 进口处理 | U4: 进口处理 | V4: 进口处理 | W4: 进口处理 | X4: 进口处理 | Y4: 进口处理 | Z4: 进口处理 | AA4: 进口处理 | AB4: 进口处理 | AC4: 进口处理 | AD4: 进口处理 | AE4: 进口处理 | AF4: 进口处理 | AG4: 进口处理
A5: 1 | B5: 散件处理量 | C5: ='26年4月处理量'!D3 -> 190399 | D5: ='26年4月处理量'!D4 -> 166604 | E5: ='26年4月处理量'!D5 -> 171010 | F5: ='26年4月处理量'!D6 -> 175028 | G5: ='26年4月处理量'!D7 -> 160677 | H5: ='26年4月处理量'!D8 -> 162166 | I5: ='26年4月处理量'!D9 -> 171401 | J5: ='26年4月处理量'!D10 -> 149607 | AG5: =SUM(C5:AF5) -> 1346892
A6: 2 | B6: 大件、总包经转量 | C6: ='26年4月处理量'!C3 -> 88239 | D6: ='26年4月处理量'!C4 -> 86437 | E6: ='26年4月处理量'!C5 -> 82874 | F6: ='26年4月处理量'!C6 -> 78969 | G6: ='26年4月处理量'!C7 -> 68918 | H6: ='26年4月处理量'!C8 -> 66287 | I6: ='26年4月处理量'!C9 -> 73270 | J6: ='26年4月处理量'!C10 -> 83645 | AG6: =SUM(C6:AF6) -> 628639
A7: 3 | B7: 散件处理单价 | C7: =0.0722*0.95 -> 0.06859 | D7: =0.0722*0.95 -> 0.06859 | E7: =0.0722*0.95 -> 0.06859 | F7: =0.0722*0.95 -> 0.06859 | G7: =0.0722*0.95 -> 0.06859 | H7: =0.0722*0.95 -> 0.06859 | I7: =0.0722*0.95 -> 0.06859 | J7: =0.0722*0.95 -> 0.06859 | AG7: =SUM(C7:AF7) -> 0.54872
A8: 4 | B8: 总包经传单价 | C8: =0.2911*0.95 -> 0.276545 | D8: =0.2911*0.95 -> 0.276545 | E8: =0.2911*0.95 -> 0.276545 | F8: =0.2911*0.95 -> 0.276545 | G8: =0.2911*0.95 -> 0.276545 | H8: =0.2911*0.95 -> 0.276545 | I8: =0.2911*0.95 -> 0.276545 | J8: =0.2911*0.95 -> 0.276545 | AG8: =SUM(C8:AF8) -> 2.21236
A9: 5 | B9: 散件处理收入 | C9: =ROUND(C5*C7,2) -> 13059.47 | D9: =ROUND(D5*D7,2) -> 11427.37 | E9: =ROUND(E5*E7,2) -> 11729.58 | F9: =ROUND(F5*F7,2) -> 12005.17 | G9: =ROUND(G5*G7,2) -> 11020.84 | H9: =ROUND(H5*H7,2) -> 11122.97 | I9: =ROUND(I5*I7,2) -> 11756.39 | J9: =ROUND(J5*J7,2) -> 10261.54 | AG9: =SUM(C9:AF9) -> 92383.33
A10: 6 | B10: 总包经传收入 | C10: =C6*C8 -> 24402.054 | D10: =D6*D8 -> 23903.72 | E10: =E6*E8 -> 22918.39 | F10: =F6*F8 -> 21838.482 | G10: =G6*G8 -> 19058.928 | H10: =H6*H8 -> 18331.338 | I10: =I6*I8 -> 20262.452 | J10: =J6*J8 -> 23131.607 | AG10: =SUM(C10:AF10) -> 173846.97
A11: 7 | B11: 考核扣款 | C11: 1500 | D11: 1500 | E11: 1500 | F11: 1500 | G11: 1500 | H11: 1500 | I11: 1500 | J11: 1500 | AG11: =SUM(C11:AF11) -> 12000
A12: 8 | B12: 补贴费用 | AG12: =SUM(C12:AF12) -> 0
A13: 9 | B13: 开票金额 | C13: =C9+C10-C11 -> 35961.524 | D13: =D9+D10-D11 -> 33831.09 | E13: =E9+E10-E11 -> 33147.97 | F13: =F9+F10-F11 -> 32343.652 | G13: =G9+G10-G11 -> 28579.768 | H13: =H9+H10-H11 -> 27954.308 | I13: =I9+I10-I11 -> 30518.842 | J13: =J9+J10-J11 -> 31893.147 | AG13: =SUM(C13:AF13) -> 254230.3
A14: 一、主营业务收入总计 | C14: =C13/1.06 -> 33925.966 | D14: =D13/1.06 -> 31916.123 | E14: =E13/1.06 -> 31271.67 | F14: =F13/1.06 -> 30512.879 | G14: =G13/1.06 -> 26962.046 | H14: =H13/1.06 -> 26371.989 | I14: =I13/1.06 -> 28791.361 | J14: =J13/1.06 -> 30087.874 | AG14: =SUM(C14:AF14) -> 239839.91
A15: 1 | B15: 管理人员数量 | C15: 11 | D15: 11 | E15: 11 | F15: 11 | G15: 10 | H15: 10 | I15: 11 | J15: 11 | AG15: =SUM(C15:AF15) -> 86
A16: 2 | B16: 自有员工数量 | C16: =47+13+43+17+6+3+5 -> 134 | D16: =47+11+44+22+8+2+5 -> 139 | E16: =46+11+41+19+6+4+5 -> 132 | F16: =38+12+36+14+3+7+5 -> 115 | G16: =40+11+36+17+6+4+5 -> 119 | H16: =41+11+40+14+6+3+6 -> 121 | I16: =45+10+45+12+4+5+6 -> 127 | J16: =45+8+46+10+5+4+5 -> 123 | AG16: =SUM(C16:AF16) -> 1010
A17: 3 | B17: 劳务人员数量 | C17: =28 -> 28 | D17: =18 -> 18 | E17: =26 -> 26 | F17: =4+34 -> 38 | G17: =3+28 -> 31 | H17: =26 -> 26 | I17: =26 -> 26 | J17: =25 -> 25 | AG17: =SUM(C17:AF17) -> 218
A18: 4 | B18: 总人数 | C18: =SUM(C15:C17) -> 173 | D18: =SUM(D15:D17) -> 168 | E18: =SUM(E15:E17) -> 169 | F18: =SUM(F15:F17) -> 164 | G18: =SUM(G15:G17) -> 160 | H18: =SUM(H15:H17) -> 157 | I18: =SUM(I15:I17) -> 164 | J18: =SUM(J15:J17) -> 159 | AG18: =SUM(C18:AF18) -> 1314
A19: 5 | B19: 总工时 | C19: =(65*11)+((64+28)*13)+(6*12.5)+(3*6) -> 2004 | D19: =(61*11)+((69+18)*13)+(8*12.5)+(2*6) -> 1914 | E19: =(62*11)+((63+26)*13)+(6*12.5)+(4*6) -> 1938 | F19: =((56+4)*11)+((53+34)*13)+(3*12.5)+(7*6) -> 1870.5 | G19: =((56+3)*11)+((60+28)*13)+(6*12.5)+(4*6) -> 1892 | H19: =(57*11)+((59+26)*13)+(6*12.5)+(3*6) -> 1825 | I19: =(57*11)+((59+26)*13)+(6*12.5)+(3*6) -> 1825 | J19: =(53*11)+((56+25)*13)+(5*12.5)+(4*6) -> 1722.5 | AG19: =SUM(C19:AF19) -> 14991
A20: 人均效能 | C20: =SUM(C5:C6)/C18 -> 1610.6243 | D20: =SUM(D5:D6)/D18 -> 1506.1964 | E20: =SUM(E5:E6)/E18 -> 1502.2722 | F20: =SUM(F5:F6)/F18 -> 1548.7622 | G20: =SUM(G5:G6)/G18 -> 1434.9688 | H20: =SUM(H5:H6)/H18 -> 1455.1146 | I20: =SUM(I5:I6)/I18 -> 1491.8963 | J20: =SUM(J5:J6)/J18 -> 1466.9937 | ... AF20: =SUM(AF5:AF6)/AF18 -> #DIV/0! | AG20: =SUM(C20:AF20) -> #DIV/0!
A21: 人均小时效能 | C21: =(C5+C6)/C19 -> 139.04092 | D21: =(D5+D6)/D19 -> 132.20533 | E21: =(E5+E6)/E19 -> 131.0031 | F21: =(F5+F6)/F19 -> 135.79096 | G21: =(G5+G6)/G19 -> 121.35042 | H21: =(H5+H6)/H19 -> 125.17973 | I21: =(I5+I6)/I19 -> 134.0663 | J21: =(J5+J6)/J19 -> 135.4148 | ... AF21: =(AF5+AF6)/AF19 -> #DIV/0! | AG21: =SUM(C21:AF21) -> #DIV/0!
A22: 变动成本 | B22: 自有员工工资 | C22: =(47*160)+(42*190)+6122+(4400/28*3)+(4900/28*2)+200 -> 22643.429 | D22: =(45*160)+(42*190)+7232.46+(4400/28*3)+(4900/28*2)+200 -> 23433.889 | E22: =(46*160)+(39*190)+6367+(4400/28*3)+(4900/28*2)+200 -> 22158.429 | F22: =(39*160)+(34*190)+5031+(4400/28*3)+(4900/28*2)+200 -> 18752.429 | G22: =(40*160)+(36*190)+6013+(4400/28*3)+(4900/28*2)+200 -> 20274.429 | H22: =(41*160)+(40*190)+5310+(4400/28*3)+(4900/28*2)+200 -> 20491.429 | I22: =(45*160)+(45*190)+4702+(4400/28*3)+(4900/28*2)+200 -> 21473.429 | J22: =(45*160)+(46*190)+4241+(4400/28*3)+(4900/28*2)+200 -> 21202.429 | AG22: =SUM(C22:AF22) -> 170429.89
B23: 劳务人员工资 | C23: =(28*18*13) -> 6552 | D23: =(18*18*13) -> 4212 | E23: =(26*18*13) -> 6084 | F23: =(4*18*11)+(34*18*13) -> 8748 | G23: =(3*18*11)+(28*18*13) -> 7146 | H23: =(26*18*13) -> 6084 | I23: =(24*18*13) -> 5616 | J23: =(24*18*13)+(18*6) -> 5724 | AG23: =SUM(C23:AF23) -> 50166
A24: 成本总计： | C24: =C22+C23 -> 29195.429 | D24: =D22+D23 -> 27645.889 | E24: =E22+E23 -> 28242.429 | F24: =F22+F23 -> 27500.429 | G24: =G22+G23 -> 27420.429 | H24: =H22+H23 -> 26575.429 | I24: =I22+I23 -> 27089.429 | J24: =J22+J23 -> 26926.429 | AG24: =SUM(C24:AF24) -> 220595.89
A25: 变动成本件均成本 | C25: =C24/(C5+C6) -> 0.10477906 | D25: =D24/(D5+D6) -> 0.10925458 | E25: =E24/(E5+E6) -> 0.11124147 | F25: =F24/(F5+F6) -> 0.10827068 | G25: =G24/(G5+G6) -> 0.11942955 | H25: =H24/(H5+H6) -> 0.11632777 | I25: =I24/(I5+I6) -> 0.11071777 | J25: =J24/(J5+J6) -> 0.11543922 | ... AF25: =AF24/(AF5+AF6) -> #DIV/0! | AG25: =SUM(C25:AF25) -> #DIV/0!
A26: 期间成本 | B26: 工单赔付 | C26: =20000/30 -> 666.66667 | D26: =20000/30 -> 666.66667 | E26: =20000/30 -> 666.66667 | F26: =20000/30 -> 666.66667 | G26: =20000/30 -> 666.66667 | H26: =20000/30 -> 666.66667 | I26: =20000/30 -> 666.66667 | J26: =20000/30 -> 666.66667 | AG26: =SUM(C26:AF26) -> 5333.3333
B27: 员工餐费 | C27: 0 | D27: 0 | E27: 0 | F27: 0 | G27: 0 | H27: 0 | I27: 0 | J27: 0 | AG27: =SUM(C27:AF27) -> 0
B28: 保洁费 | C28: 0 | D28: 0 | E28: 0 | F28: 0 | G28: 0 | H28: 0 | I28: 0 | J28: 0 | AG28: =SUM(C28:AF28) -> 0
B29: 意外险 | C29: =2*200 -> 400 | D29: =2*200 -> 400 | E29: =2*200 -> 400 | F29: =2*200 -> 400 | G29: =2*200 -> 400 | H29: =2*200 -> 400 | I29: =2*200 -> 400 | J29: =2*200 -> 400 | AG29: =SUM(C29:AF29) -> 3200
B30: 雇主险 | C30: =2.5*200 -> 500 | D30: =2.5*200 -> 500 | E30: =2.5*200 -> 500 | F30: =2.5*200 -> 500 | G30: =2.5*200 -> 500 | H30: =2.5*200 -> 500 | I30: =2.5*200 -> 500 | J30: =2.5*200 -> 500 | AG30: =SUM(C30:AF30) -> 4000
B31: 房租 | C31: 0 | D31: 0 | E31: 0 | F31: 0 | G31: 0 | H31: 0 | I31: 0 | J31: 0 | AG31: =SUM(C31:AF31) -> 0
B32: 水电费 | C32: 0 | D32: 0 | E32: 0 | F32: 0 | G32: 0 | H32: 0 | I32: 0 | J32: 0 | AG32: =SUM(C32:AF32) -> 0
B33: 员工宿舍费 | C33: 0 | D33: 0 | E33: 0 | F33: 0 | G33: 0 | H33: 0 | I33: 0 | J33: 0 | AG33: =SUM(C33:AF33) -> 0
B34: 福利费用 | C34: 0 | D34: 0 | E34: 0 | F34: 0 | G34: 0 | H34: 0 | I34: 0 | J34: 0 | AG34: =SUM(C34:AF34) -> 0
B35: 办公费 | C35: 0 | D35: 0 | E35: 0 | F35: 0 | G35: 0 | H35: 0 | I35: 0 | J35: 0 | AG35: =SUM(C35:AF35) -> 0
B36: 物料采购费 | C36: 0 | D36: 0 | E36: 0 | F36: 0 | G36: 0 | H36: 0 | I36: 0 | J36: 0 | AG36: =SUM(C36:AF36) -> 0
B37: 招聘费 | C37: 0 | D37: 0 | E37: 0 | F37: 0 | G37: 0 | H37: 0 | I37: 0 | J37: 0 | AG37: =SUM(C37:AF37) -> 0
B38: 设备维修费 | C38: 0 | D38: 0 | E38: 0 | F38: 0 | G38: 0 | H38: 0 | I38: 0 | J38: 0 | AG38: =SUM(C38:AF38) -> 0
B39: 差旅费 | C39: 0 | D39: 0 | E39: 0 | F39: 0 | G39: 0 | H39: 0 | I39: 0 | J39: 0 | AG39: =SUM(C39:AF39) -> 0
B40: 招标代理费 | C40: 0 | D40: 0 | E40: 0 | F40: 0 | G40: 0 | H40: 0 | I40: 0 | J40: 0 | AG40: =SUM(C40:AF40) -> 0
A41: 成本总计： | C41: =SUM(C26:C40) -> 1566.6667 | D41: =SUM(D26:D40) -> 1566.6667 | E41: =SUM(E26:E40) -> 1566.6667 | F41: =SUM(F26:F40) -> 1566.6667 | G41: =SUM(G26:G40) -> 1566.6667 | H41: =SUM(H26:H40) -> 1566.6667 | I41: =SUM(I26:I40) -> 1566.6667 | J41: =SUM(J26:J40) -> 1566.6667 | AG41: =SUM(C41:AF41) -> 12533.333
A42: 期间成本件均成本 | C42: =C41/(C5+C6) -> 0.005622588 | D42: =D41/(D5+D6) -> 0.006191355 | E42: =E41/(E5+E6) -> 0.0061707972 | F42: =F41/(F5+F6) -> 0.0061680519 | G42: =G41/(G5+G6) -> 0.0068236097 | H42: =H41/(H5+H6) -> 0.0068577198 | I42: =I41/(I5+I6) -> 0.0064031563 | J42: =J41/(J5+J6) -> 0.0067166269 | ... AF42: =AF41/(AF5+AF6) -> #DIV/0! | AG42: =SUM(C42:AF42) -> #DIV/0!
A43: 固定成本 | B43: 设备成本摊销 | C43: 0 | D43: 0 | E43: 0 | F43: 0 | G43: 0 | H43: 0 | I43: 0 | J43: 0 | K43: 0 | L43: 0 | M43: 0 | N43: 0 | O43: 0 | P43: 0 | Q43: 0 | R43: 0 | S43: 0 | T43: 0 | U43: 0 | V43: 0 | W43: 0 | X43: 0 | Y43: 0 | Z43: 0 | AA43: 0 | AB43: 0 | AC43: 0 | AD43: 0 | AE43: 0 | AF43: 0 | AG43: =SUM(C43:AF43) -> 0
B44: 场租 | C44: 0 | D44: 0 | E44: 0 | F44: 0 | G44: 0 | H44: 0 | I44: 0 | J44: 0 | K44: 0 | L44: 0 | M44: 0 | N44: 0 | O44: 0 | P44: 0 | Q44: 0 | R44: 0 | S44: 0 | T44: 0 | U44: 0 | V44: 0 | W44: 0 | X44: 0 | Y44: 0 | Z44: 0 | AA44: 0 | AB44: 0 | AC44: 0 | AD44: 0 | AE44: 0 | AF44: 0 | AG44: =SUM(C44:AF44) -> 0
A45: 成本总计： | C45: =SUM(C43:C44) -> 0 | D45: =SUM(D43:D44) -> 0 | E45: =SUM(E43:E44) -> 0 | F45: =SUM(F43:F44) -> 0 | G45: =SUM(G43:G44) -> 0 | H45: =SUM(H43:H44) -> 0 | I45: =SUM(I43:I44) -> 0 | J45: =SUM(J43:J44) -> 0 | ... AF45: =SUM(AF43:AF44) -> 0 | AG45: =SUM(C45:AF45) -> 0
A46: 固定成本件均成本 | C46: =C45/(C5+C6) -> 0 | D46: =D45/(D5+D6) -> 0 | E46: =E45/(E5+E6) -> 0 | F46: =F45/(F5+F6) -> 0 | G46: =G45/(G5+G6) -> 0 | H46: =H45/(H5+H6) -> 0 | I46: =I45/(I5+I6) -> 0 | J46: =J45/(J5+J6) -> 0 | ... AF46: =AF45/(AF5+AF6) -> #DIV/0! | AG46: =SUM(C46:AF46) -> #DIV/0!
A47: 二、主营业务成本总计 | C47: =C45+C41+C24 -> 30762.095 | D47: =D45+D41+D24 -> 29212.555 | E47: =E45+E41+E24 -> 29809.095 | F47: =F45+F41+F24 -> 29067.095 | G47: =G45+G41+G24 -> 28987.095 | H47: =H45+H41+H24 -> 28142.095 | I47: =I45+I41+I24 -> 28656.095 | J47: =J45+J41+J24 -> 28493.095 | ... AF47: =AF45+AF41+AF24 -> 0 | AG47: =SUM(C47:AF47) -> 233129.22
A48: 主营业务税金及附加 | C48: =ROUND(C14*6%*12%,2) -> 244.27 | D48: =ROUND(D14*6%*12%,2) -> 229.8 | E48: =ROUND(E14*6%*12%,2) -> 225.16 | F48: =ROUND(F14*6%*12%,2) -> 219.69 | G48: =ROUND(G14*6%*12%,2) -> 194.13 | H48: =ROUND(H14*6%*12%,2) -> 189.88 | I48: =ROUND(I14*6%*12%,2) -> 207.3 | J48: =ROUND(J14*6%*12%,2) -> 216.63 | ... AF48: =ROUND(AF14*6%*12%,2) -> 0 | AG48: =SUM(C48:AF48) -> 1726.86
A49: 三、主营业务利润（亏损以“-”号填列) | C49: =C14-C47-C48 -> 2919.601 | D49: =D14-D47-D48 -> 2473.7676 | E49: =E14-E47-E48 -> 1237.4149 | F49: =F14-F47-F48 -> 1226.0941 | G49: =G14-G47-G48 -> -2219.1797 | H49: =H14-H47-H48 -> -1959.9862 | I49: =I14-I47-I48 -> -72.034719 | J49: =J14-J47-J48 -> 1378.1488 | ... AF49: =AF14-AF47-AF48 -> 0 | AG49: =SUM(C49:AF49) -> 4983.8259
A50: 管理成本 | B50: 管理人员工资 | C50: =(110000+16600+24900)/30 -> 5050 | D50: =(110000+16600+24900)/30 -> 5050 | E50: =(110000+16600+24900)/30 -> 5050 | F50: =(110000+16600+24900)/30 -> 5050 | G50: =(110000+16600+24900)/30 -> 5050 | H50: =(110000+16600+24900)/30 -> 5050 | I50: =(110000+16600+24900)/30 -> 5050 | J50: =(110000+16600+24900)/30 -> 5050 | AG50: =SUM(C50:AF50) -> 40400
B51: 人事工资 | C51: 0 | D51: 0 | E51: 0 | F51: 0 | G51: 0 | H51: 0 | I51: 0 | J51: 0 | AG51: =SUM(C51:AF51) -> 0
B52: 社会保险费 | C52: =(14*1130)/30 -> 527.33333 | D52: =(14*1130)/30 -> 527.33333 | E52: =(14*1130)/30 -> 527.33333 | F52: =(14*1130)/30 -> 527.33333 | G52: =(14*1130)/30 -> 527.33333 | H52: =(14*1130)/30 -> 527.33333 | I52: =(14*1130)/30 -> 527.33333 | J52: =(14*1130)/30 -> 527.33333 | AG52: =SUM(C52:AF52) -> 4218.6667
B53: 客服 | C53: =(4200/30*2) -> 280 | D53: =(4200/30*2) -> 280 | E53: =(4200/30*2) -> 280 | F53: =(4200/30*2) -> 280 | G53: =(4200/30*2) -> 280 | H53: =(4200/30*2) -> 280 | I53: =(4200/30*2) -> 280 | J53: =(4200/30*2) -> 280 | AG53: =SUM(C53:AF53) -> 2240
A54: 成本总计： | C54: =SUM(C50:C53) -> 5857.3333 | D54: =SUM(D50:D53) -> 5857.3333 | E54: =SUM(E50:E53) -> 5857.3333 | F54: =SUM(F50:F53) -> 5857.3333 | G54: =SUM(G50:G53) -> 5857.3333 | H54: =SUM(H50:H53) -> 5857.3333 | I54: =SUM(I50:I53) -> 5857.3333 | J54: =SUM(J50:J53) -> 5857.3333 | AG54: =SUM(C54:AF54) -> 46858.667
A55: 管理成本件均成本 | C55: =C54/(C5+C6) -> 0.021021301 | D55: =D54/(D5+D6) -> 0.023147764 | E55: =E54/(E5+E6) -> 0.023070904 | F55: =F54/(F5+F6) -> 0.02306064 | G55: =G54/(G5+G6) -> 0.025511589 | H55: =H54/(H5+H6) -> 0.025639118 | I55: =I54/(I5+I6) -> 0.02393963 | J55: =J54/(J5+J6) -> 0.02511161 | ... AF55: =AF54/(AF5+AF6) -> #DIV/0! | AG55: =SUM(C55:AF55) -> #DIV/0!
A56: 三、总费用合计 | C56: =C54+C47+C48 -> 36863.699 | D56: =D54+D47+D48 -> 35299.689 | E56: =E54+E47+E48 -> 35891.589 | F56: =F54+F47+F48 -> 35144.119 | G56: =G54+G47+G48 -> 35038.559 | H56: =H54+H47+H48 -> 34189.309 | I56: =I54+I47+I48 -> 34720.729 | J56: =J54+J47+J48 -> 34567.059 | ... AF56: =AF54+AF47+AF48 -> 0 | AG56: =SUM(C56:AF56) -> 281714.75
A57: 总费用件均成本： | C57: =C56/(C5+C6) -> 0.13229961 | D57: =D56/(D5+D6) -> 0.13950185 | E57: =E56/(E5+E6) -> 0.14137003 | F57: =F56/(F5+F6) -> 0.13836431 | G57: =G56/(G5+G6) -> 0.15261029 | H57: =H56/(H5+H6) -> 0.14965577 | I57: =I56/(I5+I6) -> 0.14190782 | J57: =J56/(J5+J6) -> 0.14819619 | ... AF57: =AF56/(AF5+AF6) -> #DIV/0! | AG57: =SUM(C57:AF57) -> #DIV/0!
A58: 四、利润总额（亏损总额以“-”号填列） | C58: =ROUND(C14-C56,2) -> -2937.73 | D58: =ROUND(D14-D56,2) -> -3383.57 | E58: =ROUND(E14-E56,2) -> -4619.92 | F58: =ROUND(F14-F56,2) -> -4631.24 | G58: =ROUND(G14-G56,2) -> -8076.51 | H58: =ROUND(H14-H56,2) -> -7817.32 | I58: =ROUND(I14-I56,2) -> -5929.37 | J58: =ROUND(J14-J56,2) -> -4479.18 | ... AF58: =ROUND(AF14-AF56,2) -> 0 | AG58: =SUM(C58:AF58) -> -41874.84
A59: 五、亏损分析 | C59: 招聘费、补偿金、管理成本（网格长离职1人“包景强”）已剔除。 | D59: 处理量减少 | E59: 散件减少，劳务人员增加 | G59: 处理量减少
A60: 注：请注意业务量跳档时单价的变化

Sheet 26年4月处理量
B1: 淄博中心业务量统计表
B2: 日期 | C2: 大件外走量 | D2: 小件封发量 | E2: 文件量 | F2: 合计 | G2: 纯散件量
B3: 46113 | C3: 88239 | D3: 190399 | F3: =C3+D3 -> 278638
B4: 46114 | C4: 86437 | D4: 166604 | F4: =C4+D4 -> 253041
B5: 46115 | C5: 82874 | D5: 171010 | F5: =C5+D5 -> 253884
B6: 46116 | C6: 78969 | D6: 175028 | F6: =C6+D6 -> 253997
B7: 46117 | C7: 68918 | D7: 160677 | F7: =C7+D7 -> 229595
B8: 46118 | C8: 66287 | D8: 162166 | F8: =C8+D8 -> 228453
B9: 46119 | C9: 73270 | D9: 171401 | F9: =C9+D9 -> 244671
B10: 46120 | C10: 83645 | D10: 149607 | F10: =C10+D10 -> 233252
B11: 46121 | F11: =C11+D11 -> 0
B12: 46122 | F12: =C12+D12 -> 0
B13: 46123 | F13: =C13+D13 -> 0
B14: 46124 | F14: =C14+D14 -> 0
B15: 46125 | F15: =C15+D15 -> 0
B16: 46126 | F16: =C16+D16 -> 0
B17: 46127 | F17: =C17+D17 -> 0
B18: 46128 | F18: =C18+D18 -> 0
B19: 46129 | F19: =C19+D19 -> 0
B20: 46130 | F20: =C20+D20 -> 0
B21: 46131 | F21: =C21+D21 -> 0
B22: 46132 | F22: =C22+D22 -> 0
... B27: 46137 | F27: =C27+D27 -> 0
B28: 46138 | F28: =C28+D28+E28 -> 0
B29: 46139 | F29: =C29+D29+E29 -> 0
B30: 46140 | F30: =C30+D30+E30 -> 0
B31: 46141 | F31: =C31+D31 -> 0
B32: 46142 | F32: =C32+D32 -> 0
